Workbook

Sheet DATA_ADN
A1: id_multitabla | B1: codigo_tabla | C1: nombre_tabla | D1: codigo | E1: orden | F1: valor | G1: valor_aux | H1: valor_crm | I1: valor_flex | J1: estado | K1: estado_tabla | L1: usuario_crea | M1: fecha_crea | N1: usuario_modif | O1: fecha_modif
A2: 455 | B2: 001 | C2: Tipo de Documento Identidad | D2: NULL | E2: NULL | F2: NULL | G2: NULL | H2: NULL | I2: NULL | J2: NULL | K2: 1 | L2: admin | M2: 43606.789 | N2: NULL | O2: NULL
A3: 456 | B3: 001 | C3: Tipo de Documento Identidad | D3: 1 | E3: 1 | F3: DNI | G3: NULL | H3: 538560000 | I3: D | J3: 1 | K3: 1 | L3: admin | M3: 43606.789 | N3: NULL | O3: NULL
A4: 457 | B4: 001 | C4: Tipo de Documento Identidad | D4: 2 | E4: 2 | F4: Carnet ExtranjerÃ­a | G4: NULL | H4: 538560001 | I4: E | J4: 1 | K4: 1 | L4: admin | M4: 43606.789 | N4: NULL | O4: NULL
A5: 458 | B5: 001 | C5: Tipo de Documento Identidad | D5: 3 | E5: 3 | F5: Carnet Identidad Policial | G5: NULL | H5: 538560002 | I5: I | J5: 2 | K5: 1 | L5: admin | M5: 43606.789 | N5: NULL | O5: NULL
A6: 459 | B6: 001 | C6: Tipo de Documento Identidad | D6: 4 | E6: 4 | F6: Carnet de AutorizaciÃ³n | G6: NULL | H6: 538560003 | I6: M | J6: 2 | K6: 1 | L6: admin | M6: 43606.789 | N6: NULL | O6: NULL
A7: 460 | B7: 001 | C7: Tipo de Documento Identidad | D7: 5 | E7: 5 | F7: Pasaporte | G7: NULL | H7: 538560004 | I7: P | J7: 2 | K7: 1 | L7: admin | M7: 43606.789 | N7: NULL | O7: NULL
A8: 461 | B8: 001 | C8: Tipo de Documento Identidad | D8: 6 | E8: 6 | F8: Licencia de Conducir | G8: NULL | H8: 538560005 | I8: K | J8: 2 | K8: 1 | L8: admin | M8: 43606.789 | N8: NULL | O8: NULL
A9: 462 | B9: 001 | C9: Tipo de Documento Identidad | D9: 7 | E9: 7 | F9: Libreta Electoral | G9: NULL | H9: 538560006 | I9: L | J9: 2 | K9: 1 | L9: admin | M9: 43606.789 | N9: NULL | O9: NULL
A10: 463 | B10: 001 | C10: Tipo de Documento Identidad | D10: 8 | E10: 8 | F10: Partida Nacimiento | G10: NULL | H10: 538560007 | I10: N | J10: 2 | K10: 1 | L10: admin | M10: 43606.789 | N10: NULL | O10: NULL
A11: 464 | B11: 001 | C11: Tipo de Documento Identidad | D11: 9 | E11: 9 | F11: Otro Documento | G11: NULL | H11: 538560008 | J11: 2 | K11: 1 | L11: admin | M11: 43606.789 | N11: NULL | O11: NULL
A12: 465 | B12: 001 | C12: Tipo de Documento Identidad | D12: 10 | E12: 10 | F12: RUC Persona Natural | G12: NULL | H12: 538560009 | I12: R | J12: 2 | K12: 1 | L12: admin | M12: 43606.789 | N12: NULL | O12: NULL
A13: 466 | B13: 001 | C13: Tipo de Documento Identidad | D13: 11 | E13: 11 | F13: RUC Persona JurÃ­dica | G13: NULL | H13: 538560011 | I13: J | J13: 2 | K13: 1 | L13: admin | M13: 43606.789 | N13: NULL | O13: NULL
A14: 467 | B14: 001 | C14: Tipo de Documento Identidad | D14: 12 | E14: 12 | F14: Sin Documento | G14: NULL | H14: 538560010 | I14: S | J14: 2 | K14: 1 | L14: admin | M14: 43606.789 | N14: NULL | O14: NULL
A15: 468 | B15: 002 | C15: GÃ©nero | D15: NULL | E15: NULL | F15: NULL | G15: NULL | H15: NULL | I15: NULL | J15: NULL | K15: 1 | L15: admin | M15: 43606.789 | N15: NULL | O15: NULL
A16: 469 | B16: 002 | C16: GÃ©nero | D16: 1 | E16: 1 | F16: Masculino | G16: NULL | H16: 538560000 | I16: M | J16: 1 | K16: 1 | L16: admin | M16: 43606.789 | N16: NULL | O16: NULL
A17: 470 | B17: 002 | C17: GÃ©nero | D17: 2 | E17: 2 | F17: Femenino | G17: NULL | H17: 538560001 | I17: F | J17: 1 | K17: 1 | L17: admin | M17: 43606.789 | N17: NULL | O17: NULL
A18: 471 | B18: 002 | C18: GÃ©nero | D18: 3 | E18: 3 | F18: Desconocido | G18: NULL | H18: 538560002 | I18: NULL | J18: 2 | K18: 1 | L18: admin | M18: 43606.789 | N18: NULL | O18: NULL
A19: 472 | B19: 003 | C19: ProfesiÃ³n | D19: NULL | E19: NULL | F19: NULL | G19: NULL | H19: NULL | I19: NULL | J19: NULL | K19: 1 | L19: admin | M19: 43606.789 | N19: NULL | O19: NULL
A20: 473 | B20: 003 | C20: ProfesiÃ³n | D20: 1 | E20: 1 | F20: Abogados (no penalistas) | G20: NULL | H20: 1 | I20: NULL | J20: 1 | K20: 1 | L20: admin | M20: 43606.789 | N20: NULL | O20: NULL
A21: 474 | B21: 003 | C21: ProfesiÃ³n | D21: 2 | E21: 2 | F21: Actuarios | G21: NULL | H21: 2 | I21: NULL | J21: 1 | K21: 1 | L21: admin | M21: 43606.789 | N21: NULL | O21: NULL
A22: 475 | B22: 003 | C22: ProfesiÃ³n | D22: 3 | E22: 3 | F22: Administrador | G22: NULL | H22: 3 | I22: NULL | J22: 1 | K22: 1 | L22: admin | M22: 43606.789 | N22: NULL | O22: NULL
A23: 476 | B23: 003 | C23: ProfesiÃ³n | D23: 4 | E23: 4 | F23: Ala Delta | G23: NULL | H23: 4 | I23: NULL | J23: 1 | K23: 1 | L23: admin | M23: 43606.789 | N23: NULL | O23: NULL
A24: 477 | B24: 003 | C24: ProfesiÃ³n | D24: 5 | E24: 5 | F24: AlbaÃ±iles | G24: NULL | H24: 5 | I24: NULL | J24: 1 | K24: 1 | L24: admin | M24: 43606.789 | N24: NULL | O24: NULL
A25: 478 | B25: 003 | C25: ProfesiÃ³n | D25: 6 | E25: 6 | F25: Arquitecto (obra) | G25: NULL | H25: 6 | I25: NULL | J25: 1 | K25: 1 | L25: admin | M25: 43606.789 | N25: NULL | O25: NULL
A26: 479 | B26: 003 | C26: ProfesiÃ³n | D26: 7 | E26: 7 | F26: Arquitecto (sin ingreso a obra) | G26: NULL | H26: 7 | I26: NULL | J26: 1 | K26: 1 | L26: admin | M26: 43606.789 | N26: NULL | O26: NULL
A27: 480 | B27: 003 | C27: ProfesiÃ³n | D27: 8 | E27: 8 | F27: Artista PlÃ¡stico | G27: NULL | H27: 8 | I27: NULL | J27: 1 | K27: 1 | L27: admin | M27: 43606.789 | N27: NULL | O27: NULL
A28: 481 | B28: 003 | C28: ProfesiÃ³n | D28: 9 | E28: 9 | F28: Asesores | G28: NULL | H28: 9 | I28: NULL | J28: 1 | K28: 1 | L28: admin | M28: 43606.789 | N28: NULL | O28: NULL
A29: 482 | B29: 003 | C29: ProfesiÃ³n | D29: 10 | E29: 10 | F29: Auxiliares Administrativos | G29: NULL | H29: 10 | I29: NULL | J29: 1 | K29: 1 | L29: admin | M29: 43606.789 | N29: NULL | O29: NULL
A30: 483 | B30: 003 | C30: ProfesiÃ³n | D30: 11 | E30: 11 | F30: Bibliotecarios | G30: NULL | H30: 11 | I30: NULL | J30: 1 | K30: 1 | L30: admin | M30: 43606.789 | N30: NULL | O30: NULL
A31: 484 | B31: 003 | C31: ProfesiÃ³n | D31: 12 | E31: 12 | F31: BiÃ³logo | G31: NULL | H31: 12 | I31: NULL | J31: 1 | K31: 1 | L31: admin | M31: 43606.789 | N31: NULL | O31: NULL
... A131: 584 | B131: 003 | C131: ProfesiÃ³n | D131: 112 | E131: 112 | F131: Vigilante sin Uso de Arma | G131: NULL | H131: 112 | I131: NULL | J131: 1 | K131: 1 | L131: admin | M131: 43606.789 | N131: NULL | O131: NULL
A132: 585 | B132: 004 | C132: Actividad EconÃ³mica | D132: NULL | E132: NULL | F132: NULL | G132: NULL | H132: NULL | I132: NULL | J132: NULL | K132: 1 | L132: admin | M132: 43606.789 | N132: NULL | O132: NULL
A133: 586 | B133: 004 | C133: Actividad EconÃ³mica | D133: 1 | E133: 1 | F133: Acabado de productos textiles | G133: NULL | H133: 1712 | I133: NULL | J133: 1 | K133: 1 | L133: admin | M133: 43606.789 | N133: NULL | O133: NULL
A134: 587 | B134: 004 | C134: Actividad EconÃ³mica | D134: 2 | E134: 2 | F134: Acondicionamiento de edificios | G134: NULL | H134: 4530 | I134: NULL | J134: 1 | K134: 1 | L134: admin | M134: 43606.789 | N134: NULL | O134: NULL
A135: 588 | B135: 004 | C135: Actividad EconÃ³mica | D135: 3 | E135: 3 | F135: Actividades auxiliares de la financiaciÃ³n de planes de seguros y de pensiones | G135: NULL | H135: 6720 | I135: NULL | J135: 1 | K135: 1 | L135: admin | M135: 43606.789 | N135: NULL | O135: NULL
A136: 589 | B136: 004 | C136: Actividad EconÃ³mica | D136: 4 | E136: 4 | F136: Actividades auxiliares de la intermediaciÃ³n financiera n.c.p. | G136: NULL | H136: 6719 | I136: NULL | J136: 1 | K136: 1 | L136: admin | M136: 43606.789 | N136: NULL | O136: NULL
A137: 590 | B137: 004 | C137: Actividad EconÃ³mica | D137: 5 | E137: 5 | F137: Actividades bursÃ¡tiles | G137: NULL | H137: 6712 | I137: NULL | J137: 1 | K137: 1 | L137: admin | M137: 43606.789 | N137: NULL | O137: NULL
A138: 591 | B138: 004 | C138: Actividad EconÃ³mica | D138: 6 | E138: 6 | F138: Actividades de agencias de noticias | G138: NULL | H138: 9220 | I138: NULL | J138: 1 | K138: 1 | L138: admin | M138: 43606.789 | N138: NULL | O138: NULL
A139: 592 | B139: 004 | C139: Actividad EconÃ³mica | D139: 7 | E139: 7 | F139: Actividades de agencias de viajes y organizadores de viajes; actividades de asistencÃ­a a turistas n.c.p. | G139: NULL | H139: 6304 | I139: NULL | J139: 1 | K139: 1 | L139: admin | M139: 43606.789 | N139: NULL | O139: NULL
A140: 593 | B140: 004 | C140: Actividad EconÃ³mica | D140: 8 | E140: 8 | F140: Actividades de arquitectura e ingenierÃ­a y actividades conexas de asesoramiento tÃ©cnico | G140: NULL | H140: 7421 | I140: NULL | J140: 1 | K140: 1 | L140: admin | M140: 43606.789 | N140: NULL | O140: NULL
A141: 594 | B141: 004 | C141: Actividad EconÃ³mica | D141: 9 | E141: 9 | F141: Actividades de asesoramiento empresarial y en materÃ­a de gestiÃ³n | G141: NULL | H141: 7414 | I141: NULL | J141: 1 | K141: 1 | L141: admin | M141: 43606.789 | N141: NULL | O141: NULL
A142: 595 | B142: 004 | C142: Actividad EconÃ³mica | D142: 10 | E142: 10 | F142: Actividades de bibliotecas y archivos | G142: NULL | H142: 9231 | I142: NULL | J142: 1 | K142: 1 | L142: admin | M142: 43606.789 | N142: NULL | O142: NULL
A143: 596 | B143: 004 | C143: Actividad EconÃ³mica | D143: 11 | E143: 11 | F143: Actividades de contabilidad, tenedurÃ­a de libros y auditorÃ­a; asesoramiento en materÃ­a de impuestos | G143: NULL | H143: 7412 | I143: NULL | J143: 1 | K143: 1 | L143: admin | M143: 43606.789 | N143: NULL | O143: NULL
A144: 597 | B144: 004 | C144: Actividad EconÃ³mica | D144: 12 | E144: 12 | F144: Actividades de correo distintas de las actividades postales nacionales | G144: NULL | H144: 6412 | I144: NULL | J144: 1 | K144: 1 | L144: admin | M144: 43606.789 | N144: NULL | O144: NULL
... A425: 878 | B425: 004 | C425: Actividad EconÃ³mica | D425: 293 | E425: 293 | F425: Venta de vehiculos automotores | G425: NULL | H425: 5010 | I425: NULL | J425: 1 | K425: 1 | L425: admin | M425: 43606.79 | N425: NULL | O425: NULL
A426: 879 | B426: 005 | C426: Fumador | D426: NULL | E426: NULL | F426: NULL | G426: NULL | H426: NULL | I426: NULL | J426: NULL | K426: 1 | L426: admin | M426: 43606.79 | N426: NULL | O426: NULL
A427: 880 | B427: 005 | C427: Fumador | D427: 1 | E427: 1 | F427: Si | G427: NULL | H427: 538560000 | I427: 10 | J427: 1 | K427: 1 | L427: admin | M427: 43606.79 | N427: NULL | O427: NULL
A428: 881 | B428: 005 | C428: Fumador | D428: 2 | E428: 2 | F428: No | G428: NULL | H428: 538560001 | I428: - | J428: 1 | K428: 1 | L428: admin | M428: 43606.79 | N428: NULL | O428: NULL
A429: 882 | B429: 006 | C429: Tipo RelaciÃ³n | D429: NULL | E429: NULL | F429: NULL | G429: NULL | H429: NULL | I429: NULL | J429: NULL | K429: 1 | L429: admin | M429: 43606.79 | N429: NULL | O429: NULL
A430: 883 | B430: 006 | C430: Tipo RelaciÃ³n | D430: 1 | E430: 1 | F430: Afiliado | G430: NULL | H430: 538560017 | I430: NULL | J430: 0 | K430: 1 | L430: admin | M430: 43606.79 | N430: NULL | O430: NULL
A431: 884 | B431: 006 | C431: Tipo RelaciÃ³n | D431: 2 | E431: 2 | F431: Ahijado del asegurado | G431: NULL | H431: 538560014 | I431: NULL | J431: 0 | K431: 1 | L431: admin | M431: 43606.79 | N431: NULL | O431: NULL
A432: 885 | B432: 006 | C432: Tipo RelaciÃ³n | D432: 3 | E432: 3 | F432: Concubino | G432: NULL | H432: 538560018 | I432: NULL | J432: 0 | K432: 1 | L432: admin | M432: 43606.79 | N432: NULL | O432: NULL
A433: 886 | B433: 006 | C433: Tipo RelaciÃ³n | D433: 4 | E433: 4 | F433: Contratante | G433: NULL | H433: 538560013 | I433: NULL | J433: 0 | K433: 1 | L433: admin | M433: 43606.79 | N433: NULL | O433: NULL
A434: 887 | B434: 006 | C434: Tipo RelaciÃ³n | D434: 5 | E434: 5 | F434: Conviviente del asegurado | G434: NULL | H434: 538560008 | I434: NULL | J434: 1 | K434: 1 | L434: admin | M434: 43606.79 | N434: NULL | O434: NULL
A435: 888 | B435: 006 | C435: Tipo RelaciÃ³n | D435: 6 | E435: 6 | F435: CÃ³nyuge del asegurado | G435: NULL | H435: 538560004 | I435: NULL | J435: 1 | K435: 1 | L435: admin | M435: 43606.79 | N435: NULL | O435: NULL
A436: 889 | B436: 006 | C436: Tipo RelaciÃ³n | D436: 7 | E436: 7 | F436: Empleador | G436: NULL | H436: 538560001 | I436: NULL | J436: 0 | K436: 1 | L436: admin | M436: 43606.79 | N436: NULL | O436: NULL
A437: 890 | B437: 006 | C437: Tipo RelaciÃ³n | D437: 8 | E437: 8 | F437: Hermano del asegurado | G437: NULL | H437: 538560007 | I437: NULL | J437: 1 | K437: 1 | L437: admin | M437: 43606.79 | N437: NULL | O437: NULL
A438: 891 | B438: 006 | C438: Tipo RelaciÃ³n | D438: 9 | E438: 9 | F438: Hijastro/a del asegurado | G438: NULL | H438: 538560010 | I438: NULL | J438: 0 | K438: 1 | L438: admin | M438: 43606.79 | N438: NULL | O438: NULL
A439: 892 | B439: 006 | C439: Tipo RelaciÃ³n | D439: 10 | E439: 10 | F439: Hijo adoptivos del asegurado | G439: NULL | H439: 538560009 | I439: NULL | J439: 0 | K439: 1 | L439: admin | M439: 43606.79 | N439: NULL | O439: NULL
A440: 893 | B440: 006 | C440: Tipo RelaciÃ³n | D440: 11 | E440: 11 | F440: Hijo del asegurable | G440: NULL | H440: 538560002 | I440: NULL | J440: 1 | K440: 1 | L440: admin | M440: 43606.79 | N440: NULL | O440: NULL
A441: 894 | B441: 006 | C441: Tipo RelaciÃ³n | D441: 12 | E441: 12 | F441: Madre del asegurado | G441: NULL | H441: 538560005 | I441: NULL | J441: 1 | K441: 1 | L441: admin | M441: 43606.79 | N441: NULL | O441: NULL
... A445: 898 | B445: 006 | C445: Tipo RelaciÃ³n | D445: 16 | E445: 16 | F445: Sobrino del asegurado | G445: NULL | H445: 538560016 | I445: NULL | J445: 0 | K445: 1 | L445: admin | M445: 43606.79 | N445: NULL | O445: NULL
A446: 899 | B446: 007 | C446: Estado General | D446: NULL | E446: NULL | F446: NULL | G446: NULL | H446: NULL | I446: NULL | J446: NULL | K446: 1 | L446: admin | M446: 43606.79 | N446: NULL | O446: NULL
A447: 900 | B447: 007 | C447: Estado General | D447: 1 | E447: 1 | F447: Activo | G447: NULL | H447: NULL | I447: NULL | J447: 1 | K447: 1 | L447: admin | M447: 43606.79 | N447: NULL | O447: NULL
A448: 901 | B448: 007 | C448: Estado General | D448: 2 | E448: 2 | F448: Inactivo | G448: NULL | H448: NULL | I448: NULL | J448: 1 | K448: 1 | L448: admin | M448: 43606.79 | N448: NULL | O448: NULL
A449: 911 | B449: 008 | C449: ParÃ¡metros ADN | D449: NULL | E449: NULL | F449: NULL | G449: NULL | H449: NULL | I449: NULL | J449: NULL | K449: 1 | L449: admin | M449: 43606.871 | N449: NULL | O449: NULL
A450: 912 | B450: 008 | C450: ParÃ¡metros ADN | D450: 1 | E450: 1 | F450: porcentaje_ing_ini | G450: 5 | H450: NULL | I450: NULL | J450: 1 | K450: 1 | L450: admin | M450: 43606.871 | N450: NULL | O450: NULL
A451: 913 | B451: 008 | C451: ParÃ¡metros ADN | D451: 2 | E451: 2 | F451: porcentaje_ing_fin | G451: 10 | H451: NULL | I451: NULL | J451: 1 | K451: 1 | L451: admin | M451: 43606.871 | N451: NULL | O451: NULL
A452: 914 | B452: 008 | C452: ParÃ¡metros ADN | D452: 3 | E452: 3 | F452: seguro_vida_ley_regla | G452: 16 | H452: NULL | I452: NULL | J452: 1 | K452: 1 | L452: admin | M452: 43606.871 | N452: NULL | O452: NULL
A453: 915 | B453: 008 | C453: ParÃ¡metros ADN | D453: 4 | E453: 4 | F453: autoguardado_tiempo | G453: 15 | H453: NULL | I453: NULL | J453: 1 | K453: 1 | L453: admin | M453: 43606.871 | N453: NULL | O453: NULL
A454: 916 | B454: 008 | C454: ParÃ¡metros ADN | D454: 5 | E454: 5 | F454: porcentaje_ing_default | G454: 5 | H454: NULL | I454: NULL | J454: 1 | K454: 1 | L454: admin | M454: 43606.871 | N454: NULL | O454: NULL
A455: 917 | B455: 008 | C455: ParÃ¡metros ADN | D455: 6 | E455: 6 | F455: url_pdf_evidencias | G455: https://wwwp.interseguro.pe/siv-web/files/Manual_de_Evidencias_Vida_Individual.pdf | H455: NULL | I455: NULL | J455: 1 | K455: 1 | L455: admin | M455: 43606.871 | N455: NULL | O455: NULL
A456: 918 | B456: 008 | C456: ParÃ¡metros ADN | D456: 7 | E456: 7 | F456: url_pdf_educacion | G456: https://wwwp.interseguro.pe/siv-web/files/Prod_EducGarantizada.pdf | H456: NULL | I456: NULL | J456: 1 | K456: 1 | L456: admin | M456: 43606.871 | N456: NULL | O456: NULL
A457: 919 | B457: 008 | C457: ParÃ¡metros ADN | D457: 8 | E457: 8 | F457: url_pdf_proyectos | G457: https://wwwp.interseguro.pe/siv-web/files/Prod_SuenioGarantizado.pdf | H457: NULL | I457: NULL | J457: 1 | K457: 1 | L457: admin | M457: 43606.871 | N457: NULL | O457: NULL
A458: 920 | B458: 008 | C458: ParÃ¡metros ADN | D458: 9 | E458: 9 | F458: url_pdf_jubilacion | G458: https://wwwp.interseguro.pe/siv-web/files/Prod_JubilacGarantizada.pdf | H458: NULL | I458: NULL | J458: 1 | K458: 1 | L458: admin | M458: 43606.871 | N458: NULL | O458: NULL

Sheet DATA_SOLICITUD
A1: @id_multitabla | B1: @codigo_tabla | C1: @nombre_tabla | D1: @codigo | E1: @orden | F1: @valor@ | G1: @valor_aux | H1: @valor_crm | I1: @valor_flex | J1: @estado@ | K1: @estado_tabla | L1: @usuario_crea | M1: @fecha_crea | N1: @usuario_modif | O1: @fecha_modif | P1: INSERT
A2: DEFAULT | B2: 010 | C2: Nacionalidad | D2: NULL | E2: NULL | F2: NULL | G2: NULL | H2: NULL | I2: NULL | J2: NULL | K2: 1 | L2: admin | M2: DEFAULT | N2: NULL | O2: NULL | P2: =SUBSTITUTE(SUBSTITUTE(SUBSTITUTE(SUBSTITUTE(SUBSTITUTE(SUBSTITUTE(SUBSTITUTE(SUBSTITUTE(SUBSTITUTE(SUBSTITUTE(SUBSTITUTE(INSERT!$B$3,DATA_SOLICITUD!$B$1,IF(B2="NULL",B2,CONCATENATE("'",B2,"'"))),DATA_SOLICITUD!$C$1,IF(C2="NULL",C2,CONCATENATE("'",C2,"'"))),DATA_SOLICITUD!$D$1,IF(D2="NULL",D2,CONCATENATE("'",D2,"'"))),DATA_SOLICITUD!$E$1,IF(E2="NULL",E2,CONCATENATE("'",E2,"'"))),DATA_SOLICITUD!$F$1,IF(F2="NULL",F2,CONCATENATE("'",F2,"'"))),DATA_SOLICITUD!$G$1,IF(G2="NULL",G2,CONCATENATE("'",G2,"'"))),DATA_SOLICITUD!$H$1,IF(H2="NULL",H2,CONCATENATE("'",H2,"'"))),DATA_SOLICITUD!$I$1,IF(I2="NULL",I2,CONCATENATE("'",I2,"'"))),DATA_SOLICITUD!$J$1,IF(J2="NULL",J2,CONCATENATE("'",J2,"'"))),DATA_SOLICITUD!$K$1,IF(K2="NULL",K2,CONCATENATE("'",K2,"'"))),DATA_SOLICITUD!$L$1,IF(L2="NULL",L2,CONCATENATE("'",L2,"'"))) -> INSERT INTO `multitabla` (`id_multitabla`, `codigo_tabla`, `nombre_tabla`, `codigo`, `orden`, `valor`, `valor_aux`, `valor_crm`, `estado`, `estado_tabla`, `usuario_crea`, `fecha_crea`, `usuario_modif`, `fecha_modif`) VALUES (DEFAULT, '010', 'Nacionalidad', NULL, NULL, NULL, NULL, NULL, NULL, '1', 'admin', DEFAULT, NULL, NULL);
A3: DEFAULT | B3: 010 | C3: Nacionalidad | D3: 1 | E3: 1 | F3: Afgano | G3: 1 | H3: 538560018 | I3: NULL | J3: 1 | K3: 1 | L3: admin | M3: DEFAULT | N3: NULL | O3: NULL | P3: =SUBSTITUTE(SUBSTITUTE(SUBSTITUTE(SUBSTITUTE(SUBSTITUTE(SUBSTITUTE(SUBSTITUTE(SUBSTITUTE(SUBSTITUTE(SUBSTITUTE(SUBSTITUTE(INSERT!$B$3,DATA_SOLICITUD!$B$1,IF(B3="NULL",B3,CONCATENATE("'",B3,"'"))),DATA_SOLICITUD!$C$1,IF(C3="NULL",C3,CONCATENATE("'",C3,"'"))),DATA_SOLICITUD!$D$1,IF(D3="NULL",D3,CONCATENATE("'",D3,"'"))),DATA_SOLICITUD!$E$1,IF(E3="NULL",E3,CONCATENATE("'",E3,"'"))),DATA_SOLICITUD!$F$1,IF(F3="NULL",F3,CONCATENATE("'",F3,"'"))),DATA_SOLICITUD!$G$1,IF(G3="NULL",G3,CONCATENATE("'",G3,"'"))),DATA_SOLICITUD!$H$1,IF(H3="NULL",H3,CONCATENATE("'",H3,"'"))),DATA_SOLICITUD!$I$1,IF(I3="NULL",I3,CONCATENATE("'",I3,"'"))),DATA_SOLICITUD!$J$1,IF(J3="NULL",J3,CONCATENATE("'",J3,"'"))),DATA_SOLICITUD!$K$1,IF(K3="NULL",K3,CONCATENATE("'",K3,"'"))),DATA_SOLICITUD!$L$1,IF(L3="NULL",L3,CONCATENATE("'",L3,"'"))) -> INSERT INTO `multitabla` (`id_multitabla`, `codigo_tabla`, `nombre_tabla`, `codigo`, `orden`, `valor`, `valor_aux`, `valor_crm`, `estado`, `estado_tabla`, `usuario_crea`, `fecha_crea`, `usuario_modif`, `fecha_modif`) VALUES (DEFAULT, '010', 'Nacionalidad', '1', '1', 'Afgano', '1', '538560018', '1', '1', 'admin', DEFAULT, NULL, NULL);
A4: DEFAULT | B4: 010 | C4: Nacionalidad | D4: 2 | E4: 2 | F4: Albanés | G4: 114 | H4: 538560019 | I4: NULL | J4: 1 | K4: 1 | L4: admin | M4: DEFAULT | N4: NULL | O4: NULL | P4: =SUBSTITUTE(SUBSTITUTE(SUBSTITUTE(SUBSTITUTE(SUBSTITUTE(SUBSTITUTE(SUBSTITUTE(SUBSTITUTE(SUBSTITUTE(SUBSTITUTE(SUBSTITUTE(INSERT!$B$3,DATA_SOLICITUD!$B$1,IF(B4="NULL",B4,CONCATENATE("'",B4,"'"))),DATA_SOLICITUD!$C$1,IF(C4="NULL",C4,CONCATENATE("'",C4,"'"))),DATA_SOLICITUD!$D$1,IF(D4="NULL",D4,CONCATENATE("'",D4,"'"))),DATA_SOLICITUD!$E$1,IF(E4="NULL",E4,CONCATENATE("'",E4,"'"))),DATA_SOLICITUD!$F$1,IF(F4="NULL",F4,CONCATENATE("'",F4,"'"))),DATA_SOLICITUD!$G$1,IF(G4="NULL",G4,CONCATENATE("'",G4,"'"))),DATA_SOLICITUD!$H$1,IF(H4="NULL",H4,CONCATENATE("'",H4,"'"))),DATA_SOLICITUD!$I$1,IF(I4="NULL",I4,CONCATENATE("'",I4,"'"))),DATA_SOLICITUD!$J$1,IF(J4="NULL",J4,CONCATENATE("'",J4,"'"))),DATA_SOLICITUD!$K$1,IF(K4="NULL",K4,CONCATENATE("'",K4,"'"))),DATA_SOLICITUD!$L$1,IF(L4="NULL",L4,CONCATENATE("'",L4,"'"))) -> INSERT INTO `multitabla` (`id_multitabla`, `codigo_tabla`, `nombre_tabla`, `codigo`, `orden`, `valor`, `valor_aux`, `valor_crm`, `estado`, `estado_tabla`, `usuario_crea`, `fecha_crea`, `usuario_modif`, `fecha_modif`) VALUES (DEFAULT, '010', 'Nacionalidad', '2', '2', 'Albanés', '114', '538560019', '1', '1', 'admin', DEFAULT, NULL, NULL);
A5: DEFAULT | B5: 010 | C5: Nacionalidad | D5: 3 | E5: 3 | F5: Alemán | G5: 2 | H5: 538560020 | I5: NULL | J5: 1 | K5: 1 | L5: admin | M5: DEFAULT | N5: NULL | O5: NULL | P5: =SUBSTITUTE(SUBSTITUTE(SUBSTITUTE(SUBSTITUTE(SUBSTITUTE(SUBSTITUTE(SUBSTITUTE(SUBSTITUTE(SUBSTITUTE(SUBSTITUTE(SUBSTITUTE(INSERT!$B$3,DATA_SOLICITUD!$B$1,IF(B5="NULL",B5,CONCATENATE("'",B5,"'"))),DATA_SOLICITUD!$C$1,IF(C5="NULL",C5,CONCATENATE("'",C5,"'"))),DATA_SOLICITUD!$D$1,IF(D5="NULL",D5,CONCATENATE("'",D5,"'"))),DATA_SOLICITUD!$E$1,IF(E5="NULL",E5,CONCATENATE("'",E5,"'"))),DATA_SOLICITUD!$F$1,IF(F5="NULL",F5,CONCATENATE("'",F5,"'"))),DATA_SOLICITUD!$G$1,IF(G5="NULL",G5,CONCATENATE("'",G5,"'"))),DATA_SOLICITUD!$H$1,IF(H5="NULL",H5,CONCATENATE("'",H5,"'"))),DATA_SOLICITUD!$I$1,IF(I5="NULL",I5,CONCATENATE("'",I5,"'"))),DATA_SOLICITUD!$J$1,IF(J5="NULL",J5,CONCATENATE("'",J5,"'"))),DATA_SOLICITUD!$K$1,IF(K5="NULL",K5,CONCATENATE("'",K5,"'"))),DATA_SOLICITUD!$L$1,IF(L5="NULL",L5,CONCATENATE("'",L5,"'"))) -> INSERT INTO `multitabla` (`id_multitabla`, `codigo_tabla`, `nombre_tabla`, `codigo`, `orden`, `valor`, `valor_aux`, `valor_crm`, `estado`, `estado_tabla`, `usuario_crea`, `fecha_crea`, `usuario_modif`, `fecha_modif`) VALUES (DEFAULT, '010', 'Nacionalidad', '3', '3', 'Alemán', '2', '538560020', '1', '1', 'admin', DEFAULT, NULL, NULL);
A6: DEFAULT | B6: 010 | C6: Nacionalidad | D6: 4 | E6: 4 | F6: Andorrana | G6: 96 | H6: 538560021 | I6: NULL | J6: 1 | K6: 1 | L6: admin | M6: DEFAULT | N6: NULL | O6: NULL | P6: =SUBSTITUTE(SUBSTITUTE(SUBSTITUTE(SUBSTITUTE(SUBSTITUTE(SUBSTITUTE(SUBSTITUTE(SUBSTITUTE(SUBSTITUTE(SUBSTITUTE(SUBSTITUTE(INSERT!$B$3,DATA_SOLICITUD!$B$1,IF(B6="NULL",B6,CONCATENATE("'",B6,"'"))),DATA_SOLICITUD!$C$1,IF(C6="NULL",C6,CONCATENATE("'",C6,"'"))),DATA_SOLICITUD!$D$1,IF(D6="NULL",D6,CONCATENATE("'",D6,"'"))),DATA_SOLICITUD!$E$1,IF(E6="NULL",E6,CONCATENATE("'",E6,"'"))),DATA_SOLICITUD!$F$1,IF(F6="NULL",F6,CONCATENATE("'",F6,"'"))),DATA_SOLICITUD!$G$1,IF(G6="NULL",G6,CONCATENATE("'",G6,"'"))),DATA_SOLICITUD!$H$1,IF(H6="NULL",H6,CONCATENATE("'",H6,"'"))),DATA_SOLICITUD!$I$1,IF(I6="NULL",I6,CONCATENATE("'",I6,"'"))),DATA_SOLICITUD!$J$1,IF(J6="NULL",J6,CONCATENATE("'",J6,"'"))),DATA_SOLICITUD!$K$1,IF(K6="NULL",K6,CONCATENATE("'",K6,"'"))),DATA_SOLICITUD!$L$1,IF(L6="NULL",L6,CONCATENATE("'",L6,"'"))) -> INSERT INTO `multitabla` (`id_multitabla`, `codigo_tabla`, `nombre_tabla`, `codigo`, `orden`, `valor`, `valor_aux`, `valor_crm`, `estado`, `estado_tabla`, `usuario_crea`, `fecha_crea`, `usuario_modif`, `fecha_modif`) VALUES (DEFAULT, '010', 'Nacionalidad', '4', '4', 'Andorrana', '96', '538560021', '1', '1', 'admin', DEFAULT, NULL, NULL);
A7: DEFAULT | B7: 010 | C7: Nacionalidad | D7: 5 | E7: 5 | F7: Anguilense | G7: 73 | H7: 538560022 | I7: NULL | J7: 1 | K7: 1 | L7: admin | M7: DEFAULT | N7: NULL | O7: NULL | P7: =SUBSTITUTE(SUBSTITUTE(SUBSTITUTE(SUBSTITUTE(SUBSTITUTE(SUBSTITUTE(SUBSTITUTE(SUBSTITUTE(SUBSTITUTE(SUBSTITUTE(SUBSTITUTE(INSERT!$B$3,DATA_SOLICITUD!$B$1,IF(B7="NULL",B7,CONCATENATE("'",B7,"'"))),DATA_SOLICITUD!$C$1,IF(C7="NULL",C7,CONCATENATE("'",C7,"'"))),DATA_SOLICITUD!$D$1,IF(D7="NULL",D7,CONCATENATE("'",D7,"'"))),DATA_SOLICITUD!$E$1,IF(E7="NULL",E7,CONCATENATE("'",E7,"'"))),DATA_SOLICITUD!$F$1,IF(F7="NULL",F7,CONCATENATE("'",F7,"'"))),DATA_SOLICITUD!$G$1,IF(G7="NULL",G7,CONCATENATE("'",G7,"'"))),DATA_SOLICITUD!$H$1,IF(H7="NULL",H7,CONCATENATE("'",H7,"'"))),DATA_SOLICITUD!$I$1,IF(I7="NULL",I7,CONCATENATE("'",I7,"'"))),DATA_SOLICITUD!$J$1,IF(J7="NULL",J7,CONCATENATE("'",J7,"'"))),DATA_SOLICITUD!$K$1,IF(K7="NULL",K7,CONCATENATE("'",K7,"'"))),DATA_SOLICITUD!$L$1,IF(L7="NULL",L7,CONCATENATE("'",L7,"'"))) -> INSERT INTO `multitabla` (`id_multitabla`, `codigo_tabla`, `nombre_tabla`, `codigo`, `orden`, `valor`, `valor_aux`, `valor_crm`, `estado`, `estado_tabla`, `usuario_crea`, `fecha_crea`, `usuario_modif`, `fecha_modif`) VALUES (DEFAULT, '010', 'Nacionalidad', '5', '5', 'Anguilense', '73', '538560022', '1', '1', 'admin', DEFAULT, NULL, NULL);
A8: DEFAULT | B8: 010 | C8: Nacionalidad | D8: 6 | E8: 6 | F8: Antiguana | G8: 74 | H8: 538560023 | I8: NULL | J8: 1 | K8: 1 | L8: admin | M8: DEFAULT | N8: NULL | O8: NULL | P8: =SUBSTITUTE(SUBSTITUTE(SUBSTITUTE(SUBSTITUTE(SUBSTITUTE(SUBSTITUTE(SUBSTITUTE(SUBSTITUTE(SUBSTITUTE(SUBSTITUTE(SUBSTITUTE(INSERT!$B$3,DATA_SOLICITUD!$B$1,IF(B8="NULL",B8,CONCATENATE("'",B8,"'"))),DATA_SOLICITUD!$C$1,IF(C8="NULL",C8,CONCATENATE("'",C8,"'"))),DATA_SOLICITUD!$D$1,IF(D8="NULL",D8,CONCATENATE("'",D8,"'"))),DATA_SOLICITUD!$E$1,IF(E8="NULL",E8,CONCATENATE("'",E8,"'"))),DATA_SOLICITUD!$F$1,IF(F8="NULL",F8,CONCATENATE("'",F8,"'"))),DATA_SOLICITUD!$G$1,IF(G8="NULL",G8,CONCATENATE("'",G8,"'"))),DATA_SOLICITUD!$H$1,IF(H8="NULL",H8,CONCATENATE("'",H8,"'"))),DATA_SOLICITUD!$I$1,IF(I8="NULL",I8,CONCATENATE("'",I8,"'"))),DATA_SOLICITUD!$J$1,IF(J8="NULL",J8,CONCATENATE("'",J8,"'"))),DATA_SOLICITUD!$K$1,IF(K8="NULL",K8,CONCATENATE("'",K8,"'"))),DATA_SOLICITUD!$L$1,IF(L8="NULL",L8,CONCATENATE("'",L8,"'"))) -> INSERT INTO `multitabla` (`id_multitabla`, `codigo_tabla`, `nombre_tabla`, `codigo`, `orden`, `valor`, `valor_aux`, `valor_crm`, `estado`, `estado_tabla`, `usuario_crea`, `fecha_crea`, `usuario_modif`, `fecha_modif`) VALUES (DEFAULT, '010', 'Nacionalidad', '6', '6', 'Antiguana', '74', '538560023', '1', '1', 'admin', DEFAULT, NULL, NULL);
A9: DEFAULT | B9: 010 | C9: Nacionalidad | D9: 7 | E9: 7 | F9: Árabe | G9: 3 | H9: 538560024 | I9: NULL | J9: 1 | K9: 1 | L9: admin | M9: DEFAULT | N9: NULL | O9: NULL | P9: =SUBSTITUTE(SUBSTITUTE(SUBSTITUTE(SUBSTITUTE(SUBSTITUTE(SUBSTITUTE(SUBSTITUTE(SUBSTITUTE(SUBSTITUTE(SUBSTITUTE(SUBSTITUTE(INSERT!$B$3,DATA_SOLICITUD!$B$1,IF(B9="NULL",B9,CONCATENATE("'",B9,"'"))),DATA_SOLICITUD!$C$1,IF(C9="NULL",C9,CONCATENATE("'",C9,"'"))),DATA_SOLICITUD!$D$1,IF(D9="NULL",D9,CONCATENATE("'",D9,"'"))),DATA_SOLICITUD!$E$1,IF(E9="NULL",E9,CONCATENATE("'",E9,"'"))),DATA_SOLICITUD!$F$1,IF(F9="NULL",F9,CONCATENATE("'",F9,"'"))),DATA_SOLICITUD!$G$1,IF(G9="NULL",G9,CONCATENATE("'",G9,"'"))),DATA_SOLICITUD!$H$1,IF(H9="NULL",H9,CONCATENATE("'",H9,"'"))),DATA_SOLICITUD!$I$1,IF(I9="NULL",I9,CONCATENATE("'",I9,"'"))),DATA_SOLICITUD!$J$1,IF(J9="NULL",J9,CONCATENATE("'",J9,"'"))),DATA_SOLICITUD!$K$1,IF(K9="NULL",K9,CONCATENATE("'",K9,"'"))),DATA_SOLICITUD!$L$1,IF(L9="NULL",L9,CONCATENATE("'",L9,"'"))) -> INSERT INTO `multitabla` (`id_multitabla`, `codigo_tabla`, `nombre_tabla`, `codigo`, `orden`, `valor`, `valor_aux`, `valor_crm`, `estado`, `estado_tabla`, `usuario_crea`, `fecha_crea`, `usuario_modif`, `fecha_modif`) VALUES (DEFAULT, '010', 'Nacionalidad', '7', '7', 'Árabe', '3', '538560024', '1', '1', 'admin', DEFAULT, NULL, NULL);
A10: DEFAULT | B10: 010 | C10: Nacionalidad | D10: 8 | E10: 8 | F10: Argentino | G10: 4 | H10: 538560001 | I10: NULL | J10: 1 | K10: 1 | L10: admin | M10: DEFAULT | N10: NULL | O10: NULL | P10: =SUBSTITUTE(SUBSTITUTE(SUBSTITUTE(SUBSTITUTE(SUBSTITUTE(SUBSTITUTE(SUBSTITUTE(SUBSTITUTE(SUBSTITUTE(SUBSTITUTE(SUBSTITUTE(INSERT!$B$3,DATA_SOLICITUD!$B$1,IF(B10="NULL",B10,CONCATENATE("'",B10,"'"))),DATA_SOLICITUD!$C$1,IF(C10="NULL",C10,CONCATENATE("'",C10,"'"))),DATA_SOLICITUD!$D$1,IF(D10="NULL",D10,CONCATENATE("'",D10,"'"))),DATA_SOLICITUD!$E$1,IF(E10="NULL",E10,CONCATENATE("'",E10,"'"))),DATA_SOLICITUD!$F$1,IF(F10="NULL",F10,CONCATENATE("'",F10,"'"))),DATA_SOLICITUD!$G$1,IF(G10="NULL",G10,CONCATENATE("'",G10,"'"))),DATA_SOLICITUD!$H$1,IF(H10="NULL",H10,CONCATENATE("'",H10,"'"))),DATA_SOLICITUD!$I$1,IF(I10="NULL",I10,CONCATENATE("'",I10,"'"))),DATA_SOLICITUD!$J$1,IF(J10="NULL",J10,CONCATENATE("'",J10,"'"))),DATA_SOLICITUD!$K$1,IF(K10="NULL",K10,CONCATENATE("'",K10,"'"))),DATA_SOLICITUD!$L$1,IF(L10="NULL",L10,CONCATENATE("'",L10,"'"))) -> INSERT INTO `multitabla` (`id_multitabla`, `codigo_tabla`, `nombre_tabla`, `codigo`, `orden`, `valor`, `valor_aux`, `valor_crm`, `estado`, `estado_tabla`, `usuario_crea`, `fecha_crea`, `usuario_modif`, `fecha_modif`) VALUES (DEFAULT, '010', 'Nacionalidad', '8', '8', 'Argentino', '4', '538560001', '1', '1', 'admin', DEFAULT, NULL, NULL);
A11: DEFAULT | B11: 010 | C11: Nacionalidad | D11: 9 | E11: 9 | F11: Arubana | G11: 75 | H11: 538560025 | I11: NULL | J11: 1 | K11: 1 | L11: admin | M11: DEFAULT | N11: NULL | O11: NULL | P11: =SUBSTITUTE(SUBSTITUTE(SUBSTITUTE(SUBSTITUTE(SUBSTITUTE(SUBSTITUTE(SUBSTITUTE(SUBSTITUTE(SUBSTITUTE(SUBSTITUTE(SUBSTITUTE(INSERT!$B$3,DATA_SOLICITUD!$B$1,IF(B11="NULL",B11,CONCATENATE("'",B11,"'"))),DATA_SOLICITUD!$C$1,IF(C11="NULL",C11,CONCATENATE("'",C11,"'"))),DATA_SOLICITUD!$D$1,IF(D11="NULL",D11,CONCATENATE("'",D11,"'"))),DATA_SOLICITUD!$E$1,IF(E11="NULL",E11,CONCATENATE("'",E11,"'"))),DATA_SOLICITUD!$F$1,IF(F11="NULL",F11,CONCATENATE("'",F11,"'"))),DATA_SOLICITUD!$G$1,IF(G11="NULL",G11,CONCATENATE("'",G11,"'"))),DATA_SOLICITUD!$H$1,IF(H11="NULL",H11,CONCATENATE("'",H11,"'"))),DATA_SOLICITUD!$I$1,IF(I11="NULL",I11,CONCATENATE("'",I11,"'"))),DATA_SOLICITUD!$J$1,IF(J11="NULL",J11,CONCATENATE("'",J11,"'"))),DATA_SOLICITUD!$K$1,IF(K11="NULL",K11,CONCATENATE("'",K11,"'"))),DATA_SOLICITUD!$L$1,IF(L11="NULL",L11,CONCATENATE("'",L11,"'"))) -> INSERT INTO `multitabla` (`id_multitabla`, `codigo_tabla`, `nombre_tabla`, `codigo`, `orden`, `valor`, `valor_aux`, `valor_crm`, `estado`, `estado_tabla`, `usuario_crea`, `fecha_crea`, `usuario_modif`, `fecha_modif`) VALUES (DEFAULT, '010', 'Nacionalidad', '9', '9', 'Arubana', '75', '538560025', '1', '1', 'admin', DEFAULT, NULL, NULL);
A12: DEFAULT | B12: 010 | C12: Nacionalidad | D12: 10 | E12: 10 | F12: Australiano | G12: 5 | H12: 538560015 | I12: NULL | J12: 1 | K12: 1 | L12: admin | M12: DEFAULT | N12: NULL | O12: NULL | P12: =SUBSTITUTE(SUBSTITUTE(SUBSTITUTE(SUBSTITUTE(SUBSTITUTE(SUBSTITUTE(SUBSTITUTE(SUBSTITUTE(SUBSTITUTE(SUBSTITUTE(SUBSTITUTE(INSERT!$B$3,DATA_SOLICITUD!$B$1,IF(B12="NULL",B12,CONCATENATE("'",B12,"'"))),DATA_SOLICITUD!$C$1,IF(C12="NULL",C12,CONCATENATE("'",C12,"'"))),DATA_SOLICITUD!$D$1,IF(D12="NULL",D12,CONCATENATE("'",D12,"'"))),DATA_SOLICITUD!$E$1,IF(E12="NULL",E12,CONCATENATE("'",E12,"'"))),DATA_SOLICITUD!$F$1,IF(F12="NULL",F12,CONCATENATE("'",F12,"'"))),DATA_SOLICITUD!$G$1,IF(G12="NULL",G12,CONCATENATE("'",G12,"'"))),DATA_SOLICITUD!$H$1,IF(H12="NULL",H12,CONCATENATE("'",H12,"'"))),DATA_SOLICITUD!$I$1,IF(I12="NULL",I12,CONCATENATE("'",I12,"'"))),DATA_SOLICITUD!$J$1,IF(J12="NULL",J12,CONCATENATE("'",J12,"'"))),DATA_SOLICITUD!$K$1,IF(K12="NULL",K12,CONCATENATE("'",K12,"'"))),DATA_SOLICITUD!$L$1,IF(L12="NULL",L12,CONCATENATE("'",L12,"'"))) -> INSERT INTO `multitabla` (`id_multitabla`, `codigo_tabla`, `nombre_tabla`, `codigo`, `orden`, `valor`, `valor_aux`, `valor_crm`, `estado`, `estado_tabla`, `usuario_crea`, `fecha_crea`, `usuario_modif`, `fecha_modif`) VALUES (DEFAULT, '010', 'Nacionalidad', '10', '10', 'Australiano', '5', '538560015', '1', '1', 'admin', DEFAULT, NULL, NULL);
A13: DEFAULT | B13: 010 | C13: Nacionalidad | D13: 11 | E13: 11 | F13: Bahameña | G13: 94 | H13: 538560026 | I13: NULL | J13: 1 | K13: 1 | L13: admin | M13: DEFAULT | N13: NULL | O13: NULL | P13: =SUBSTITUTE(SUBSTITUTE(SUBSTITUTE(SUBSTITUTE(SUBSTITUTE(SUBSTITUTE(SUBSTITUTE(SUBSTITUTE(SUBSTITUTE(SUBSTITUTE(SUBSTITUTE(INSERT!$B$3,DATA_SOLICITUD!$B$1,IF(B13="NULL",B13,CONCATENATE("'",B13,"'"))),DATA_SOLICITUD!$C$1,IF(C13="NULL",C13,CONCATENATE("'",C13,"'"))),DATA_SOLICITUD!$D$1,IF(D13="NULL",D13,CONCATENATE("'",D13,"'"))),DATA_SOLICITUD!$E$1,IF(E13="NULL",E13,CONCATENATE("'",E13,"'"))),DATA_SOLICITUD!$F$1,IF(F13="NULL",F13,CONCATENATE("'",F13,"'"))),DATA_SOLICITUD!$G$1,IF(G13="NULL",G13,CONCATENATE("'",G13,"'"))),DATA_SOLICITUD!$H$1,IF(H13="NULL",H13,CONCATENATE("'",H13,"'"))),DATA_SOLICITUD!$I$1,IF(I13="NULL",I13,CONCATENATE("'",I13,"'"))),DATA_SOLICITUD!$J$1,IF(J13="NULL",J13,CONCATENATE("'",J13,"'"))),DATA_SOLICITUD!$K$1,IF(K13="NULL",K13,CONCATENATE("'",K13,"'"))),DATA_SOLICITUD!$L$1,IF(L13="NULL",L13,CONCATENATE("'",L13,"'"))) -> INSERT INTO `multitabla` (`id_multitabla`, `codigo_tabla`, `nombre_tabla`, `codigo`, `orden`, `valor`, `valor_aux`, `valor_crm`, `estado`, `estado_tabla`, `usuario_crea`, `fecha_crea`, `usuario_modif`, `fecha_modif`) VALUES (DEFAULT, '010', 'Nacionalidad', '11', '11', 'Bahameña', '94', '538560026', '1', '1', 'admin', DEFAULT, NULL, NULL);
A14: DEFAULT | B14: 010 | C14: Nacionalidad | D14: 12 | E14: 12 | F14: Barbadense | G14: 77 | H14: 538560027 | I14: NULL | J14: 1 | K14: 1 | L14: admin | M14: DEFAULT | N14: NULL | O14: NULL | P14: =SUBSTITUTE(SUBSTITUTE(SUBSTITUTE(SUBSTITUTE(SUBSTITUTE(SUBSTITUTE(SUBSTITUTE(SUBSTITUTE(SUBSTITUTE(SUBSTITUTE(SUBSTITUTE(INSERT!$B$3,DATA_SOLICITUD!$B$1,IF(B14="NULL",B14,CONCATENATE("'",B14,"'"))),DATA_SOLICITUD!$C$1,IF(C14="NULL",C14,CONCATENATE("'",C14,"'"))),DATA_SOLICITUD!$D$1,IF(D14="NULL",D14,CONCATENATE("'",D14,"'"))),DATA_SOLICITUD!$E$1,IF(E14="NULL",E14,CONCATENATE("'",E14,"'"))),DATA_SOLICITUD!$F$1,IF(F14="NULL",F14,CONCATENATE("'",F14,"'"))),DATA_SOLICITUD!$G$1,IF(G14="NULL",G14,CONCATENATE("'",G14,"'"))),DATA_SOLICITUD!$H$1,IF(H14="NULL",H14,CONCATENATE("'",H14,"'"))),DATA_SOLICITUD!$I$1,IF(I14="NULL",I14,CONCATENATE("'",I14,"'"))),DATA_SOLICITUD!$J$1,IF(J14="NULL",J14,CONCATENATE("'",J14,"'"))),DATA_SOLICITUD!$K$1,IF(K14="NULL",K14,CONCATENATE("'",K14,"'"))),DATA_SOLICITUD!$L$1,IF(L14="NULL",L14,CONCATENATE("'",L14,"'"))) -> INSERT INTO `multitabla` (`id_multitabla`, `codigo_tabla`, `nombre_tabla`, `codigo`, `orden`, `valor`, `valor_aux`, `valor_crm`, `estado`, `estado_tabla`, `usuario_crea`, `fecha_crea`, `usuario_modif`, `fecha_modif`) VALUES (DEFAULT, '010', 'Nacionalidad', '12', '12', 'Barbadense', '77', '538560027', '1', '1', 'admin', DEFAULT, NULL, NULL);
... A83: DEFAULT | B83: 010 | C83: Nacionalidad | D83: 81 | E83: 81 | F83: Montserratense | G83: 89 | H83: 538560094 | I83: NULL | J83: 1 | K83: 1 | L83: admin | M83: DEFAULT | N83: NULL | O83: NULL | P83: =SUBSTITUTE(SUBSTITUTE(SUBSTITUTE(SUBSTITUTE(SUBSTITUTE(SUBSTITUTE(SUBSTITUTE(SUBSTITUTE(SUBSTITUTE(SUBSTITUTE(SUBSTITUTE(INSERT!$B$3,DATA_SOLICITUD!$B$1,IF(B83="NULL",B83,CONCATENATE("'",B83,"'"))),DATA_SOLICITUD!$C$1,IF(C83="NULL",C83,CONCATENATE("'",C83,"'"))),DATA_SOLICITUD!$D$1,IF(D83="NULL",D83,CONCATENATE("'",D83,"'"))),DATA_SOLICITUD!$E$1,IF(E83="NULL",E83,CONCATENATE("'",E83,"'"))),DATA_SOLICITUD!$F$1,IF(F83="NULL",F83,CONCATENATE("'",F83,"'"))),DATA_SOLICITUD!$G$1,IF(G83="NULL",G83,CONCATENATE("'",G83,"'"))),DATA_SOLICITUD!$H$1,IF(H83="NULL",H83,CONCATENATE("'",H83,"'"))),DATA_SOLICITUD!$I$1,IF(I83="NULL",I83,CONCATENATE("'",I83,"'"))),DATA_SOLICITUD!$J$1,IF(J83="NULL",J83,CONCATENATE("'",J83,"'"))),DATA_SOLICITUD!$K$1,IF(K83="NULL",K83,CONCATENATE("'",K83,"'"))),DATA_SOLICITUD!$L$1,IF(L83="NULL",L83,CONCATENATE("'",L83,"'"))) -> INSERT INTO `multitabla` (`id_multitabla`, `codigo_tabla`, `nombre_tabla`, `codigo`, `orden`, `valor`, `valor_aux`, `valor_crm`, `estado`, `estado_tabla`, `usuario_crea`, `fecha_crea`, `usuario_modif`, `fecha_modif`) VALUES (DEFAULT, '010', 'Nacionalidad', '81', '81', 'Montserratense', '89', '538560094', '1', '1', 'admin', DEFAULT, NULL, NULL);
A84: DEFAULT | B84: 010 | C84: Nacionalidad | D84: 82 | E84: 82 | F84: NACIONALIDAD DESCONOCIDA | G84: NULL | H84: 538560017 | I84: NULL | J84: 1 | K84: 1 | L84: admin | M84: DEFAULT | N84: NULL | O84: NULL | P84: =SUBSTITUTE(SUBSTITUTE(SUBSTITUTE(SUBSTITUTE(SUBSTITUTE(SUBSTITUTE(SUBSTITUTE(SUBSTITUTE(SUBSTITUTE(SUBSTITUTE(SUBSTITUTE(INSERT!$B$3,DATA_SOLICITUD!$B$1,IF(B84="NULL",B84,CONCATENATE("'",B84,"'"))),DATA_SOLICITUD!$C$1,IF(C84="NULL",C84,CONCATENATE("'",C84,"'"))),DATA_SOLICITUD!$D$1,IF(D84="NULL",D84,CONCATENATE("'",D84,"'"))),DATA_SOLICITUD!$E$1,IF(E84="NULL",E84,CONCATENATE("'",E84,"'"))),DATA_SOLICITUD!$F$1,IF(F84="NULL",F84,CONCATENATE("'",F84,"'"))),DATA_SOLICITUD!$G$1,IF(G84="NULL",G84,CONCATENATE("'",G84,"'"))),DATA_SOLICITUD!$H$1,IF(H84="NULL",H84,CONCATENATE("'",H84,"'"))),DATA_SOLICITUD!$I$1,IF(I84="NULL",I84,CONCATENATE("'",I84,"'"))),DATA_SOLICITUD!$J$1,IF(J84="NULL",J84,CONCATENATE("'",J84,"'"))),DATA_SOLICITUD!$K$1,IF(K84="NULL",K84,CONCATENATE("'",K84,"'"))),DATA_SOLICITUD!$L$1,IF(L84="NULL",L84,CONCATENATE("'",L84,"'"))) -> INSERT INTO `multitabla` (`id_multitabla`, `codigo_tabla`, `nombre_tabla`, `codigo`, `orden`, `valor`, `valor_aux`, `valor_crm`, `estado`, `estado_tabla`, `usuario_crea`, `fecha_crea`, `usuario_modif`, `fecha_modif`) VALUES (DEFAULT, '010', 'Nacionalidad', '82', '82', 'NACIONALIDAD DESCONOCIDA', NULL, '538560017', '1', '1', 'admin', DEFAULT, NULL, NULL);
A85: DEFAULT | B85: 010 | C85: Nacionalidad | D85: 83 | E85: 83 | F85: Nauruano | G85: 106 | H85: 538560095 | I85: NULL | J85: 1 | K85: 1 | L85: admin | M85: DEFAULT | N85: NULL | O85: NULL | P85: =SUBSTITUTE(SUBSTITUTE(SUBSTITUTE(SUBSTITUTE(SUBSTITUTE(SUBSTITUTE(SUBSTITUTE(SUBSTITUTE(SUBSTITUTE(SUBSTITUTE(SUBSTITUTE(INSERT!$B$3,DATA_SOLICITUD!$B$1,IF(B85="NULL",B85,CONCATENATE("'",B85,"'"))),DATA_SOLICITUD!$C$1,IF(C85="NULL",C85,CONCATENATE("'",C85,"'"))),DATA_SOLICITUD!$D$1,IF(D85="NULL",D85,CONCATENATE("'",D85,"'"))),DATA_SOLICITUD!$E$1,IF(E85="NULL",E85,CONCATENATE("'",E85,"'"))),DATA_SOLICITUD!$F$1,IF(F85="NULL",F85,CONCATENATE("'",F85,"'"))),DATA_SOLICITUD!$G$1,IF(G85="NULL",G85,CONCATENATE("'",G85,"'"))),DATA_SOLICITUD!$H$1,IF(H85="NULL",H85,CONCATENATE("'",H85,"'"))),DATA_SOLICITUD!$I$1,IF(I85="NULL",I85,CONCATENATE("'",I85,"'"))),DATA_SOLICITUD!$J$1,IF(J85="NULL",J85,CONCATENATE("'",J85,"'"))),DATA_SOLICITUD!$K$1,IF(K85="NULL",K85,CONCATENATE("'",K85,"'"))),DATA_SOLICITUD!$L$1,IF(L85="NULL",L85,CONCATENATE("'",L85,"'"))) -> INSERT INTO `multitabla` (`id_multitabla`, `codigo_tabla`, `nombre_tabla`, `codigo`, `orden`, `valor`, `valor_aux`, `valor_crm`, `estado`, `estado_tabla`, `usuario_crea`, `fecha_crea`, `usuario_modif`, `fecha_modif`) VALUES (DEFAULT, '010', 'Nacionalidad', '83', '83', 'Nauruano', '106', '538560095', '1', '1', 'admin', DEFAULT, NULL, NULL);
A86: DEFAULT | B86: 010 | C86: Nacionalidad | D86: 84 | E86: 84 | F86: Neocelandés | G86: 52 | H86: 538560096 | I86: NULL | J86: 1 | K86: 1 | L86: admin | M86: DEFAULT | N86: NULL | O86: NULL | P86: =SUBSTITUTE(SUBSTITUTE(SUBSTITUTE(SUBSTITUTE(SUBSTITUTE(SUBSTITUTE(SUBSTITUTE(SUBSTITUTE(SUBSTITUTE(SUBSTITUTE(SUBSTITUTE(INSERT!$B$3,DATA_SOLICITUD!$B$1,IF(B86="NULL",B86,CONCATENATE("'",B86,"'"))),DATA_SOLICITUD!$C$1,IF(C86="NULL",C86,CONCATENATE("'",C86,"'"))),DATA_SOLICITUD!$D$1,IF(D86="NULL",D86,CONCATENATE("'",D86,"'"))),DATA_SOLICITUD!$E$1,IF(E86="NULL",E86,CONCATENATE("'",E86,"'"))),DATA_SOLICITUD!$F$1,IF(F86="NULL",F86,CONCATENATE("'",F86,"'"))),DATA_SOLICITUD!$G$1,IF(G86="NULL",G86,CONCATENATE("'",G86,"'"))),DATA_SOLICITUD!$H$1,IF(H86="NULL",H86,CONCATENATE("'",H86,"'"))),DATA_SOLICITUD!$I$1,IF(I86="NULL",I86,CONCATENATE("'",I86,"'"))),DATA_SOLICITUD!$J$1,IF(J86="NULL",J86,CONCATENATE("'",J86,"'"))),DATA_SOLICITUD!$K$1,IF(K86="NULL",K86,CONCATENATE("'",K86,"'"))),DATA_SOLICITUD!$L$1,IF(L86="NULL",L86,CONCATENATE("'",L86,"'"))) -> INSERT INTO `multitabla` (`id_multitabla`, `codigo_tabla`, `nombre_tabla`, `codigo`, `orden`, `valor`, `valor_aux`, `valor_crm`, `estado`, `estado_tabla`, `usuario_crea`, `fecha_crea`, `usuario_modif`, `fecha_modif`) VALUES (DEFAULT, '010', 'Nacionalidad', '84', '84', 'Neocelandés', '52', '538560096', '1', '1', 'admin', DEFAULT, NULL, NULL);
A87: DEFAULT | B87: 010 | C87: Nacionalidad | D87: 85 | E87: 85 | F87: Nicaragüense | G87: 50 | H87: 538560098 | I87: NULL | J87: 1 | K87: 1 | L87: admin | M87: DEFAULT | N87: NULL | O87: NULL | P87: =SUBSTITUTE(SUBSTITUTE(SUBSTITUTE(SUBSTITUTE(SUBSTITUTE(SUBSTITUTE(SUBSTITUTE(SUBSTITUTE(SUBSTITUTE(SUBSTITUTE(SUBSTITUTE(INSERT!$B$3,DATA_SOLICITUD!$B$1,IF(B87="NULL",B87,CONCATENATE("'",B87,"'"))),DATA_SOLICITUD!$C$1,IF(C87="NULL",C87,CONCATENATE("'",C87,"'"))),DATA_SOLICITUD!$D$1,IF(D87="NULL",D87,CONCATENATE("'",D87,"'"))),DATA_SOLICITUD!$E$1,IF(E87="NULL",E87,CONCATENATE("'",E87,"'"))),DATA_SOLICITUD!$F$1,IF(F87="NULL",F87,CONCATENATE("'",F87,"'"))),DATA_SOLICITUD!$G$1,IF(G87="NULL",G87,CONCATENATE("'",G87,"'"))),DATA_SOLICITUD!$H$1,IF(H87="NULL",H87,CONCATENATE("'",H87,"'"))),DATA_SOLICITUD!$I$1,IF(I87="NULL",I87,CONCATENATE("'",I87,"'"))),DATA_SOLICITUD!$J$1,IF(J87="NULL",J87,CONCATENATE("'",J87,"'"))),DATA_SOLICITUD!$K$1,IF(K87="NULL",K87,CONCATENATE("'",K87,"'"))),DATA_SOLICITUD!$L$1,IF(L87="NULL",L87,CONCATENATE("'",L87,"'"))) -> INSERT INTO `multitabla` (`id_multitabla`, `codigo_tabla`, `nombre_tabla`, `codigo`, `orden`, `valor`, `valor_aux`, `valor_crm`, `estado`, `estado_tabla`, `usuario_crea`, `fecha_crea`, `usuario_modif`, `fecha_modif`) VALUES (DEFAULT, '010', 'Nacionalidad', '85', '85', 'Nicaragüense', '50', '538560098', '1', '1', 'admin', DEFAULT, NULL, NULL);
A88: DEFAULT | B88: 010 | C88: Nacionalidad | D88: 86 | E88: 86 | F88: Ninhuana | G88: 95 | H88: 538560099 | I88: NULL | J88: 1 | K88: 1 | L88: admin | M88: DEFAULT | N88: NULL | O88: NULL | P88: =SUBSTITUTE(SUBSTITUTE(SUBSTITUTE(SUBSTITUTE(SUBSTITUTE(SUBSTITUTE(SUBSTITUTE(SUBSTITUTE(SUBSTITUTE(SUBSTITUTE(SUBSTITUTE(INSERT!$B$3,DATA_SOLICITUD!$B$1,IF(B88="NULL",B88,CONCATENATE("'",B88,"'"))),DATA_SOLICITUD!$C$1,IF(C88="NULL",C88,CONCATENATE("'",C88,"'"))),DATA_SOLICITUD!$D$1,IF(D88="NULL",D88,CONCATENATE("'",D88,"'"))),DATA_SOLICITUD!$E$1,IF(E88="NULL",E88,CONCATENATE("'",E88,"'"))),DATA_SOLICITUD!$F$1,IF(F88="NULL",F88,CONCATENATE("'",F88,"'"))),DATA_SOLICITUD!$G$1,IF(G88="NULL",G88,CONCATENATE("'",G88,"'"))),DATA_SOLICITUD!$H$1,IF(H88="NULL",H88,CONCATENATE("'",H88,"'"))),DATA_SOLICITUD!$I$1,IF(I88="NULL",I88,CONCATENATE("'",I88,"'"))),DATA_SOLICITUD!$J$1,IF(J88="NULL",J88,CONCATENATE("'",J88,"'"))),DATA_SOLICITUD!$K$1,IF(K88="NULL",K88,CONCATENATE("'",K88,"'"))),DATA_SOLICITUD!$L$1,IF(L88="NULL",L88,CONCATENATE("'",L88,"'"))) -> INSERT INTO `multitabla` (`id_multitabla`, `codigo_tabla`, `nombre_tabla`, `codigo`, `orden`, `valor`, `valor_aux`, `valor_crm`, `estado`, `estado_tabla`, `usuario_crea`, `fecha_crea`, `usuario_modif`, `fecha_modif`) VALUES (DEFAULT, '010', 'Nacionalidad', '86', '86', 'Ninhuana', '95', '538560099', '1', '1', 'admin', DEFAULT, NULL, NULL);
A89: DEFAULT | B89: 010 | C89: Nacionalidad | D89: 87 | E89: 87 | F89: No identificada | G89: 71 | H89: 538560100 | I89: NULL | J89: 1 | K89: 1 | L89: admin | M89: DEFAULT | N89: NULL | O89: NULL | P89: =SUBSTITUTE(SUBSTITUTE(SUBSTITUTE(SUBSTITUTE(SUBSTITUTE(SUBSTITUTE(SUBSTITUTE(SUBSTITUTE(SUBSTITUTE(SUBSTITUTE(SUBSTITUTE(INSERT!$B$3,DATA_SOLICITUD!$B$1,IF(B89="NULL",B89,CONCATENATE("'",B89,"'"))),DATA_SOLICITUD!$C$1,IF(C89="NULL",C89,CONCATENATE("'",C89,"'"))),DATA_SOLICITUD!$D$1,IF(D89="NULL",D89,CONCATENATE("'",D89,"'"))),DATA_SOLICITUD!$E$1,IF(E89="NULL",E89,CONCATENATE("'",E89,"'"))),DATA_SOLICITUD!$F$1,IF(F89="NULL",F89,CONCATENATE("'",F89,"'"))),DATA_SOLICITUD!$G$1,IF(G89="NULL",G89,CONCATENATE("'",G89,"'"))),DATA_SOLICITUD!$H$1,IF(H89="NULL",H89,CONCATENATE("'",H89,"'"))),DATA_SOLICITUD!$I$1,IF(I89="NULL",I89,CONCATENATE("'",I89,"'"))),DATA_SOLICITUD!$J$1,IF(J89="NULL",J89,CONCATENATE("'",J89,"'"))),DATA_SOLICITUD!$K$1,IF(K89="NULL",K89,CONCATENATE("'",K89,"'"))),DATA_SOLICITUD!$L$1,IF(L89="NULL",L89,CONCATENATE("'",L89,"'"))) -> INSERT INTO `multitabla` (`id_multitabla`, `codigo_tabla`, `nombre_tabla`, `codigo`, `orden`, `valor`, `valor_aux`, `valor_crm`, `estado`, `estado_tabla`, `usuario_crea`, `fecha_crea`, `usuario_modif`, `fecha_modif`) VALUES (DEFAULT, '010', 'Nacionalidad', '87', '87', 'No identificada', '71', '538560100', '1', '1', 'admin', DEFAULT, NULL, NULL);
A90: DEFAULT | B90: 010 | C90: Nacionalidad | D90: 88 | E90: 88 | F90: Noruego | G90: 51 | H90: 538560101 | I90: NULL | J90: 1 | K90: 1 | L90: admin | M90: DEFAULT | N90: NULL | O90: NULL | P90: =SUBSTITUTE(SUBSTITUTE(SUBSTITUTE(SUBSTITUTE(SUBSTITUTE(SUBSTITUTE(SUBSTITUTE(SUBSTITUTE(SUBSTITUTE(SUBSTITUTE(SUBSTITUTE(INSERT!$B$3,DATA_SOLICITUD!$B$1,IF(B90="NULL",B90,CONCATENATE("'",B90,"'"))),DATA_SOLICITUD!$C$1,IF(C90="NULL",C90,CONCATENATE("'",C90,"'"))),DATA_SOLICITUD!$D$1,IF(D90="NULL",D90,CONCATENATE("'",D90,"'"))),DATA_SOLICITUD!$E$1,IF(E90="NULL",E90,CONCATENATE("'",E90,"'"))),DATA_SOLICITUD!$F$1,IF(F90="NULL",F90,CONCATENATE("'",F90,"'"))),DATA_SOLICITUD!$G$1,IF(G90="NULL",G90,CONCATENATE("'",G90,"'"))),DATA_SOLICITUD!$H$1,IF(H90="NULL",H90,CONCATENATE("'",H90,"'"))),DATA_SOLICITUD!$I$1,IF(I90="NULL",I90,CONCATENATE("'",I90,"'"))),DATA_SOLICITUD!$J$1,IF(J90="NULL",J90,CONCATENATE("'",J90,"'"))),DATA_SOLICITUD!$K$1,IF(K90="NULL",K90,CONCATENATE("'",K90,"'"))),DATA_SOLICITUD!$L$1,IF(L90="NULL",L90,CONCATENATE("'",L90,"'"))) -> INSERT INTO `multitabla` (`id_multitabla`, `codigo_tabla`, `nombre_tabla`, `codigo`, `orden`, `valor`, `valor_aux`, `valor_crm`, `estado`, `estado_tabla`, `usuario_crea`, `fecha_crea`, `usuario_modif`, `fecha_modif`) VALUES (DEFAULT, '010', 'Nacionalidad', '88', '88', 'Noruego', '51', '538560101', '1', '1', 'admin', DEFAULT, NULL, NULL);
A91: DEFAULT | B91: 010 | C91: Nacionalidad | D91: 89 | E91: 89 | F91: OTRA NACIONALIDAD | G91: NULL | H91: 538560016 | I91: NULL | J91: 1 | K91: 1 | L91: admin | M91: DEFAULT | N91: NULL | O91: NULL | P91: =SUBSTITUTE(SUBSTITUTE(SUBSTITUTE(SUBSTITUTE(SUBSTITUTE(SUBSTITUTE(SUBSTITUTE(SUBSTITUTE(SUBSTITUTE(SUBSTITUTE(SUBSTITUTE(INSERT!$B$3,DATA_SOLICITUD!$B$1,IF(B91="NULL",B91,CONCATENATE("'",B91,"'"))),DATA_SOLICITUD!$C$1,IF(C91="NULL",C91,CONCATENATE("'",C91,"'"))),DATA_SOLICITUD!$D$1,IF(D91="NULL",D91,CONCATENATE("'",D91,"'"))),DATA_SOLICITUD!$E$1,IF(E91="NULL",E91,CONCATENATE("'",E91,"'"))),DATA_SOLICITUD!$F$1,IF(F91="NULL",F91,CONCATENATE("'",F91,"'"))),DATA_SOLICITUD!$G$1,IF(G91="NULL",G91,CONCATENATE("'",G91,"'"))),DATA_SOLICITUD!$H$1,IF(H91="NULL",H91,CONCATENATE("'",H91,"'"))),DATA_SOLICITUD!$I$1,IF(I91="NULL",I91,CONCATENATE("'",I91,"'"))),DATA_SOLICITUD!$J$1,IF(J91="NULL",J91,CONCATENATE("'",J91,"'"))),DATA_SOLICITUD!$K$1,IF(K91="NULL",K91,CONCATENATE("'",K91,"'"))),DATA_SOLICITUD!$L$1,IF(L91="NULL",L91,CONCATENATE("'",L91,"'"))) -> INSERT INTO `multitabla` (`id_multitabla`, `codigo_tabla`, `nombre_tabla`, `codigo`, `orden`, `valor`, `valor_aux`, `valor_crm`, `estado`, `estado_tabla`, `usuario_crea`, `fecha_crea`, `usuario_modif`, `fecha_modif`) VALUES (DEFAULT, '010', 'Nacionalidad', '89', '89', 'OTRA NACIONALIDAD', NULL, '538560016', '1', '1', 'admin', DEFAULT, NULL, NULL);
A92: DEFAULT | B92: 010 | C92: Nacionalidad | D92: 90 | E92: 90 | F92: Panameño | G92: 53 | H92: 538560014 | I92: NULL | J92: 1 | K92: 1 | L92: admin | M92: DEFAULT | N92: NULL | O92: NULL | P92: =SUBSTITUTE(SUBSTITUTE(SUBSTITUTE(SUBSTITUTE(SUBSTITUTE(SUBSTITUTE(SUBSTITUTE(SUBSTITUTE(SUBSTITUTE(SUBSTITUTE(SUBSTITUTE(INSERT!$B$3,DATA_SOLICITUD!$B$1,IF(B92="NULL",B92,CONCATENATE("'",B92,"'"))),DATA_SOLICITUD!$C$1,IF(C92="NULL",C92,CONCATENATE("'",C92,"'"))),DATA_SOLICITUD!$D$1,IF(D92="NULL",D92,CONCATENATE("'",D92,"'"))),DATA_SOLICITUD!$E$1,IF(E92="NULL",E92,CONCATENATE("'",E92,"'"))),DATA_SOLICITUD!$F$1,IF(F92="NULL",F92,CONCATENATE("'",F92,"'"))),DATA_SOLICITUD!$G$1,IF(G92="NULL",G92,CONCATENATE("'",G92,"'"))),DATA_SOLICITUD!$H$1,IF(H92="NULL",H92,CONCATENATE("'",H92,"'"))),DATA_SOLICITUD!$I$1,IF(I92="NULL",I92,CONCATENATE("'",I92,"'"))),DATA_SOLICITUD!$J$1,IF(J92="NULL",J92,CONCATENATE("'",J92,"'"))),DATA_SOLICITUD!$K$1,IF(K92="NULL",K92,CONCATENATE("'",K92,"'"))),DATA_SOLICITUD!$L$1,IF(L92="NULL",L92,CONCATENATE("'",L92,"'"))) -> INSERT INTO `multitabla` (`id_multitabla`, `codigo_tabla`, `nombre_tabla`, `codigo`, `orden`, `valor`, `valor_aux`, `valor_crm`, `estado`, `estado_tabla`, `usuario_crea`, `fecha_crea`, `usuario_modif`, `fecha_modif`) VALUES (DEFAULT, '010', 'Nacionalidad', '90', '90', 'Panameño', '53', '538560014', '1', '1', 'admin', DEFAULT, NULL, NULL);
A93: DEFAULT | B93: 010 | C93: Nacionalidad | D93: 91 | E93: 91 | F93: Paraguayo | G93: 54 | H93: 538560012 | I93: NULL | J93: 1 | K93: 1 | L93: admin | M93: DEFAULT | N93: NULL | O93: NULL | P93: =SUBSTITUTE(SUBSTITUTE(SUBSTITUTE(SUBSTITUTE(SUBSTITUTE(SUBSTITUTE(SUBSTITUTE(SUBSTITUTE(SUBSTITUTE(SUBSTITUTE(SUBSTITUTE(INSERT!$B$3,DATA_SOLICITUD!$B$1,IF(B93="NULL",B93,CONCATENATE("'",B93,"'"))),DATA_SOLICITUD!$C$1,IF(C93="NULL",C93,CONCATENATE("'",C93,"'"))),DATA_SOLICITUD!$D$1,IF(D93="NULL",D93,CONCATENATE("'",D93,"'"))),DATA_SOLICITUD!$E$1,IF(E93="NULL",E93,CONCATENATE("'",E93,"'"))),DATA_SOLICITUD!$F$1,IF(F93="NULL",F93,CONCATENATE("'",F93,"'"))),DATA_SOLICITUD!$G$1,IF(G93="NULL",G93,CONCATENATE("'",G93,"'"))),DATA_SOLICITUD!$H$1,IF(H93="NULL",H93,CONCATENATE("'",H93,"'"))),DATA_SOLICITUD!$I$1,IF(I93="NULL",I93,CONCATENATE("'",I93,"'"))),DATA_SOLICITUD!$J$1,IF(J93="NULL",J93,CONCATENATE("'",J93,"'"))),DATA_SOLICITUD!$K$1,IF(K93="NULL",K93,CONCATENATE("'",K93,"'"))),DATA_SOLICITUD!$L$1,IF(L93="NULL",L93,CONCATENATE("'",L93,"'"))) -> INSERT INTO `multitabla` (`id_multitabla`, `codigo_tabla`, `nombre_tabla`, `codigo`, `orden`, `valor`, `valor_aux`, `valor_crm`, `estado`, `estado_tabla`, `usuario_crea`, `fecha_crea`, `usuario_modif`, `fecha_modif`) VALUES (DEFAULT, '010', 'Nacionalidad', '91', '91', 'Paraguayo', '54', '538560012', '1', '1', 'admin', DEFAULT, NULL, NULL);
A94: DEFAULT | B94: 010 | C94: Nacionalidad | D94: 92 | E94: 92 | F94: Peruano | G94: 55 | H94: 538560003 | I94: NULL | J94: 1 | K94: 1 | L94: admin | M94: DEFAULT | N94: NULL | O94: NULL | P94: =SUBSTITUTE(SUBSTITUTE(SUBSTITUTE(SUBSTITUTE(SUBSTITUTE(SUBSTITUTE(SUBSTITUTE(SUBSTITUTE(SUBSTITUTE(SUBSTITUTE(SUBSTITUTE(INSERT!$B$3,DATA_SOLICITUD!$B$1,IF(B94="NULL",B94,CONCATENATE("'",B94,"'"))),DATA_SOLICITUD!$C$1,IF(C94="NULL",C94,CONCATENATE("'",C94,"'"))),DATA_SOLICITUD!$D$1,IF(D94="NULL",D94,CONCATENATE("'",D94,"'"))),DATA_SOLICITUD!$E$1,IF(E94="NULL",E94,CONCATENATE("'",E94,"'"))),DATA_SOLICITUD!$F$1,IF(F94="NULL",F94,CONCATENATE("'",F94,"'"))),DATA_SOLICITUD!$G$1,IF(G94="NULL",G94,CONCATENATE("'",G94,"'"))),DATA_SOLICITUD!$H$1,IF(H94="NULL",H94,CONCATENATE("'",H94,"'"))),DATA_SOLICITUD!$I$1,IF(I94="NULL",I94,CONCATENATE("'",I94,"'"))),DATA_SOLICITUD!$J$1,IF(J94="NULL",J94,CONCATENATE("'",J94,"'"))),DATA_SOLICITUD!$K$1,IF(K94="NULL",K94,CONCATENATE("'",K94,"'"))),DATA_SOLICITUD!$L$1,IF(L94="NULL",L94,CONCATENATE("'",L94,"'"))) -> INSERT INTO `multitabla` (`id_multitabla`, `codigo_tabla`, `nombre_tabla`, `codigo`, `orden`, `valor`, `valor_aux`, `valor_crm`, `estado`, `estado_tabla`, `usuario_crea`, `fecha_crea`, `usuario_modif`, `fecha_modif`) VALUES (DEFAULT, '010', 'Nacionalidad', '92', '92', 'Peruano', '55', '538560003', '1', '1', 'admin', DEFAULT, NULL, NULL);
A95: DEFAULT | B95: 010 | C95: Nacionalidad | D95: 93 | E95: 93 | F95: Polaco | G95: 56 | H95: 538560102 | I95: NULL | J95: 1 | K95: 1 | L95: admin | M95: DEFAULT | N95: NULL | O95: NULL | P95: =SUBSTITUTE(SUBSTITUTE(SUBSTITUTE(SUBSTITUTE(SUBSTITUTE(SUBSTITUTE(SUBSTITUTE(SUBSTITUTE(SUBSTITUTE(SUBSTITUTE(SUBSTITUTE(INSERT!$B$3,DATA_SOLICITUD!$B$1,IF(B95="NULL",B95,CONCATENATE("'",B95,"'"))),DATA_SOLICITUD!$C$1,IF(C95="NULL",C95,CONCATENATE("'",C95,"'"))),DATA_SOLICITUD!$D$1,IF(D95="NULL",D95,CONCATENATE("'",D95,"'"))),DATA_SOLICITUD!$E$1,IF(E95="NULL",E95,CONCATENATE("'",E95,"'"))),DATA_SOLICITUD!$F$1,IF(F95="NULL",F95,CONCATENATE("'",F95,"'"))),DATA_SOLICITUD!$G$1,IF(G95="NULL",G95,CONCATENATE("'",G95,"'"))),DATA_SOLICITUD!$H$1,IF(H95="NULL",H95,CONCATENATE("'",H95,"'"))),DATA_SOLICITUD!$I$1,IF(I95="NULL",I95,CONCATENATE("'",I95,"'"))),DATA_SOLICITUD!$J$1,IF(J95="NULL",J95,CONCATENATE("'",J95,"'"))),DATA_SOLICITUD!$K$1,IF(K95="NULL",K95,CONCATENATE("'",K95,"'"))),DATA_SOLICITUD!$L$1,IF(L95="NULL",L95,CONCATENATE("'",L95,"'"))) -> INSERT INTO `multitabla` (`id_multitabla`, `codigo_tabla`, `nombre_tabla`, `codigo`, `orden`, `valor`, `valor_aux`, `valor_crm`, `estado`, `estado_tabla`, `usuario_crea`, `fecha_crea`, `usuario_modif`, `fecha_modif`) VALUES (DEFAULT, '010', 'Nacionalidad', '93', '93', 'Polaco', '56', '538560102', '1', '1', 'admin', DEFAULT, NULL, NULL);
A96: DEFAULT | B96: 010 | C96: Nacionalidad | D96: 94 | E96: 94 | F96: Portugués | G96: 57 | H96: 538560103 | I96: NULL | J96: 1 | K96: 1 | L96: admin | M96: DEFAULT | N96: NULL | O96: NULL | P96: =SUBSTITUTE(SUBSTITUTE(SUBSTITUTE(SUBSTITUTE(SUBSTITUTE(SUBSTITUTE(SUBSTITUTE(SUBSTITUTE(SUBSTITUTE(SUBSTITUTE(SUBSTITUTE(INSERT!$B$3,DATA_SOLICITUD!$B$1,IF(B96="NULL",B96,CONCATENATE("'",B96,"'"))),DATA_SOLICITUD!$C$1,IF(C96="NULL",C96,CONCATENATE("'",C96,"'"))),DATA_SOLICITUD!$D$1,IF(D96="NULL",D96,CONCATENATE("'",D96,"'"))),DATA_SOLICITUD!$E$1,IF(E96="NULL",E96,CONCATENATE("'",E96,"'"))),DATA_SOLICITUD!$F$1,IF(F96="NULL",F96,CONCATENATE("'",F96,"'"))),DATA_SOLICITUD!$G$1,IF(G96="NULL",G96,CONCATENATE("'",G96,"'"))),DATA_SOLICITUD!$H$1,IF(H96="NULL",H96,CONCATENATE("'",H96,"'"))),DATA_SOLICITUD!$I$1,IF(I96="NULL",I96,CONCATENATE("'",I96,"'"))),DATA_SOLICITUD!$J$1,IF(J96="NULL",J96,CONCATENATE("'",J96,"'"))),DATA_SOLICITUD!$K$1,IF(K96="NULL",K96,CONCATENATE("'",K96,"'"))),DATA_SOLICITUD!$L$1,IF(L96="NULL",L96,CONCATENATE("'",L96,"'"))) -> INSERT INTO `multitabla` (`id_multitabla`, `codigo_tabla`, `nombre_tabla`, `codigo`, `orden`, `valor`, `valor_aux`, `valor_crm`, `estado`, `estado_tabla`, `usuario_crea`, `fecha_crea`, `usuario_modif`, `fecha_modif`) VALUES (DEFAULT, '010', 'Nacionalidad', '94', '94', 'Portugués', '57', '538560103', '1', '1', 'admin', DEFAULT, NULL, NULL);
A97: DEFAULT | B97: 010 | C97: Nacionalidad | D97: 95 | E97: 95 | F97: Puertorriqueño | G97: 58 | H97: 538560104 | I97: NULL | J97: 1 | K97: 1 | L97: admin | M97: DEFAULT | N97: NULL | O97: NULL | P97: =SUBSTITUTE(SUBSTITUTE(SUBSTITUTE(SUBSTITUTE(SUBSTITUTE(SUBSTITUTE(SUBSTITUTE(SUBSTITUTE(SUBSTITUTE(SUBSTITUTE(SUBSTITUTE(INSERT!$B$3,DATA_SOLICITUD!$B$1,IF(B97="NULL",B97,CONCATENATE("'",B97,"'"))),DATA_SOLICITUD!$C$1,IF(C97="NULL",C97,CONCATENATE("'",C97,"'"))),DATA_SOLICITUD!$D$1,IF(D97="NULL",D97,CONCATENATE("'",D97,"'"))),DATA_SOLICITUD!$E$1,IF(E97="NULL",E97,CONCATENATE("'",E97,"'"))),DATA_SOLICITUD!$F$1,IF(F97="NULL",F97,CONCATENATE("'",F97,"'"))),DATA_SOLICITUD!$G$1,IF(G97="NULL",G97,CONCATENATE("'",G97,"'"))),DATA_SOLICITUD!$H$1,IF(H97="NULL",H97,CONCATENATE("'",H97,"'"))),DATA_SOLICITUD!$I$1,IF(I97="NULL",I97,CONCATENATE("'",I97,"'"))),DATA_SOLICITUD!$J$1,IF(J97="NULL",J97,CONCATENATE("'",J97,"'"))),DATA_SOLICITUD!$K$1,IF(K97="NULL",K97,CONCATENATE("'",K97,"'"))),DATA_SOLICITUD!$L$1,IF(L97="NULL",L97,CONCATENATE("'",L97,"'"))) -> INSERT INTO `multitabla` (`id_multitabla`, `codigo_tabla`, `nombre_tabla`, `codigo`, `orden`, `valor`, `valor_aux`, `valor_crm`, `estado`, `estado_tabla`, `usuario_crea`, `fecha_crea`, `usuario_modif`, `fecha_modif`) VALUES (DEFAULT, '010', 'Nacionalidad', '95', '95', 'Puertorriqueño', '58', '538560104', '1', '1', 'admin', DEFAULT, NULL, NULL);
A98: DEFAULT | B98: 010 | C98: Nacionalidad | D98: 96 | E98: 96 | F98: Rumano | G98: 60 | H98: 538560105 | I98: NULL | J98: 1 | K98: 1 | L98: admin | M98: DEFAULT | N98: NULL | O98: NULL | P98: =SUBSTITUTE(SUBSTITUTE(SUBSTITUTE(SUBSTITUTE(SUBSTITUTE(SUBSTITUTE(SUBSTITUTE(SUBSTITUTE(SUBSTITUTE(SUBSTITUTE(SUBSTITUTE(INSERT!$B$3,DATA_SOLICITUD!$B$1,IF(B98="NULL",B98,CONCATENATE("'",B98,"'"))),DATA_SOLICITUD!$C$1,IF(C98="NULL",C98,CONCATENATE("'",C98,"'"))),DATA_SOLICITUD!$D$1,IF(D98="NULL",D98,CONCATENATE("'",D98,"'"))),DATA_SOLICITUD!$E$1,IF(E98="NULL",E98,CONCATENATE("'",E98,"'"))),DATA_SOLICITUD!$F$1,IF(F98="NULL",F98,CONCATENATE("'",F98,"'"))),DATA_SOLICITUD!$G$1,IF(G98="NULL",G98,CONCATENATE("'",G98,"'"))),DATA_SOLICITUD!$H$1,IF(H98="NULL",H98,CONCATENATE("'",H98,"'"))),DATA_SOLICITUD!$I$1,IF(I98="NULL",I98,CONCATENATE("'",I98,"'"))),DATA_SOLICITUD!$J$1,IF(J98="NULL",J98,CONCATENATE("'",J98,"'"))),DATA_SOLICITUD!$K$1,IF(K98="NULL",K98,CONCATENATE("'",K98,"'"))),DATA_SOLICITUD!$L$1,IF(L98="NULL",L98,CONCATENATE("'",L98,"'"))) -> INSERT INTO `multitabla` (`id_multitabla`, `codigo_tabla`, `nombre_tabla`, `codigo`, `orden`, `valor`, `valor_aux`, `valor_crm`, `estado`, `estado_tabla`, `usuario_crea`, `fecha_crea`, `usuario_modif`, `fecha_modif`) VALUES (DEFAULT, '010', 'Nacionalidad', '96', '96', 'Rumano', '60', '538560105', '1', '1', 'admin', DEFAULT, NULL, NULL);
A99: DEFAULT | B99: 010 | C99: Nacionalidad | D99: 97 | E99: 97 | F99: Rusa | G99: 130 | H99: 538560106 | I99: NULL | J99: 1 | K99: 1 | L99: admin | M99: DEFAULT | N99: NULL | O99: NULL | P99: =SUBSTITUTE(SUBSTITUTE(SUBSTITUTE(SUBSTITUTE(SUBSTITUTE(SUBSTITUTE(SUBSTITUTE(SUBSTITUTE(SUBSTITUTE(SUBSTITUTE(SUBSTITUTE(INSERT!$B$3,DATA_SOLICITUD!$B$1,IF(B99="NULL",B99,CONCATENATE("'",B99,"'"))),DATA_SOLICITUD!$C$1,IF(C99="NULL",C99,CONCATENATE("'",C99,"'"))),DATA_SOLICITUD!$D$1,IF(D99="NULL",D99,CONCATENATE("'",D99,"'"))),DATA_SOLICITUD!$E$1,IF(E99="NULL",E99,CONCATENATE("'",E99,"'"))),DATA_SOLICITUD!$F$1,IF(F99="NULL",F99,CONCATENATE("'",F99,"'"))),DATA_SOLICITUD!$G$1,IF(G99="NULL",G99,CONCATENATE("'",G99,"'"))),DATA_SOLICITUD!$H$1,IF(H99="NULL",H99,CONCATENATE("'",H99,"'"))),DATA_SOLICITUD!$I$1,IF(I99="NULL",I99,CONCATENATE("'",I99,"'"))),DATA_SOLICITUD!$J$1,IF(J99="NULL",J99,CONCATENATE("'",J99,"'"))),DATA_SOLICITUD!$K$1,IF(K99="NULL",K99,CONCATENATE("'",K99,"'"))),DATA_SOLICITUD!$L$1,IF(L99="NULL",L99,CONCATENATE("'",L99,"'"))) -> INSERT INTO `multitabla` (`id_multitabla`, `codigo_tabla`, `nombre_tabla`, `codigo`, `orden`, `valor`, `valor_aux`, `valor_crm`, `estado`, `estado_tabla`, `usuario_crea`, `fecha_crea`, `usuario_modif`, `fecha_modif`) VALUES (DEFAULT, '010', 'Nacionalidad', '97', '97', 'Rusa', '130', '538560106', '1', '1', 'admin', DEFAULT, NULL, NULL);
A100: DEFAULT | B100: 010 | C100: Nacionalidad | D100: 98 | E100: 98 | F100: Salvadoreño | G100: 20 | H100: 538560108 | I100: NULL | J100: 1 | K100: 1 | L100: admin | M100: DEFAULT | N100: NULL | O100: NULL | P100: =SUBSTITUTE(SUBSTITUTE(SUBSTITUTE(SUBSTITUTE(SUBSTITUTE(SUBSTITUTE(SUBSTITUTE(SUBSTITUTE(SUBSTITUTE(SUBSTITUTE(SUBSTITUTE(INSERT!$B$3,DATA_SOLICITUD!$B$1,IF(B100="NULL",B100,CONCATENATE("'",B100,"'"))),DATA_SOLICITUD!$C$1,IF(C100="NULL",C100,CONCATENATE("'",C100,"'"))),DATA_SOLICITUD!$D$1,IF(D100="NULL",D100,CONCATENATE("'",D100,"'"))),DATA_SOLICITUD!$E$1,IF(E100="NULL",E100,CONCATENATE("'",E100,"'"))),DATA_SOLICITUD!$F$1,IF(F100="NULL",F100,CONCATENATE("'",F100,"'"))),DATA_SOLICITUD!$G$1,IF(G100="NULL",G100,CONCATENATE("'",G100,"'"))),DATA_SOLICITUD!$H$1,IF(H100="NULL",H100,CONCATENATE("'",H100,"'"))),DATA_SOLICITUD!$I$1,IF(I100="NULL",I100,CONCATENATE("'",I100,"'"))),DATA_SOLICITUD!$J$1,IF(J100="NULL",J100,CONCATENATE("'",J100,"'"))),DATA_SOLICITUD!$K$1,IF(K100="NULL",K100,CONCATENATE("'",K100,"'"))),DATA_SOLICITUD!$L$1,IF(L100="NULL",L100,CONCATENATE("'",L100,"'"))) -> INSERT INTO `multitabla` (`id_multitabla`, `codigo_tabla`, `nombre_tabla`, `codigo`, `orden`, `valor`, `valor_aux`, `valor_crm`, `estado`, `estado_tabla`, `usuario_crea`, `fecha_crea`, `usuario_modif`, `fecha_modif`) VALUES (DEFAULT, '010', 'Nacionalidad', '98', '98', 'Salvadoreño', '20', '538560108', '1', '1', 'admin', DEFAULT, NULL, NULL);
A101: DEFAULT | B101: 010 | C101: Nacionalidad | D101: 99 | E101: 99 | F101: Samboana | G101: 81 | H101: 538560109 | I101: NULL | J101: 1 | K101: 1 | L101: admin | M101: DEFAULT | N101: NULL | O101: NULL | P101: =SUBSTITUTE(SUBSTITUTE(SUBSTITUTE(SUBSTITUTE(SUBSTITUTE(SUBSTITUTE(SUBSTITUTE(SUBSTITUTE(SUBSTITUTE(SUBSTITUTE(SUBSTITUTE(INSERT!$B$3,DATA_SOLICITUD!$B$1,IF(B101="NULL",B101,CONCATENATE("'",B101,"'"))),DATA_SOLICITUD!$C$1,IF(C101="NULL",C101,CONCATENATE("'",C101,"'"))),DATA_SOLICITUD!$D$1,IF(D101="NULL",D101,CONCATENATE("'",D101,"'"))),DATA_SOLICITUD!$E$1,IF(E101="NULL",E101,CONCATENATE("'",E101,"'"))),DATA_SOLICITUD!$F$1,IF(F101="NULL",F101,CONCATENATE("'",F101,"'"))),DATA_SOLICITUD!$G$1,IF(G101="NULL",G101,CONCATENATE("'",G101,"'"))),DATA_SOLICITUD!$H$1,IF(H101="NULL",H101,CONCATENATE("'",H101,"'"))),DATA_SOLICITUD!$I$1,IF(I101="NULL",I101,CONCATENATE("'",I101,"'"))),DATA_SOLICITUD!$J$1,IF(J101="NULL",J101,CONCATENATE("'",J101,"'"))),DATA_SOLICITUD!$K$1,IF(K101="NULL",K101,CONCATENATE("'",K101,"'"))),DATA_SOLICITUD!$L$1,IF(L101="NULL",L101,CONCATENATE("'",L101,"'"))) -> INSERT INTO `multitabla` (`id_multitabla`, `codigo_tabla`, `nombre_tabla`, `codigo`, `orden`, `valor`, `valor_aux`, `valor_crm`, `estado`, `estado_tabla`, `usuario_crea`, `fecha_crea`, `usuario_modif`, `fecha_modif`) VALUES (DEFAULT, '010', 'Nacionalidad', '99', '99', 'Samboana', '81', '538560109', '1', '1', 'admin', DEFAULT, NULL, NULL);
A102: DEFAULT | B102: 010 | C102: Nacionalidad | D102: 100 | E102: 100 | F102: Samoana Estadounidense | G102: 112 | H102: 538560110 | I102: NULL | J102: 1 | K102: 1 | L102: admin | M102: DEFAULT | N102: NULL | O102: NULL | P102: =SUBSTITUTE(SUBSTITUTE(SUBSTITUTE(SUBSTITUTE(SUBSTITUTE(SUBSTITUTE(SUBSTITUTE(SUBSTITUTE(SUBSTITUTE(SUBSTITUTE(SUBSTITUTE(INSERT!$B$3,DATA_SOLICITUD!$B$1,IF(B102="NULL",B102,CONCATENATE("'",B102,"'"))),DATA_SOLICITUD!$C$1,IF(C102="NULL",C102,CONCATENATE("'",C102,"'"))),DATA_SOLICITUD!$D$1,IF(D102="NULL",D102,CONCATENATE("'",D102,"'"))),DATA_SOLICITUD!$E$1,IF(E102="NULL",E102,CONCATENATE("'",E102,"'"))),DATA_SOLICITUD!$F$1,IF(F102="NULL",F102,CONCATENATE("'",F102,"'"))),DATA_SOLICITUD!$G$1,IF(G102="NULL",G102,CONCATENATE("'",G102,"'"))),DATA_SOLICITUD!$H$1,IF(H102="NULL",H102,CONCATENATE("'",H102,"'"))),DATA_SOLICITUD!$I$1,IF(I102="NULL",I102,CONCATENATE("'",I102,"'"))),DATA_SOLICITUD!$J$1,IF(J102="NULL",J102,CONCATENATE("'",J102,"'"))),DATA_SOLICITUD!$K$1,IF(K102="NULL",K102,CONCATENATE("'",K102,"'"))),DATA_SOLICITUD!$L$1,IF(L102="NULL",L102,CONCATENATE("'",L102,"'"))) -> INSERT INTO `multitabla` (`id_multitabla`, `codigo_tabla`, `nombre_tabla`, `codigo`, `orden`, `valor`, `valor_aux`, `valor_crm`, `estado`, `estado_tabla`, `usuario_crea`, `fecha_crea`, `usuario_modif`, `fecha_modif`) VALUES (DEFAULT, '010', 'Nacionalidad', '100', '100', 'Samoana Estadounidense', '112', '538560110', '1', '1', 'admin', DEFAULT, NULL, NULL);
A103: DEFAULT | B103: 010 | C103: Nacionalidad | D103: 101 | E103: 101 | F103: Sancristobaleña | G103: 82 | H103: 538560111 | I103: NULL | J103: 1 | K103: 1 | L103: admin | M103: DEFAULT | N103: NULL | O103: NULL | P103: =SUBSTITUTE(SUBSTITUTE(SUBSTITUTE(SUBSTITUTE(SUBSTITUTE(SUBSTITUTE(SUBSTITUTE(SUBSTITUTE(SUBSTITUTE(SUBSTITUTE(SUBSTITUTE(INSERT!$B$3,DATA_SOLICITUD!$B$1,IF(B103="NULL",B103,CONCATENATE("'",B103,"'"))),DATA_SOLICITUD!$C$1,IF(C103="NULL",C103,CONCATENATE("'",C103,"'"))),DATA_SOLICITUD!$D$1,IF(D103="NULL",D103,CONCATENATE("'",D103,"'"))),DATA_SOLICITUD!$E$1,IF(E103="NULL",E103,CONCATENATE("'",E103,"'"))),DATA_SOLICITUD!$F$1,IF(F103="NULL",F103,CONCATENATE("'",F103,"'"))),DATA_SOLICITUD!$G$1,IF(G103="NULL",G103,CONCATENATE("'",G103,"'"))),DATA_SOLICITUD!$H$1,IF(H103="NULL",H103,CONCATENATE("'",H103,"'"))),DATA_SOLICITUD!$I$1,IF(I103="NULL",I103,CONCATENATE("'",I103,"'"))),DATA_SOLICITUD!$J$1,IF(J103="NULL",J103,CONCATENATE("'",J103,"'"))),DATA_SOLICITUD!$K$1,IF(K103="NULL",K103,CONCATENATE("'",K103,"'"))),DATA_SOLICITUD!$L$1,IF(L103="NULL",L103,CONCATENATE("'",L103,"'"))) -> INSERT INTO `multitabla` (`id_multitabla`, `codigo_tabla`, `nombre_tabla`, `codigo`, `orden`, `valor`, `valor_aux`, `valor_crm`, `estado`, `estado_tabla`, `usuario_crea`, `fecha_crea`, `usuario_modif`, `fecha_modif`) VALUES (DEFAULT, '010', 'Nacionalidad', '101', '101', 'Sancristobaleña', '82', '538560111', '1', '1', 'admin', DEFAULT, NULL, NULL);
... A127: DEFAULT | B127: 010 | C127: Nacionalidad | D127: 125 | E127: 125 | F127: Zimbabuense | G127: 133 | H127: 538560135 | I127: NULL | J127: 1 | K127: 1 | L127: admin | M127: DEFAULT | N127: NULL | O127: NULL | P127: =SUBSTITUTE(SUBSTITUTE(SUBSTITUTE(SUBSTITUTE(SUBSTITUTE(SUBSTITUTE(SUBSTITUTE(SUBSTITUTE(SUBSTITUTE(SUBSTITUTE(SUBSTITUTE(INSERT!$B$3,DATA_SOLICITUD!$B$1,IF(B127="NULL",B127,CONCATENATE("'",B127,"'"))),DATA_SOLICITUD!$C$1,IF(C127="NULL",C127,CONCATENATE("'",C127,"'"))),DATA_SOLICITUD!$D$1,IF(D127="NULL",D127,CONCATENATE("'",D127,"'"))),DATA_SOLICITUD!$E$1,IF(E127="NULL",E127,CONCATENATE("'",E127,"'"))),DATA_SOLICITUD!$F$1,IF(F127="NULL",F127,CONCATENATE("'",F127,"'"))),DATA_SOLICITUD!$G$1,IF(G127="NULL",G127,CONCATENATE("'",G127,"'"))),DATA_SOLICITUD!$H$1,IF(H127="NULL",H127,CONCATENATE("'",H127,"'"))),DATA_SOLICITUD!$I$1,IF(I127="NULL",I127,CONCATENATE("'",I127,"'"))),DATA_SOLICITUD!$J$1,IF(J127="NULL",J127,CONCATENATE("'",J127,"'"))),DATA_SOLICITUD!$K$1,IF(K127="NULL",K127,CONCATENATE("'",K127,"'"))),DATA_SOLICITUD!$L$1,IF(L127="NULL",L127,CONCATENATE("'",L127,"'"))) -> INSERT INTO `multitabla` (`id_multitabla`, `codigo_tabla`, `nombre_tabla`, `codigo`, `orden`, `valor`, `valor_aux`, `valor_crm`, `estado`, `estado_tabla`, `usuario_crea`, `fecha_crea`, `usuario_modif`, `fecha_modif`) VALUES (DEFAULT, '010', 'Nacionalidad', '125', '125', 'Zimbabuense', '133', '538560135', '1', '1', 'admin', DEFAULT, NULL, NULL);
A128: DEFAULT | B128: 011 | C128: Estado Solicitud | D128: NULL | E128: NULL | F128: NULL | G128: NULL | H128: NULL | I128: NULL | J128: NULL | K128: 1 | L128: admin | M128: DEFAULT | N128: NULL | O128: NULL | P128: =SUBSTITUTE(SUBSTITUTE(SUBSTITUTE(SUBSTITUTE(SUBSTITUTE(SUBSTITUTE(SUBSTITUTE(SUBSTITUTE(SUBSTITUTE(SUBSTITUTE(SUBSTITUTE(INSERT!$B$3,DATA_SOLICITUD!$B$1,IF(B128="NULL",B128,CONCATENATE("'",B128,"'"))),DATA_SOLICITUD!$C$1,IF(C128="NULL",C128,CONCATENATE("'",C128,"'"))),DATA_SOLICITUD!$D$1,IF(D128="NULL",D128,CONCATENATE("'",D128,"'"))),DATA_SOLICITUD!$E$1,IF(E128="NULL",E128,CONCATENATE("'",E128,"'"))),DATA_SOLICITUD!$F$1,IF(F128="NULL",F128,CONCATENATE("'",F128,"'"))),DATA_SOLICITUD!$G$1,IF(G128="NULL",G128,CONCATENATE("'",G128,"'"))),DATA_SOLICITUD!$H$1,IF(H128="NULL",H128,CONCATENATE("'",H128,"'"))),DATA_SOLICITUD!$I$1,IF(I128="NULL",I128,CONCATENATE("'",I128,"'"))),DATA_SOLICITUD!$J$1,IF(J128="NULL",J128,CONCATENATE("'",J128,"'"))),DATA_SOLICITUD!$K$1,IF(K128="NULL",K128,CONCATENATE("'",K128,"'"))),DATA_SOLICITUD!$L$1,IF(L128="NULL",L128,CONCATENATE("'",L128,"'"))) -> INSERT INTO `multitabla` (`id_multitabla`, `codigo_tabla`, `nombre_tabla`, `codigo`, `orden`, `valor`, `valor_aux`, `valor_crm`, `estado`, `estado_tabla`, `usuario_crea`, `fecha_crea`, `usuario_modif`, `fecha_modif`) VALUES (DEFAULT, '011', 'Estado Solicitud', NULL, NULL, NULL, NULL, NULL, NULL, '1', 'admin', DEFAULT, NULL, NULL);
A129: DEFAULT | B129: 011 | C129: Estado Solicitud | D129: 1 | E129: 1 | F129: Pendiente | G129: NULL | H129: NULL | I129: NULL | J129: 1 | K129: 1 | L129: admin | M129: DEFAULT | N129: NULL | O129: NULL | P129: =SUBSTITUTE(SUBSTITUTE(SUBSTITUTE(SUBSTITUTE(SUBSTITUTE(SUBSTITUTE(SUBSTITUTE(SUBSTITUTE(SUBSTITUTE(SUBSTITUTE(SUBSTITUTE(INSERT!$B$3,DATA_SOLICITUD!$B$1,IF(B129="NULL",B129,CONCATENATE("'",B129,"'"))),DATA_SOLICITUD!$C$1,IF(C129="NULL",C129,CONCATENATE("'",C129,"'"))),DATA_SOLICITUD!$D$1,IF(D129="NULL",D129,CONCATENATE("'",D129,"'"))),DATA_SOLICITUD!$E$1,IF(E129="NULL",E129,CONCATENATE("'",E129,"'"))),DATA_SOLICITUD!$F$1,IF(F129="NULL",F129,CONCATENATE("'",F129,"'"))),DATA_SOLICITUD!$G$1,IF(G129="NULL",G129,CONCATENATE("'",G129,"'"))),DATA_SOLICITUD!$H$1,IF(H129="NULL",H129,CONCATENATE("'",H129,"'"))),DATA_SOLICITUD!$I$1,IF(I129="NULL",I129,CONCATENATE("'",I129,"'"))),DATA_SOLICITUD!$J$1,IF(J129="NULL",J129,CONCATENATE("'",J129,"'"))),DATA_SOLICITUD!$K$1,IF(K129="NULL",K129,CONCATENATE("'",K129,"'"))),DATA_SOLICITUD!$L$1,IF(L129="NULL",L129,CONCATENATE("'",L129,"'"))) -> INSERT INTO `multitabla` (`id_multitabla`, `codigo_tabla`, `nombre_tabla`, `codigo`, `orden`, `valor`, `valor_aux`, `valor_crm`, `estado`, `estado_tabla`, `usuario_crea`, `fecha_crea`, `usuario_modif`, `fecha_modif`) VALUES (DEFAULT, '011', 'Estado Solicitud', '1', '1', 'Pendiente', NULL, NULL, '1', '1', 'admin', DEFAULT, NULL, NULL);
A130: DEFAULT | B130: 011 | C130: Estado Solicitud | D130: 2 | E130: 2 | F130: Pendiente Firma | G130: NULL | H130: NULL | I130: NULL | J130: 1 | K130: 1 | L130: admin | M130: DEFAULT | N130: NULL | O130: NULL | P130: =SUBSTITUTE(SUBSTITUTE(SUBSTITUTE(SUBSTITUTE(SUBSTITUTE(SUBSTITUTE(SUBSTITUTE(SUBSTITUTE(SUBSTITUTE(SUBSTITUTE(SUBSTITUTE(INSERT!$B$3,DATA_SOLICITUD!$B$1,IF(B130="NULL",B130,CONCATENATE("'",B130,"'"))),DATA_SOLICITUD!$C$1,IF(C130="NULL",C130,CONCATENATE("'",C130,"'"))),DATA_SOLICITUD!$D$1,IF(D130="NULL",D130,CONCATENATE("'",D130,"'"))),DATA_SOLICITUD!$E$1,IF(E130="NULL",E130,CONCATENATE("'",E130,"'"))),DATA_SOLICITUD!$F$1,IF(F130="NULL",F130,CONCATENATE("'",F130,"'"))),DATA_SOLICITUD!$G$1,IF(G130="NULL",G130,CONCATENATE("'",G130,"'"))),DATA_SOLICITUD!$H$1,IF(H130="NULL",H130,CONCATENATE("'",H130,"'"))),DATA_SOLICITUD!$I$1,IF(I130="NULL",I130,CONCATENATE("'",I130,"'"))),DATA_SOLICITUD!$J$1,IF(J130="NULL",J130,CONCATENATE("'",J130,"'"))),DATA_SOLICITUD!$K$1,IF(K130="NULL",K130,CONCATENATE("'",K130,"'"))),DATA_SOLICITUD!$L$1,IF(L130="NULL",L130,CONCATENATE("'",L130,"'"))) -> INSERT INTO `multitabla` (`id_multitabla`, `codigo_tabla`, `nombre_tabla`, `codigo`, `orden`, `valor`, `valor_aux`, `valor_crm`, `estado`, `estado_tabla`, `usuario_crea`, `fecha_crea`, `usuario_modif`, `fecha_modif`) VALUES (DEFAULT, '011', 'Estado Solicitud', '2', '2', 'Pendiente Firma', NULL, NULL, '1', '1', 'admin', DEFAULT, NULL, NULL);
A131: DEFAULT | B131: 011 | C131: Estado Solicitud | D131: 3 | E131: 3 | F131: Firmado | G131: NULL | H131: NULL | I131: NULL | J131: 1 | K131: 1 | L131: admin | M131: DEFAULT | N131: NULL | O131: NULL | P131: =SUBSTITUTE(SUBSTITUTE(SUBSTITUTE(SUBSTITUTE(SUBSTITUTE(SUBSTITUTE(SUBSTITUTE(SUBSTITUTE(SUBSTITUTE(SUBSTITUTE(SUBSTITUTE(INSERT!$B$3,DATA_SOLICITUD!$B$1,IF(B131="NULL",B131,CONCATENATE("'",B131,"'"))),DATA_SOLICITUD!$C$1,IF(C131="NULL",C131,CONCATENATE("'",C131,"'"))),DATA_SOLICITUD!$D$1,IF(D131="NULL",D131,CONCATENATE("'",D131,"'"))),DATA_SOLICITUD!$E$1,IF(E131="NULL",E131,CONCATENATE("'",E131,"'"))),DATA_SOLICITUD!$F$1,IF(F131="NULL",F131,CONCATENATE("'",F131,"'"))),DATA_SOLICITUD!$G$1,IF(G131="NULL",G131,CONCATENATE("'",G131,"'"))),DATA_SOLICITUD!$H$1,IF(H131="NULL",H131,CONCATENATE("'",H131,"'"))),DATA_SOLICITUD!$I$1,IF(I131="NULL",I131,CONCATENATE("'",I131,"'"))),DATA_SOLICITUD!$J$1,IF(J131="NULL",J131,CONCATENATE("'",J131,"'"))),DATA_SOLICITUD!$K$1,IF(K131="NULL",K131,CONCATENATE("'",K131,"'"))),DATA_SOLICITUD!$L$1,IF(L131="NULL",L131,CONCATENATE("'",L131,"'"))) -> INSERT INTO `multitabla` (`id_multitabla`, `codigo_tabla`, `nombre_tabla`, `codigo`, `orden`, `valor`, `valor_aux`, `valor_crm`, `estado`, `estado_tabla`, `usuario_crea`, `fecha_crea`, `usuario_modif`, `fecha_modif`) VALUES (DEFAULT, '011', 'Estado Solicitud', '3', '3', 'Firmado', NULL, NULL, '1', '1', 'admin', DEFAULT, NULL, NULL);
A132: DEFAULT | B132: 012 | C132: Estado Civil | D132: NULL | E132: NULL | F132: NULL | G132: NULL | H132: NULL | I132: NULL | J132: NULL | K132: 1 | L132: admin | M132: DEFAULT | N132: NULL | O132: NULL | P132: =SUBSTITUTE(SUBSTITUTE(SUBSTITUTE(SUBSTITUTE(SUBSTITUTE(SUBSTITUTE(SUBSTITUTE(SUBSTITUTE(SUBSTITUTE(SUBSTITUTE(SUBSTITUTE(INSERT!$B$3,DATA_SOLICITUD!$B$1,IF(B132="NULL",B132,CONCATENATE("'",B132,"'"))),DATA_SOLICITUD!$C$1,IF(C132="NULL",C132,CONCATENATE("'",C132,"'"))),DATA_SOLICITUD!$D$1,IF(D132="NULL",D132,CONCATENATE("'",D132,"'"))),DATA_SOLICITUD!$E$1,IF(E132="NULL",E132,CONCATENATE("'",E132,"'"))),DATA_SOLICITUD!$F$1,IF(F132="NULL",F132,CONCATENATE("'",F132,"'"))),DATA_SOLICITUD!$G$1,IF(G132="NULL",G132,CONCATENATE("'",G132,"'"))),DATA_SOLICITUD!$H$1,IF(H132="NULL",H132,CONCATENATE("'",H132,"'"))),DATA_SOLICITUD!$I$1,IF(I132="NULL",I132,CONCATENATE("'",I132,"'"))),DATA_SOLICITUD!$J$1,IF(J132="NULL",J132,CONCATENATE("'",J132,"'"))),DATA_SOLICITUD!$K$1,IF(K132="NULL",K132,CONCATENATE("'",K132,"'"))),DATA_SOLICITUD!$L$1,IF(L132="NULL",L132,CONCATENATE("'",L132,"'"))) -> INSERT INTO `multitabla` (`id_multitabla`, `codigo_tabla`, `nombre_tabla`, `codigo`, `orden`, `valor`, `valor_aux`, `valor_crm`, `estado`, `estado_tabla`, `usuario_crea`, `fecha_crea`, `usuario_modif`, `fecha_modif`) VALUES (DEFAULT, '012', 'Estado Civil', NULL, NULL, NULL, NULL, NULL, NULL, '1', 'admin', DEFAULT, NULL, NULL);
A133: DEFAULT | B133: 012 | C133: Estado Civil | D133: 1 | E133: 1 | F133: Soltero(a) | G133: NULL | H133: 538560001 | I133: NULL | J133: 1 | K133: 1 | L133: admin | M133: DEFAULT | N133: NULL | O133: NULL | P133: =SUBSTITUTE(SUBSTITUTE(SUBSTITUTE(SUBSTITUTE(SUBSTITUTE(SUBSTITUTE(SUBSTITUTE(SUBSTITUTE(SUBSTITUTE(SUBSTITUTE(SUBSTITUTE(INSERT!$B$3,DATA_SOLICITUD!$B$1,IF(B133="NULL",B133,CONCATENATE("'",B133,"'"))),DATA_SOLICITUD!$C$1,IF(C133="NULL",C133,CONCATENATE("'",C133,"'"))),DATA_SOLICITUD!$D$1,IF(D133="NULL",D133,CONCATENATE("'",D133,"'"))),DATA_SOLICITUD!$E$1,IF(E133="NULL",E133,CONCATENATE("'",E133,"'"))),DATA_SOLICITUD!$F$1,IF(F133="NULL",F133,CONCATENATE("'",F133,"'"))),DATA_SOLICITUD!$G$1,IF(G133="NULL",G133,CONCATENATE("'",G133,"'"))),DATA_SOLICITUD!$H$1,IF(H133="NULL",H133,CONCATENATE("'",H133,"'"))),DATA_SOLICITUD!$I$1,IF(I133="NULL",I133,CONCATENATE("'",I133,"'"))),DATA_SOLICITUD!$J$1,IF(J133="NULL",J133,CONCATENATE("'",J133,"'"))),DATA_SOLICITUD!$K$1,IF(K133="NULL",K133,CONCATENATE("'",K133,"'"))),DATA_SOLICITUD!$L$1,IF(L133="NULL",L133,CONCATENATE("'",L133,"'"))) -> INSERT INTO `multitabla` (`id_multitabla`, `codigo_tabla`, `nombre_tabla`, `codigo`, `orden`, `valor`, `valor_aux`, `valor_crm`, `estado`, `estado_tabla`, `usuario_crea`, `fecha_crea`, `usuario_modif`, `fecha_modif`) VALUES (DEFAULT, '012', 'Estado Civil', '1', '1', 'Soltero(a)', NULL, '538560001', '1', '1', 'admin', DEFAULT, NULL, NULL);
A134: DEFAULT | B134: 012 | C134: Estado Civil | D134: 2 | E134: 2 | F134: Casado(a) | G134: NULL | H134: 538560002 | I134: NULL | J134: 1 | K134: 1 | L134: admin | M134: DEFAULT | N134: NULL | O134: NULL | P134: =SUBSTITUTE(SUBSTITUTE(SUBSTITUTE(SUBSTITUTE(SUBSTITUTE(SUBSTITUTE(SUBSTITUTE(SUBSTITUTE(SUBSTITUTE(SUBSTITUTE(SUBSTITUTE(INSERT!$B$3,DATA_SOLICITUD!$B$1,IF(B134="NULL",B134,CONCATENATE("'",B134,"'"))),DATA_SOLICITUD!$C$1,IF(C134="NULL",C134,CONCATENATE("'",C134,"'"))),DATA_SOLICITUD!$D$1,IF(D134="NULL",D134,CONCATENATE("'",D134,"'"))),DATA_SOLICITUD!$E$1,IF(E134="NULL",E134,CONCATENATE("'",E134,"'"))),DATA_SOLICITUD!$F$1,IF(F134="NULL",F134,CONCATENATE("'",F134,"'"))),DATA_SOLICITUD!$G$1,IF(G134="NULL",G134,CONCATENATE("'",G134,"'"))),DATA_SOLICITUD!$H$1,IF(H134="NULL",H134,CONCATENATE("'",H134,"'"))),DATA_SOLICITUD!$I$1,IF(I134="NULL",I134,CONCATENATE("'",I134,"'"))),DATA_SOLICITUD!$J$1,IF(J134="NULL",J134,CONCATENATE("'",J134,"'"))),DATA_SOLICITUD!$K$1,IF(K134="NULL",K134,CONCATENATE("'",K134,"'"))),DATA_SOLICITUD!$L$1,IF(L134="NULL",L134,CONCATENATE("'",L134,"'"))) -> INSERT INTO `multitabla` (`id_multitabla`, `codigo_tabla`, `nombre_tabla`, `codigo`, `orden`, `valor`, `valor_aux`, `valor_crm`, `estado`, `estado_tabla`, `usuario_crea`, `fecha_crea`, `usuario_modif`, `fecha_modif`) VALUES (DEFAULT, '012', 'Estado Civil', '2', '2', 'Casado(a)', NULL, '538560002', '1', '1', 'admin', DEFAULT, NULL, NULL);
A135: DEFAULT | B135: 012 | C135: Estado Civil | D135: 3 | E135: 3 | F135: Viudo(a) | G135: NULL | H135: 538560003 | I135: NULL | J135: 1 | K135: 1 | L135: admin | M135: DEFAULT | N135: NULL | O135: NULL | P135: =SUBSTITUTE(SUBSTITUTE(SUBSTITUTE(SUBSTITUTE(SUBSTITUTE(SUBSTITUTE(SUBSTITUTE(SUBSTITUTE(SUBSTITUTE(SUBSTITUTE(SUBSTITUTE(INSERT!$B$3,DATA_SOLICITUD!$B$1,IF(B135="NULL",B135,CONCATENATE("'",B135,"'"))),DATA_SOLICITUD!$C$1,IF(C135="NULL",C135,CONCATENATE("'",C135,"'"))),DATA_SOLICITUD!$D$1,IF(D135="NULL",D135,CONCATENATE("'",D135,"'"))),DATA_SOLICITUD!$E$1,IF(E135="NULL",E135,CONCATENATE("'",E135,"'"))),DATA_SOLICITUD!$F$1,IF(F135="NULL",F135,CONCATENATE("'",F135,"'"))),DATA_SOLICITUD!$G$1,IF(G135="NULL",G135,CONCATENATE("'",G135,"'"))),DATA_SOLICITUD!$H$1,IF(H135="NULL",H135,CONCATENATE("'",H135,"'"))),DATA_SOLICITUD!$I$1,IF(I135="NULL",I135,CONCATENATE("'",I135,"'"))),DATA_SOLICITUD!$J$1,IF(J135="NULL",J135,CONCATENATE("'",J135,"'"))),DATA_SOLICITUD!$K$1,IF(K135="NULL",K135,CONCATENATE("'",K135,"'"))),DATA_SOLICITUD!$L$1,IF(L135="NULL",L135,CONCATENATE("'",L135,"'"))) -> INSERT INTO `multitabla` (`id_multitabla`, `codigo_tabla`, `nombre_tabla`, `codigo`, `orden`, `valor`, `valor_aux`, `valor_crm`, `estado`, `estado_tabla`, `usuario_crea`, `fecha_crea`, `usuario_modif`, `fecha_modif`) VALUES (DEFAULT, '012', 'Estado Civil', '3', '3', 'Viudo(a)', NULL, '538560003', '1', '1', 'admin', DEFAULT, NULL, NULL);
A136: DEFAULT | B136: 012 | C136: Estado Civil | D136: 4 | E136: 4 | F136: Divorciado(a) | G136: NULL | H136: 538560004 | I136: NULL | J136: 1 | K136: 1 | L136: admin | M136: DEFAULT | N136: NULL | O136: NULL | P136: =SUBSTITUTE(SUBSTITUTE(SUBSTITUTE(SUBSTITUTE(SUBSTITUTE(SUBSTITUTE(SUBSTITUTE(SUBSTITUTE(SUBSTITUTE(SUBSTITUTE(SUBSTITUTE(INSERT!$B$3,DATA_SOLICITUD!$B$1,IF(B136="NULL",B136,CONCATENATE("'",B136,"'"))),DATA_SOLICITUD!$C$1,IF(C136="NULL",C136,CONCATENATE("'",C136,"'"))),DATA_SOLICITUD!$D$1,IF(D136="NULL",D136,CONCATENATE("'",D136,"'"))),DATA_SOLICITUD!$E$1,IF(E136="NULL",E136,CONCATENATE("'",E136,"'"))),DATA_SOLICITUD!$F$1,IF(F136="NULL",F136,CONCATENATE("'",F136,"'"))),DATA_SOLICITUD!$G$1,IF(G136="NULL",G136,CONCATENATE("'",G136,"'"))),DATA_SOLICITUD!$H$1,IF(H136="NULL",H136,CONCATENATE("'",H136,"'"))),DATA_SOLICITUD!$I$1,IF(I136="NULL",I136,CONCATENATE("'",I136,"'"))),DATA_SOLICITUD!$J$1,IF(J136="NULL",J136,CONCATENATE("'",J136,"'"))),DATA_SOLICITUD!$K$1,IF(K136="NULL",K136,CONCATENATE("'",K136,"'"))),DATA_SOLICITUD!$L$1,IF(L136="NULL",L136,CONCATENATE("'",L136,"'"))) -> INSERT INTO `multitabla` (`id_multitabla`, `codigo_tabla`, `nombre_tabla`, `codigo`, `orden`, `valor`, `valor_aux`, `valor_crm`, `estado`, `estado_tabla`, `usuario_crea`, `fecha_crea`, `usuario_modif`, `fecha_modif`) VALUES (DEFAULT, '012', 'Estado Civil', '4', '4', 'Divorciado(a)', NULL, '538560004', '1', '1', 'admin', DEFAULT, NULL, NULL);
A137: DEFAULT | B137: 012 | C137: Estado Civil | D137: 5 | E137: 5 | F137: Conviviente | G137: NULL | H137: 538560005 | I137: NULL | J137: 1 | K137: 1 | L137: admin | M137: DEFAULT | N137: NULL | O137: NULL | P137: =SUBSTITUTE(SUBSTITUTE(SUBSTITUTE(SUBSTITUTE(SUBSTITUTE(SUBSTITUTE(SUBSTITUTE(SUBSTITUTE(SUBSTITUTE(SUBSTITUTE(SUBSTITUTE(INSERT!$B$3,DATA_SOLICITUD!$B$1,IF(B137="NULL",B137,CONCATENATE("'",B137,"'"))),DATA_SOLICITUD!$C$1,IF(C137="NULL",C137,CONCATENATE("'",C137,"'"))),DATA_SOLICITUD!$D$1,IF(D137="NULL",D137,CONCATENATE("'",D137,"'"))),DATA_SOLICITUD!$E$1,IF(E137="NULL",E137,CONCATENATE("'",E137,"'"))),DATA_SOLICITUD!$F$1,IF(F137="NULL",F137,CONCATENATE("'",F137,"'"))),DATA_SOLICITUD!$G$1,IF(G137="NULL",G137,CONCATENATE("'",G137,"'"))),DATA_SOLICITUD!$H$1,IF(H137="NULL",H137,CONCATENATE("'",H137,"'"))),DATA_SOLICITUD!$I$1,IF(I137="NULL",I137,CONCATENATE("'",I137,"'"))),DATA_SOLICITUD!$J$1,IF(J137="NULL",J137,CONCATENATE("'",J137,"'"))),DATA_SOLICITUD!$K$1,IF(K137="NULL",K137,CONCATENATE("'",K137,"'"))),DATA_SOLICITUD!$L$1,IF(L137="NULL",L137,CONCATENATE("'",L137,"'"))) -> INSERT INTO `multitabla` (`id_multitabla`, `codigo_tabla`, `nombre_tabla`, `codigo`, `orden`, `valor`, `valor_aux`, `valor_crm`, `estado`, `estado_tabla`, `usuario_crea`, `fecha_crea`, `usuario_modif`, `fecha_modif`) VALUES (DEFAULT, '012', 'Estado Civil', '5', '5', 'Conviviente', NULL, '538560005', '1', '1', 'admin', DEFAULT, NULL, NULL);
A138: DEFAULT | B138: 013 | C138: Dirección Tipo | D138: NULL | E138: NULL | F138: NULL | G138: NULL | H138: NULL | I138: NULL | J138: NULL | K138: 1 | L138: admin | M138: DEFAULT | N138: NULL | O138: NULL | P138: =SUBSTITUTE(SUBSTITUTE(SUBSTITUTE(SUBSTITUTE(SUBSTITUTE(SUBSTITUTE(SUBSTITUTE(SUBSTITUTE(SUBSTITUTE(SUBSTITUTE(SUBSTITUTE(INSERT!$B$3,DATA_SOLICITUD!$B$1,IF(B138="NULL",B138,CONCATENATE("'",B138,"'"))),DATA_SOLICITUD!$C$1,IF(C138="NULL",C138,CONCATENATE("'",C138,"'"))),DATA_SOLICITUD!$D$1,IF(D138="NULL",D138,CONCATENATE("'",D138,"'"))),DATA_SOLICITUD!$E$1,IF(E138="NULL",E138,CONCATENATE("'",E138,"'"))),DATA_SOLICITUD!$F$1,IF(F138="NULL",F138,CONCATENATE("'",F138,"'"))),DATA_SOLICITUD!$G$1,IF(G138="NULL",G138,CONCATENATE("'",G138,"'"))),DATA_SOLICITUD!$H$1,IF(H138="NULL",H138,CONCATENATE("'",H138,"'"))),DATA_SOLICITUD!$I$1,IF(I138="NULL",I138,CONCATENATE("'",I138,"'"))),DATA_SOLICITUD!$J$1,IF(J138="NULL",J138,CONCATENATE("'",J138,"'"))),DATA_SOLICITUD!$K$1,IF(K138="NULL",K138,CONCATENATE("'",K138,"'"))),DATA_SOLICITUD!$L$1,IF(L138="NULL",L138,CONCATENATE("'",L138,"'"))) -> INSERT INTO `multitabla` (`id_multitabla`, `codigo_tabla`, `nombre_tabla`, `codigo`, `orden`, `valor`, `valor_aux`, `valor_crm`, `estado`, `estado_tabla`, `usuario_crea`, `fecha_crea`, `usuario_modif`, `fecha_modif`) VALUES (DEFAULT, '013', 'Dirección Tipo', NULL, NULL, NULL, NULL, NULL, NULL, '1', 'admin', DEFAULT, NULL, NULL);
A139: DEFAULT | B139: 013 | C139: Dirección Tipo | D139: 1 | E139: 1 | F139: Jirón | G139: Jirón | H139: NULL | I139: NULL | J139: 1 | K139: 1 | L139: admin | M139: DEFAULT | N139: NULL | O139: NULL | P139: =SUBSTITUTE(SUBSTITUTE(SUBSTITUTE(SUBSTITUTE(SUBSTITUTE(SUBSTITUTE(SUBSTITUTE(SUBSTITUTE(SUBSTITUTE(SUBSTITUTE(SUBSTITUTE(INSERT!$B$3,DATA_SOLICITUD!$B$1,IF(B139="NULL",B139,CONCATENATE("'",B139,"'"))),DATA_SOLICITUD!$C$1,IF(C139="NULL",C139,CONCATENATE("'",C139,"'"))),DATA_SOLICITUD!$D$1,IF(D139="NULL",D139,CONCATENATE("'",D139,"'"))),DATA_SOLICITUD!$E$1,IF(E139="NULL",E139,CONCATENATE("'",E139,"'"))),DATA_SOLICITUD!$F$1,IF(F139="NULL",F139,CONCATENATE("'",F139,"'"))),DATA_SOLICITUD!$G$1,IF(G139="NULL",G139,CONCATENATE("'",G139,"'"))),DATA_SOLICITUD!$H$1,IF(H139="NULL",H139,CONCATENATE("'",H139,"'"))),DATA_SOLICITUD!$I$1,IF(I139="NULL",I139,CONCATENATE("'",I139,"'"))),DATA_SOLICITUD!$J$1,IF(J139="NULL",J139,CONCATENATE("'",J139,"'"))),DATA_SOLICITUD!$K$1,IF(K139="NULL",K139,CONCATENATE("'",K139,"'"))),DATA_SOLICITUD!$L$1,IF(L139="NULL",L139,CONCATENATE("'",L139,"'"))) -> INSERT INTO `multitabla` (`id_multitabla`, `codigo_tabla`, `nombre_tabla`, `codigo`, `orden`, `valor`, `valor_aux`, `valor_crm`, `estado`, `estado_tabla`, `usuario_crea`, `fecha_crea`, `usuario_modif`, `fecha_modif`) VALUES (DEFAULT, '013', 'Dirección Tipo', '1', '1', 'Jirón', 'Jirón', NULL, '1', '1', 'admin', DEFAULT, NULL, NULL);
A140: DEFAULT | B140: 013 | C140: Dirección Tipo | D140: 2 | E140: 2 | F140: Avenida | G140: Avenida | H140: NULL | I140: NULL | J140: 1 | K140: 1 | L140: admin | M140: DEFAULT | N140: NULL | O140: NULL | P140: =SUBSTITUTE(SUBSTITUTE(SUBSTITUTE(SUBSTITUTE(SUBSTITUTE(SUBSTITUTE(SUBSTITUTE(SUBSTITUTE(SUBSTITUTE(SUBSTITUTE(SUBSTITUTE(INSERT!$B$3,DATA_SOLICITUD!$B$1,IF(B140="NULL",B140,CONCATENATE("'",B140,"'"))),DATA_SOLICITUD!$C$1,IF(C140="NULL",C140,CONCATENATE("'",C140,"'"))),DATA_SOLICITUD!$D$1,IF(D140="NULL",D140,CONCATENATE("'",D140,"'"))),DATA_SOLICITUD!$E$1,IF(E140="NULL",E140,CONCATENATE("'",E140,"'"))),DATA_SOLICITUD!$F$1,IF(F140="NULL",F140,CONCATENATE("'",F140,"'"))),DATA_SOLICITUD!$G$1,IF(G140="NULL",G140,CONCATENATE("'",G140,"'"))),DATA_SOLICITUD!$H$1,IF(H140="NULL",H140,CONCATENATE("'",H140,"'"))),DATA_SOLICITUD!$I$1,IF(I140="NULL",I140,CONCATENATE("'",I140,"'"))),DATA_SOLICITUD!$J$1,IF(J140="NULL",J140,CONCATENATE("'",J140,"'"))),DATA_SOLICITUD!$K$1,IF(K140="NULL",K140,CONCATENATE("'",K140,"'"))),DATA_SOLICITUD!$L$1,IF(L140="NULL",L140,CONCATENATE("'",L140,"'"))) -> INSERT INTO `multitabla` (`id_multitabla`, `codigo_tabla`, `nombre_tabla`, `codigo`, `orden`, `valor`, `valor_aux`, `valor_crm`, `estado`, `estado_tabla`, `usuario_crea`, `fecha_crea`, `usuario_modif`, `fecha_modif`) VALUES (DEFAULT, '013', 'Dirección Tipo', '2', '2', 'Avenida', 'Avenida', NULL, '1', '1', 'admin', DEFAULT, NULL, NULL);
A141: DEFAULT | B141: 013 | C141: Dirección Tipo | D141: 3 | E141: 3 | F141: Calle | G141: Calle | H141: NULL | I141: NULL | J141: 1 | K141: 1 | L141: admin | M141: DEFAULT | N141: NULL | O141: NULL | P141: =SUBSTITUTE(SUBSTITUTE(SUBSTITUTE(SUBSTITUTE(SUBSTITUTE(SUBSTITUTE(SUBSTITUTE(SUBSTITUTE(SUBSTITUTE(SUBSTITUTE(SUBSTITUTE(INSERT!$B$3,DATA_SOLICITUD!$B$1,IF(B141="NULL",B141,CONCATENATE("'",B141,"'"))),DATA_SOLICITUD!$C$1,IF(C141="NULL",C141,CONCATENATE("'",C141,"'"))),DATA_SOLICITUD!$D$1,IF(D141="NULL",D141,CONCATENATE("'",D141,"'"))),DATA_SOLICITUD!$E$1,IF(E141="NULL",E141,CONCATENATE("'",E141,"'"))),DATA_SOLICITUD!$F$1,IF(F141="NULL",F141,CONCATENATE("'",F141,"'"))),DATA_SOLICITUD!$G$1,IF(G141="NULL",G141,CONCATENATE("'",G141,"'"))),DATA_SOLICITUD!$H$1,IF(H141="NULL",H141,CONCATENATE("'",H141,"'"))),DATA_SOLICITUD!$I$1,IF(I141="NULL",I141,CONCATENATE("'",I141,"'"))),DATA_SOLICITUD!$J$1,IF(J141="NULL",J141,CONCATENATE("'",J141,"'"))),DATA_SOLICITUD!$K$1,IF(K141="NULL",K141,CONCATENATE("'",K141,"'"))),DATA_SOLICITUD!$L$1,IF(L141="NULL",L141,CONCATENATE("'",L141,"'"))) -> INSERT INTO `multitabla` (`id_multitabla`, `codigo_tabla`, `nombre_tabla`, `codigo`, `orden`, `valor`, `valor_aux`, `valor_crm`, `estado`, `estado_tabla`, `usuario_crea`, `fecha_crea`, `usuario_modif`, `fecha_modif`) VALUES (DEFAULT, '013', 'Dirección Tipo', '3', '3', 'Calle', 'Calle', NULL, '1', '1', 'admin', DEFAULT, NULL, NULL);
A142: DEFAULT | B142: 013 | C142: Dirección Tipo | D142: 4 | E142: 4 | F142: Pasaje | G142: Pasaje | H142: NULL | I142: NULL | J142: 1 | K142: 1 | L142: admin | M142: DEFAULT | N142: NULL | O142: NULL | P142: =SUBSTITUTE(SUBSTITUTE(SUBSTITUTE(SUBSTITUTE(SUBSTITUTE(SUBSTITUTE(SUBSTITUTE(SUBSTITUTE(SUBSTITUTE(SUBSTITUTE(SUBSTITUTE(INSERT!$B$3,DATA_SOLICITUD!$B$1,IF(B142="NULL",B142,CONCATENATE("'",B142,"'"))),DATA_SOLICITUD!$C$1,IF(C142="NULL",C142,CONCATENATE("'",C142,"'"))),DATA_SOLICITUD!$D$1,IF(D142="NULL",D142,CONCATENATE("'",D142,"'"))),DATA_SOLICITUD!$E$1,IF(E142="NULL",E142,CONCATENATE("'",E142,"'"))),DATA_SOLICITUD!$F$1,IF(F142="NULL",F142,CONCATENATE("'",F142,"'"))),DATA_SOLICITUD!$G$1,IF(G142="NULL",G142,CONCATENATE("'",G142,"'"))),DATA_SOLICITUD!$H$1,IF(H142="NULL",H142,CONCATENATE("'",H142,"'"))),DATA_SOLICITUD!$I$1,IF(I142="NULL",I142,CONCATENATE("'",I142,"'"))),DATA_SOLICITUD!$J$1,IF(J142="NULL",J142,CONCATENATE("'",J142,"'"))),DATA_SOLICITUD!$K$1,IF(K142="NULL",K142,CONCATENATE("'",K142,"'"))),DATA_SOLICITUD!$L$1,IF(L142="NULL",L142,CONCATENATE("'",L142,"'"))) -> INSERT INTO `multitabla` (`id_multitabla`, `codigo_tabla`, `nombre_tabla`, `codigo`, `orden`, `valor`, `valor_aux`, `valor_crm`, `estado`, `estado_tabla`, `usuario_crea`, `fecha_crea`, `usuario_modif`, `fecha_modif`) VALUES (DEFAULT, '013', 'Dirección Tipo', '4', '4', 'Pasaje', 'Pasaje', NULL, '1', '1', 'admin', DEFAULT, NULL, NULL);
A143: DEFAULT | B143: 013 | C143: Dirección Tipo | D143: 5 | E143: 5 | F143: Sin vía | H143: NULL | I143: NULL | J143: 1 | K143: 1 | L143: admin | M143: DEFAULT | N143: NULL | O143: NULL | P143: =SUBSTITUTE(SUBSTITUTE(SUBSTITUTE(SUBSTITUTE(SUBSTITUTE(SUBSTITUTE(SUBSTITUTE(SUBSTITUTE(SUBSTITUTE(SUBSTITUTE(SUBSTITUTE(INSERT!$B$3,DATA_SOLICITUD!$B$1,IF(B143="NULL",B143,CONCATENATE("'",B143,"'"))),DATA_SOLICITUD!$C$1,IF(C143="NULL",C143,CONCATENATE("'",C143,"'"))),DATA_SOLICITUD!$D$1,IF(D143="NULL",D143,CONCATENATE("'",D143,"'"))),DATA_SOLICITUD!$E$1,IF(E143="NULL",E143,CONCATENATE("'",E143,"'"))),DATA_SOLICITUD!$F$1,IF(F143="NULL",F143,CONCATENATE("'",F143,"'"))),DATA_SOLICITUD!$G$1,IF(G143="NULL",G143,CONCATENATE("'",G143,"'"))),DATA_SOLICITUD!$H$1,IF(H143="NULL",H143,CONCATENATE("'",H143,"'"))),DATA_SOLICITUD!$I$1,IF(I143="NULL",I143,CONCATENATE("'",I143,"'"))),DATA_SOLICITUD!$J$1,IF(J143="NULL",J143,CONCATENATE("'",J143,"'"))),DATA_SOLICITUD!$K$1,IF(K143="NULL",K143,CONCATENATE("'",K143,"'"))),DATA_SOLICITUD!$L$1,IF(L143="NULL",L143,CONCATENATE("'",L143,"'"))) -> INSERT INTO `multitabla` (`id_multitabla`, `codigo_tabla`, `nombre_tabla`, `codigo`, `orden`, `valor`, `valor_aux`, `valor_crm`, `estado`, `estado_tabla`, `usuario_crea`, `fecha_crea`, `usuario_modif`, `fecha_modif`) VALUES (DEFAULT, '013', 'Dirección Tipo', '5', '5', 'Sin vía', '', NULL, '1', '1', 'admin', DEFAULT, NULL, NULL);
A144: DEFAULT | B144: 014 | C144: Moneda | D144: NULL | E144: NULL | F144: NULL | G144: NULL | H144: NULL | I144: NULL | J144: NULL | K144: 1 | L144: admin | M144: DEFAULT | N144: NULL | O144: NULL | P144: =SUBSTITUTE(SUBSTITUTE(SUBSTITUTE(SUBSTITUTE(SUBSTITUTE(SUBSTITUTE(SUBSTITUTE(SUBSTITUTE(SUBSTITUTE(SUBSTITUTE(SUBSTITUTE(INSERT!$B$3,DATA_SOLICITUD!$B$1,IF(B144="NULL",B144,CONCATENATE("'",B144,"'"))),DATA_SOLICITUD!$C$1,IF(C144="NULL",C144,CONCATENATE("'",C144,"'"))),DATA_SOLICITUD!$D$1,IF(D144="NULL",D144,CONCATENATE("'",D144,"'"))),DATA_SOLICITUD!$E$1,IF(E144="NULL",E144,CONCATENATE("'",E144,"'"))),DATA_SOLICITUD!$F$1,IF(F144="NULL",F144,CONCATENATE("'",F144,"'"))),DATA_SOLICITUD!$G$1,IF(G144="NULL",G144,CONCATENATE("'",G144,"'"))),DATA_SOLICITUD!$H$1,IF(H144="NULL",H144,CONCATENATE("'",H144,"'"))),DATA_SOLICITUD!$I$1,IF(I144="NULL",I144,CONCATENATE("'",I144,"'"))),DATA_SOLICITUD!$J$1,IF(J144="NULL",J144,CONCATENATE("'",J144,"'"))),DATA_SOLICITUD!$K$1,IF(K144="NULL",K144,CONCATENATE("'",K144,"'"))),DATA_SOLICITUD!$L$1,IF(L144="NULL",L144,CONCATENATE("'",L144,"'"))) -> INSERT INTO `multitabla` (`id_multitabla`, `codigo_tabla`, `nombre_tabla`, `codigo`, `orden`, `valor`, `valor_aux`, `valor_crm`, `estado`, `estado_tabla`, `usuario_crea`, `fecha_crea`, `usuario_modif`, `fecha_modif`) VALUES (DEFAULT, '014', 'Moneda', NULL, NULL, NULL, NULL, NULL, NULL, '1', 'admin', DEFAULT, NULL, NULL);
A145: DEFAULT | B145: 014 | C145: Moneda | D145: 1 | E145: 1 | F145: Soles | G145: Soles | H145: S/. | I145: NULL | J145: 1 | K145: 1 | L145: admin | M145: DEFAULT | N145: NULL | O145: NULL | P145: =SUBSTITUTE(SUBSTITUTE(SUBSTITUTE(SUBSTITUTE(SUBSTITUTE(SUBSTITUTE(SUBSTITUTE(SUBSTITUTE(SUBSTITUTE(SUBSTITUTE(SUBSTITUTE(INSERT!$B$3,DATA_SOLICITUD!$B$1,IF(B145="NULL",B145,CONCATENATE("'",B145,"'"))),DATA_SOLICITUD!$C$1,IF(C145="NULL",C145,CONCATENATE("'",C145,"'"))),DATA_SOLICITUD!$D$1,IF(D145="NULL",D145,CONCATENATE("'",D145,"'"))),DATA_SOLICITUD!$E$1,IF(E145="NULL",E145,CONCATENATE("'",E145,"'"))),DATA_SOLICITUD!$F$1,IF(F145="NULL",F145,CONCATENATE("'",F145,"'"))),DATA_SOLICITUD!$G$1,IF(G145="NULL",G145,CONCATENATE("'",G145,"'"))),DATA_SOLICITUD!$H$1,IF(H145="NULL",H145,CONCATENATE("'",H145,"'"))),DATA_SOLICITUD!$I$1,IF(I145="NULL",I145,CONCATENATE("'",I145,"'"))),DATA_SOLICITUD!$J$1,IF(J145="NULL",J145,CONCATENATE("'",J145,"'"))),DATA_SOLICITUD!$K$1,IF(K145="NULL",K145,CONCATENATE("'",K145,"'"))),DATA_SOLICITUD!$L$1,IF(L145="NULL",L145,CONCATENATE("'",L145,"'"))) -> INSERT INTO `multitabla` (`id_multitabla`, `codigo_tabla`, `nombre_tabla`, `codigo`, `orden`, `valor`, `valor_aux`, `valor_crm`, `estado`, `estado_tabla`, `usuario_crea`, `fecha_crea`, `usuario_modif`, `fecha_modif`) VALUES (DEFAULT, '014', 'Moneda', '1', '1', 'Soles', 'Soles', 'S/.', '1', '1', 'admin', DEFAULT, NULL, NULL);
A146: DEFAULT | B146: 014 | C146: Moneda | D146: 2 | E146: 2 | F146: Dólares | G146: Dolares | H146: $ | I146: NULL | J146: 1 | K146: 1 | L146: admin | M146: DEFAULT | N146: NULL | O146: NULL | P146: =SUBSTITUTE(SUBSTITUTE(SUBSTITUTE(SUBSTITUTE(SUBSTITUTE(SUBSTITUTE(SUBSTITUTE(SUBSTITUTE(SUBSTITUTE(SUBSTITUTE(SUBSTITUTE(INSERT!$B$3,DATA_SOLICITUD!$B$1,IF(B146="NULL",B146,CONCATENATE("'",B146,"'"))),DATA_SOLICITUD!$C$1,IF(C146="NULL",C146,CONCATENATE("'",C146,"'"))),DATA_SOLICITUD!$D$1,IF(D146="NULL",D146,CONCATENATE("'",D146,"'"))),DATA_SOLICITUD!$E$1,IF(E146="NULL",E146,CONCATENATE("'",E146,"'"))),DATA_SOLICITUD!$F$1,IF(F146="NULL",F146,CONCATENATE("'",F146,"'"))),DATA_SOLICITUD!$G$1,IF(G146="NULL",G146,CONCATENATE("'",G146,"'"))),DATA_SOLICITUD!$H$1,IF(H146="NULL",H146,CONCATENATE("'",H146,"'"))),DATA_SOLICITUD!$I$1,IF(I146="NULL",I146,CONCATENATE("'",I146,"'"))),DATA_SOLICITUD!$J$1,IF(J146="NULL",J146,CONCATENATE("'",J146,"'"))),DATA_SOLICITUD!$K$1,IF(K146="NULL",K146,CONCATENATE("'",K146,"'"))),DATA_SOLICITUD!$L$1,IF(L146="NULL",L146,CONCATENATE("'",L146,"'"))) -> INSERT INTO `multitabla` (`id_multitabla`, `codigo_tabla`, `nombre_tabla`, `codigo`, `orden`, `valor`, `valor_aux`, `valor_crm`, `estado`, `estado_tabla`, `usuario_crea`, `fecha_crea`, `usuario_modif`, `fecha_modif`) VALUES (DEFAULT, '014', 'Moneda', '2', '2', 'Dólares', 'Dolares', '$', '1', '1', 'admin', DEFAULT, NULL, NULL);
A147: DEFAULT | B147: 015 | C147: Tipo Producto | D147: NULL | E147: NULL | F147: NULL | G147: NULL | H147: NULL | I147: NULL | J147: NULL | K147: 1 | L147: admin | M147: DEFAULT | N147: NULL | O147: NULL | P147: =SUBSTITUTE(SUBSTITUTE(SUBSTITUTE(SUBSTITUTE(SUBSTITUTE(SUBSTITUTE(SUBSTITUTE(SUBSTITUTE(SUBSTITUTE(SUBSTITUTE(SUBSTITUTE(INSERT!$B$3,DATA_SOLICITUD!$B$1,IF(B147="NULL",B147,CONCATENATE("'",B147,"'"))),DATA_SOLICITUD!$C$1,IF(C147="NULL",C147,CONCATENATE("'",C147,"'"))),DATA_SOLICITUD!$D$1,IF(D147="NULL",D147,CONCATENATE("'",D147,"'"))),DATA_SOLICITUD!$E$1,IF(E147="NULL",E147,CONCATENATE("'",E147,"'"))),DATA_SOLICITUD!$F$1,IF(F147="NULL",F147,CONCATENATE("'",F147,"'"))),DATA_SOLICITUD!$G$1,IF(G147="NULL",G147,CONCATENATE("'",G147,"'"))),DATA_SOLICITUD!$H$1,IF(H147="NULL",H147,CONCATENATE("'",H147,"'"))),DATA_SOLICITUD!$I$1,IF(I147="NULL",I147,CONCATENATE("'",I147,"'"))),DATA_SOLICITUD!$J$1,IF(J147="NULL",J147,CONCATENATE("'",J147,"'"))),DATA_SOLICITUD!$K$1,IF(K147="NULL",K147,CONCATENATE("'",K147,"'"))),DATA_SOLICITUD!$L$1,IF(L147="NULL",L147,CONCATENATE("'",L147,"'"))) -> INSERT INTO `multitabla` (`id_multitabla`, `codigo_tabla`, `nombre_tabla`, `codigo`, `orden`, `valor`, `valor_aux`, `valor_crm`, `estado`, `estado_tabla`, `usuario_crea`, `fecha_crea`, `usuario_modif`, `fecha_modif`) VALUES (DEFAULT, '015', 'Tipo Producto', NULL, NULL, NULL, NULL, NULL, NULL, '1', 'admin', DEFAULT, NULL, NULL);
A148: DEFAULT | B148: 015 | C148: Tipo Producto | D148: 1 | E148: 1 | F148: Plan Garantizado | G148: NULL | H148: NULL | I148: NULL | J148: 1 | K148: 1 | L148: admin | M148: DEFAULT | N148: NULL | O148: NULL | P148: =SUBSTITUTE(SUBSTITUTE(SUBSTITUTE(SUBSTITUTE(SUBSTITUTE(SUBSTITUTE(SUBSTITUTE(SUBSTITUTE(SUBSTITUTE(SUBSTITUTE(SUBSTITUTE(INSERT!$B$3,DATA_SOLICITUD!$B$1,IF(B148="NULL",B148,CONCATENATE("'",B148,"'"))),DATA_SOLICITUD!$C$1,IF(C148="NULL",C148,CONCATENATE("'",C148,"'"))),DATA_SOLICITUD!$D$1,IF(D148="NULL",D148,CONCATENATE("'",D148,"'"))),DATA_SOLICITUD!$E$1,IF(E148="NULL",E148,CONCATENATE("'",E148,"'"))),DATA_SOLICITUD!$F$1,IF(F148="NULL",F148,CONCATENATE("'",F148,"'"))),DATA_SOLICITUD!$G$1,IF(G148="NULL",G148,CONCATENATE("'",G148,"'"))),DATA_SOLICITUD!$H$1,IF(H148="NULL",H148,CONCATENATE("'",H148,"'"))),DATA_SOLICITUD!$I$1,IF(I148="NULL",I148,CONCATENATE("'",I148,"'"))),DATA_SOLICITUD!$J$1,IF(J148="NULL",J148,CONCATENATE("'",J148,"'"))),DATA_SOLICITUD!$K$1,IF(K148="NULL",K148,CONCATENATE("'",K148,"'"))),DATA_SOLICITUD!$L$1,IF(L148="NULL",L148,CONCATENATE("'",L148,"'"))) -> INSERT INTO `multitabla` (`id_multitabla`, `codigo_tabla`, `nombre_tabla`, `codigo`, `orden`, `valor`, `valor_aux`, `valor_crm`, `estado`, `estado_tabla`, `usuario_crea`, `fecha_crea`, `usuario_modif`, `fecha_modif`) VALUES (DEFAULT, '015', 'Tipo Producto', '1', '1', 'Plan Garantizado', NULL, NULL, '1', '1', 'admin', DEFAULT, NULL, NULL);
A149: DEFAULT | B149: 016 | C149: Frecuencia | D149: NULL | E149: NULL | F149: NULL | G149: NULL | H149: NULL | I149: NULL | J149: NULL | K149: 1 | L149: admin | M149: DEFAULT | N149: NULL | O149: NULL | P149: =SUBSTITUTE(SUBSTITUTE(SUBSTITUTE(SUBSTITUTE(SUBSTITUTE(SUBSTITUTE(SUBSTITUTE(SUBSTITUTE(SUBSTITUTE(SUBSTITUTE(SUBSTITUTE(INSERT!$B$3,DATA_SOLICITUD!$B$1,IF(B149="NULL",B149,CONCATENATE("'",B149,"'"))),DATA_SOLICITUD!$C$1,IF(C149="NULL",C149,CONCATENATE("'",C149,"'"))),DATA_SOLICITUD!$D$1,IF(D149="NULL",D149,CONCATENATE("'",D149,"'"))),DATA_SOLICITUD!$E$1,IF(E149="NULL",E149,CONCATENATE("'",E149,"'"))),DATA_SOLICITUD!$F$1,IF(F149="NULL",F149,CONCATENATE("'",F149,"'"))),DATA_SOLICITUD!$G$1,IF(G149="NULL",G149,CONCATENATE("'",G149,"'"))),DATA_SOLICITUD!$H$1,IF(H149="NULL",H149,CONCATENATE("'",H149,"'"))),DATA_SOLICITUD!$I$1,IF(I149="NULL",I149,CONCATENATE("'",I149,"'"))),DATA_SOLICITUD!$J$1,IF(J149="NULL",J149,CONCATENATE("'",J149,"'"))),DATA_SOLICITUD!$K$1,IF(K149="NULL",K149,CONCATENATE("'",K149,"'"))),DATA_SOLICITUD!$L$1,IF(L149="NULL",L149,CONCATENATE("'",L149,"'"))) -> INSERT INTO `multitabla` (`id_multitabla`, `codigo_tabla`, `nombre_tabla`, `codigo`, `orden`, `valor`, `valor_aux`, `valor_crm`, `estado`, `estado_tabla`, `usuario_crea`, `fecha_crea`, `usuario_modif`, `fecha_modif`) VALUES (DEFAULT, '016', 'Frecuencia', NULL, NULL, NULL, NULL, NULL, NULL, '1', 'admin', DEFAULT, NULL, NULL);
A150: DEFAULT | B150: 016 | C150: Frecuencia | D150: 1 | E150: 1 | F150: Mensual | G150: Mensual | H150: NULL | I150: NULL | J150: 1 | K150: 1 | L150: admin | M150: DEFAULT | N150: NULL | O150: NULL | P150: =SUBSTITUTE(SUBSTITUTE(SUBSTITUTE(SUBSTITUTE(SUBSTITUTE(SUBSTITUTE(SUBSTITUTE(SUBSTITUTE(SUBSTITUTE(SUBSTITUTE(SUBSTITUTE(INSERT!$B$3,DATA_SOLICITUD!$B$1,IF(B150="NULL",B150,CONCATENATE("'",B150,"'"))),DATA_SOLICITUD!$C$1,IF(C150="NULL",C150,CONCATENATE("'",C150,"'"))),DATA_SOLICITUD!$D$1,IF(D150="NULL",D150,CONCATENATE("'",D150,"'"))),DATA_SOLICITUD!$E$1,IF(E150="NULL",E150,CONCATENATE("'",E150,"'"))),DATA_SOLICITUD!$F$1,IF(F150="NULL",F150,CONCATENATE("'",F150,"'"))),DATA_SOLICITUD!$G$1,IF(G150="NULL",G150,CONCATENATE("'",G150,"'"))),DATA_SOLICITUD!$H$1,IF(H150="NULL",H150,CONCATENATE("'",H150,"'"))),DATA_SOLICITUD!$I$1,IF(I150="NULL",I150,CONCATENATE("'",I150,"'"))),DATA_SOLICITUD!$J$1,IF(J150="NULL",J150,CONCATENATE("'",J150,"'"))),DATA_SOLICITUD!$K$1,IF(K150="NULL",K150,CONCATENATE("'",K150,"'"))),DATA_SOLICITUD!$L$1,IF(L150="NULL",L150,CONCATENATE("'",L150,"'"))) -> INSERT INTO `multitabla` (`id_multitabla`, `codigo_tabla`, `nombre_tabla`, `codigo`, `orden`, `valor`, `valor_aux`, `valor_crm`, `estado`, `estado_tabla`, `usuario_crea`, `fecha_crea`, `usuario_modif`, `fecha_modif`) VALUES (DEFAULT, '016', 'Frecuencia', '1', '1', 'Mensual', 'Mensual', NULL, '1', '1', 'admin', DEFAULT, NULL, NULL);
A151: DEFAULT | B151: 016 | C151: Frecuencia | D151: 2 | E151: 2 | F151: Trimestral | G151: Trimestral | H151: NULL | I151: NULL | J151: 1 | K151: 1 | L151: admin | M151: DEFAULT | N151: NULL | O151: NULL | P151: =SUBSTITUTE(SUBSTITUTE(SUBSTITUTE(SUBSTITUTE(SUBSTITUTE(SUBSTITUTE(SUBSTITUTE(SUBSTITUTE(SUBSTITUTE(SUBSTITUTE(SUBSTITUTE(INSERT!$B$3,DATA_SOLICITUD!$B$1,IF(B151="NULL",B151,CONCATENATE("'",B151,"'"))),DATA_SOLICITUD!$C$1,IF(C151="NULL",C151,CONCATENATE("'",C151,"'"))),DATA_SOLICITUD!$D$1,IF(D151="NULL",D151,CONCATENATE("'",D151,"'"))),DATA_SOLICITUD!$E$1,IF(E151="NULL",E151,CONCATENATE("'",E151,"'"))),DATA_SOLICITUD!$F$1,IF(F151="NULL",F151,CONCATENATE("'",F151,"'"))),DATA_SOLICITUD!$G$1,IF(G151="NULL",G151,CONCATENATE("'",G151,"'"))),DATA_SOLICITUD!$H$1,IF(H151="NULL",H151,CONCATENATE("'",H151,"'"))),DATA_SOLICITUD!$I$1,IF(I151="NULL",I151,CONCATENATE("'",I151,"'"))),DATA_SOLICITUD!$J$1,IF(J151="NULL",J151,CONCATENATE("'",J151,"'"))),DATA_SOLICITUD!$K$1,IF(K151="NULL",K151,CONCATENATE("'",K151,"'"))),DATA_SOLICITUD!$L$1,IF(L151="NULL",L151,CONCATENATE("'",L151,"'"))) -> INSERT INTO `multitabla` (`id_multitabla`, `codigo_tabla`, `nombre_tabla`, `codigo`, `orden`, `valor`, `valor_aux`, `valor_crm`, `estado`, `estado_tabla`, `usuario_crea`, `fecha_crea`, `usuario_modif`, `fecha_modif`) VALUES (DEFAULT, '016', 'Frecuencia', '2', '2', 'Trimestral', 'Trimestral', NULL, '1', '1', 'admin', DEFAULT, NULL, NULL);
A152: DEFAULT | B152: 016 | C152: Frecuencia | D152: 3 | E152: 3 | F152: Semestral | G152: Semestral | H152: NULL | I152: NULL | J152: 1 | K152: 1 | L152: admin | M152: DEFAULT | N152: NULL | O152: NULL | P152: =SUBSTITUTE(SUBSTITUTE(SUBSTITUTE(SUBSTITUTE(SUBSTITUTE(SUBSTITUTE(SUBSTITUTE(SUBSTITUTE(SUBSTITUTE(SUBSTITUTE(SUBSTITUTE(INSERT!$B$3,DATA_SOLICITUD!$B$1,IF(B152="NULL",B152,CONCATENATE("'",B152,"'"))),DATA_SOLICITUD!$C$1,IF(C152="NULL",C152,CONCATENATE("'",C152,"'"))),DATA_SOLICITUD!$D$1,IF(D152="NULL",D152,CONCATENATE("'",D152,"'"))),DATA_SOLICITUD!$E$1,IF(E152="NULL",E152,CONCATENATE("'",E152,"'"))),DATA_SOLICITUD!$F$1,IF(F152="NULL",F152,CONCATENATE("'",F152,"'"))),DATA_SOLICITUD!$G$1,IF(G152="NULL",G152,CONCATENATE("'",G152,"'"))),DATA_SOLICITUD!$H$1,IF(H152="NULL",H152,CONCATENATE("'",H152,"'"))),DATA_SOLICITUD!$I$1,IF(I152="NULL",I152,CONCATENATE("'",I152,"'"))),DATA_SOLICITUD!$J$1,IF(J152="NULL",J152,CONCATENATE("'",J152,"'"))),DATA_SOLICITUD!$K$1,IF(K152="NULL",K152,CONCATENATE("'",K152,"'"))),DATA_SOLICITUD!$L$1,IF(L152="NULL",L152,CONCATENATE("'",L152,"'"))) -> INSERT INTO `multitabla` (`id_multitabla`, `codigo_tabla`, `nombre_tabla`, `codigo`, `orden`, `valor`, `valor_aux`, `valor_crm`, `estado`, `estado_tabla`, `usuario_crea`, `fecha_crea`, `usuario_modif`, `fecha_modif`) VALUES (DEFAULT, '016', 'Frecuencia', '3', '3', 'Semestral', 'Semestral', NULL, '1', '1', 'admin', DEFAULT, NULL, NULL);
A153: DEFAULT | B153: 016 | C153: Frecuencia | D153: 4 | E153: 4 | F153: Anual | G153: Anual | H153: NULL | I153: NULL | J153: 1 | K153: 1 | L153: admin | M153: DEFAULT | N153: NULL | O153: NULL | P153: =SUBSTITUTE(SUBSTITUTE(SUBSTITUTE(SUBSTITUTE(SUBSTITUTE(SUBSTITUTE(SUBSTITUTE(SUBSTITUTE(SUBSTITUTE(SUBSTITUTE(SUBSTITUTE(INSERT!$B$3,DATA_SOLICITUD!$B$1,IF(B153="NULL",B153,CONCATENATE("'",B153,"'"))),DATA_SOLICITUD!$C$1,IF(C153="NULL",C153,CONCATENATE("'",C153,"'"))),DATA_SOLICITUD!$D$1,IF(D153="NULL",D153,CONCATENATE("'",D153,"'"))),DATA_SOLICITUD!$E$1,IF(E153="NULL",E153,CONCATENATE("'",E153,"'"))),DATA_SOLICITUD!$F$1,IF(F153="NULL",F153,CONCATENATE("'",F153,"'"))),DATA_SOLICITUD!$G$1,IF(G153="NULL",G153,CONCATENATE("'",G153,"'"))),DATA_SOLICITUD!$H$1,IF(H153="NULL",H153,CONCATENATE("'",H153,"'"))),DATA_SOLICITUD!$I$1,IF(I153="NULL",I153,CONCATENATE("'",I153,"'"))),DATA_SOLICITUD!$J$1,IF(J153="NULL",J153,CONCATENATE("'",J153,"'"))),DATA_SOLICITUD!$K$1,IF(K153="NULL",K153,CONCATENATE("'",K153,"'"))),DATA_SOLICITUD!$L$1,IF(L153="NULL",L153,CONCATENATE("'",L153,"'"))) -> INSERT INTO `multitabla` (`id_multitabla`, `codigo_tabla`, `nombre_tabla`, `codigo`, `orden`, `valor`, `valor_aux`, `valor_crm`, `estado`, `estado_tabla`, `usuario_crea`, `fecha_crea`, `usuario_modif`, `fecha_modif`) VALUES (DEFAULT, '016', 'Frecuencia', '4', '4', 'Anual', 'Anual', NULL, '1', '1', 'admin', DEFAULT, NULL, NULL);
A154: DEFAULT | B154: 016 | C154: Frecuencia | D154: 5 | E154: 5 | F154: Única | G154: NULL | H154: NULL | I154: NULL | J154: 1 | K154: 1 | L154: admin | M154: DEFAULT | N154: NULL | O154: NULL | P154: =SUBSTITUTE(SUBSTITUTE(SUBSTITUTE(SUBSTITUTE(SUBSTITUTE(SUBSTITUTE(SUBSTITUTE(SUBSTITUTE(SUBSTITUTE(SUBSTITUTE(SUBSTITUTE(INSERT!$B$3,DATA_SOLICITUD!$B$1,IF(B154="NULL",B154,CONCATENATE("'",B154,"'"))),DATA_SOLICITUD!$C$1,IF(C154="NULL",C154,CONCATENATE("'",C154,"'"))),DATA_SOLICITUD!$D$1,IF(D154="NULL",D154,CONCATENATE("'",D154,"'"))),DATA_SOLICITUD!$E$1,IF(E154="NULL",E154,CONCATENATE("'",E154,"'"))),DATA_SOLICITUD!$F$1,IF(F154="NULL",F154,CONCATENATE("'",F154,"'"))),DATA_SOLICITUD!$G$1,IF(G154="NULL",G154,CONCATENATE("'",G154,"'"))),DATA_SOLICITUD!$H$1,IF(H154="NULL",H154,CONCATENATE("'",H154,"'"))),DATA_SOLICITUD!$I$1,IF(I154="NULL",I154,CONCATENATE("'",I154,"'"))),DATA_SOLICITUD!$J$1,IF(J154="NULL",J154,CONCATENATE("'",J154,"'"))),DATA_SOLICITUD!$K$1,IF(K154="NULL",K154,CONCATENATE("'",K154,"'"))),DATA_SOLICITUD!$L$1,IF(L154="NULL",L154,CONCATENATE("'",L154,"'"))) -> INSERT INTO `multitabla` (`id_multitabla`, `codigo_tabla`, `nombre_tabla`, `codigo`, `orden`, `valor`, `valor_aux`, `valor_crm`, `estado`, `estado_tabla`, `usuario_crea`, `fecha_crea`, `usuario_modif`, `fecha_modif`) VALUES (DEFAULT, '016', 'Frecuencia', '5', '5', 'Única', NULL, NULL, '1', '1', 'admin', DEFAULT, NULL, NULL);
A155: DEFAULT | B155: 017 | C155: Tipo Cuota | D155: NULL | E155: NULL | F155: NULL | G155: NULL | H155: NULL | I155: NULL | J155: NULL | K155: 1 | L155: admin | M155: DEFAULT | N155: NULL | O155: NULL | P155: =SUBSTITUTE(SUBSTITUTE(SUBSTITUTE(SUBSTITUTE(SUBSTITUTE(SUBSTITUTE(SUBSTITUTE(SUBSTITUTE(SUBSTITUTE(SUBSTITUTE(SUBSTITUTE(INSERT!$B$3,DATA_SOLICITUD!$B$1,IF(B155="NULL",B155,CONCATENATE("'",B155,"'"))),DATA_SOLICITUD!$C$1,IF(C155="NULL",C155,CONCATENATE("'",C155,"'"))),DATA_SOLICITUD!$D$1,IF(D155="NULL",D155,CONCATENATE("'",D155,"'"))),DATA_SOLICITUD!$E$1,IF(E155="NULL",E155,CONCATENATE("'",E155,"'"))),DATA_SOLICITUD!$F$1,IF(F155="NULL",F155,CONCATENATE("'",F155,"'"))),DATA_SOLICITUD!$G$1,IF(G155="NULL",G155,CONCATENATE("'",G155,"'"))),DATA_SOLICITUD!$H$1,IF(H155="NULL",H155,CONCATENATE("'",H155,"'"))),DATA_SOLICITUD!$I$1,IF(I155="NULL",I155,CONCATENATE("'",I155,"'"))),DATA_SOLICITUD!$J$1,IF(J155="NULL",J155,CONCATENATE("'",J155,"'"))),DATA_SOLICITUD!$K$1,IF(K155="NULL",K155,CONCATENATE("'",K155,"'"))),DATA_SOLICITUD!$L$1,IF(L155="NULL",L155,CONCATENATE("'",L155,"'"))) -> INSERT INTO `multitabla` (`id_multitabla`, `codigo_tabla`, `nombre_tabla`, `codigo`, `orden`, `valor`, `valor_aux`, `valor_crm`, `estado`, `estado_tabla`, `usuario_crea`, `fecha_crea`, `usuario_modif`, `fecha_modif`) VALUES (DEFAULT, '017', 'Tipo Cuota', NULL, NULL, NULL, NULL, NULL, NULL, '1', 'admin', DEFAULT, NULL, NULL);
... A201: DEFAULT | B201: 026 | C201: Estado Solicitud Bandeja | D201: NULL | E201: NULL | F201: NULL | G201: NULL | H201: NULL | I201: NULL | J201: NULL | K201: 1 | L201: admin | M201: DEFAULT | N201: NULL | O201: NULL | P201: =SUBSTITUTE(SUBSTITUTE(SUBSTITUTE(SUBSTITUTE(SUBSTITUTE(SUBSTITUTE(SUBSTITUTE(SUBSTITUTE(SUBSTITUTE(SUBSTITUTE(SUBSTITUTE(INSERT!$B$3,DATA_SOLICITUD!$B$1,IF(B201="NULL",B201,CONCATENATE("'",B201,"'"))),DATA_SOLICITUD!$C$1,IF(C201="NULL",C201,CONCATENATE("'",C201,"'"))),DATA_SOLICITUD!$D$1,IF(D201="NULL",D201,CONCATENATE("'",D201,"'"))),DATA_SOLICITUD!$E$1,IF(E201="NULL",E201,CONCATENATE("'",E201,"'"))),DATA_SOLICITUD!$F$1,IF(F201="NULL",F201,CONCATENATE("'",F201,"'"))),DATA_SOLICITUD!$G$1,IF(G201="NULL",G201,CONCATENATE("'",G201,"'"))),DATA_SOLICITUD!$H$1,IF(H201="NULL",H201,CONCATENATE("'",H201,"'"))),DATA_SOLICITUD!$I$1,IF(I201="NULL",I201,CONCATENATE("'",I201,"'"))),DATA_SOLICITUD!$J$1,IF(J201="NULL",J201,CONCATENATE("'",J201,"'"))),DATA_SOLICITUD!$K$1,IF(K201="NULL",K201,CONCATENATE("'",K201,"'"))),DATA_SOLICITUD!$L$1,IF(L201="NULL",L201,CONCATENATE("'",L201,"'"))) -> INSERT INTO `multitabla` (`id_multitabla`, `codigo_tabla`, `nombre_tabla`, `codigo`, `orden`, `valor`, `valor_aux`, `valor_crm`, `estado`, `estado_tabla`, `usuario_crea`, `fecha_crea`, `usuario_modif`, `fecha_modif`) VALUES (DEFAULT, '026', 'Estado Solicitud Bandeja', NULL, NULL, NULL, NULL, NULL, NULL, '1', 'admin', DEFAULT, NULL, NULL);
A202: DEFAULT | B202: 026 | C202: Estado Solicitud Bandeja | D202: 4 | E202: 4 | F202: Por transmitir | G202: NULL | H202: NULL | I202: NULL | J202: 1 | K202: 1 | L202: admin | M202: DEFAULT | N202: NULL | O202: NULL | P202: =SUBSTITUTE(SUBSTITUTE(SUBSTITUTE(SUBSTITUTE(SUBSTITUTE(SUBSTITUTE(SUBSTITUTE(SUBSTITUTE(SUBSTITUTE(SUBSTITUTE(SUBSTITUTE(INSERT!$B$3,DATA_SOLICITUD!$B$1,IF(B202="NULL",B202,CONCATENATE("'",B202,"'"))),DATA_SOLICITUD!$C$1,IF(C202="NULL",C202,CONCATENATE("'",C202,"'"))),DATA_SOLICITUD!$D$1,IF(D202="NULL",D202,CONCATENATE("'",D202,"'"))),DATA_SOLICITUD!$E$1,IF(E202="NULL",E202,CONCATENATE("'",E202,"'"))),DATA_SOLICITUD!$F$1,IF(F202="NULL",F202,CONCATENATE("'",F202,"'"))),DATA_SOLICITUD!$G$1,IF(G202="NULL",G202,CONCATENATE("'",G202,"'"))),DATA_SOLICITUD!$H$1,IF(H202="NULL",H202,CONCATENATE("'",H202,"'"))),DATA_SOLICITUD!$I$1,IF(I202="NULL",I202,CONCATENATE("'",I202,"'"))),DATA_SOLICITUD!$J$1,IF(J202="NULL",J202,CONCATENATE("'",J202,"'"))),DATA_SOLICITUD!$K$1,IF(K202="NULL",K202,CONCATENATE("'",K202,"'"))),DATA_SOLICITUD!$L$1,IF(L202="NULL",L202,CONCATENATE("'",L202,"'"))) -> INSERT INTO `multitabla` (`id_multitabla`, `codigo_tabla`, `nombre_tabla`, `codigo`, `orden`, `valor`, `valor_aux`, `valor_crm`, `estado`, `estado_tabla`, `usuario_crea`, `fecha_crea`, `usuario_modif`, `fecha_modif`) VALUES (DEFAULT, '026', 'Estado Solicitud Bandeja', '4', '4', 'Por transmitir', NULL, NULL, '1', '1', 'admin', DEFAULT, NULL, NULL);
A203: DEFAULT | B203: 026 | C203: Estado Solicitud Bandeja | D203: 5 | E203: 5 | F203: Transmitido | G203: NULL | H203: NULL | I203: NULL | J203: 1 | K203: 1 | L203: admin | M203: DEFAULT | N203: NULL | O203: NULL | P203: =SUBSTITUTE(SUBSTITUTE(SUBSTITUTE(SUBSTITUTE(SUBSTITUTE(SUBSTITUTE(SUBSTITUTE(SUBSTITUTE(SUBSTITUTE(SUBSTITUTE(SUBSTITUTE(INSERT!$B$3,DATA_SOLICITUD!$B$1,IF(B203="NULL",B203,CONCATENATE("'",B203,"'"))),DATA_SOLICITUD!$C$1,IF(C203="NULL",C203,CONCATENATE("'",C203,"'"))),DATA_SOLICITUD!$D$1,IF(D203="NULL",D203,CONCATENATE("'",D203,"'"))),DATA_SOLICITUD!$E$1,IF(E203="NULL",E203,CONCATENATE("'",E203,"'"))),DATA_SOLICITUD!$F$1,IF(F203="NULL",F203,CONCATENATE("'",F203,"'"))),DATA_SOLICITUD!$G$1,IF(G203="NULL",G203,CONCATENATE("'",G203,"'"))),DATA_SOLICITUD!$H$1,IF(H203="NULL",H203,CONCATENATE("'",H203,"'"))),DATA_SOLICITUD!$I$1,IF(I203="NULL",I203,CONCATENATE("'",I203,"'"))),DATA_SOLICITUD!$J$1,IF(J203="NULL",J203,CONCATENATE("'",J203,"'"))),DATA_SOLICITUD!$K$1,IF(K203="NULL",K203,CONCATENATE("'",K203,"'"))),DATA_SOLICITUD!$L$1,IF(L203="NULL",L203,CONCATENATE("'",L203,"'"))) -> INSERT INTO `multitabla` (`id_multitabla`, `codigo_tabla`, `nombre_tabla`, `codigo`, `orden`, `valor`, `valor_aux`, `valor_crm`, `estado`, `estado_tabla`, `usuario_crea`, `fecha_crea`, `usuario_modif`, `fecha_modif`) VALUES (DEFAULT, '026', 'Estado Solicitud Bandeja', '5', '5', 'Transmitido', NULL, NULL, '1', '1', 'admin', DEFAULT, NULL, NULL);
A204: DEFAULT | B204: 026 | C204: Estado Solicitud Bandeja | D204: 6 | E204: 6 | F204: Emitido | G204: NULL | H204: NULL | I204: NULL | J204: 1 | K204: 1 | L204: admin | M204: DEFAULT | N204: NULL | O204: NULL | P204: =SUBSTITUTE(SUBSTITUTE(SUBSTITUTE(SUBSTITUTE(SUBSTITUTE(SUBSTITUTE(SUBSTITUTE(SUBSTITUTE(SUBSTITUTE(SUBSTITUTE(SUBSTITUTE(INSERT!$B$3,DATA_SOLICITUD!$B$1,IF(B204="NULL",B204,CONCATENATE("'",B204,"'"))),DATA_SOLICITUD!$C$1,IF(C204="NULL",C204,CONCATENATE("'",C204,"'"))),DATA_SOLICITUD!$D$1,IF(D204="NULL",D204,CONCATENATE("'",D204,"'"))),DATA_SOLICITUD!$E$1,IF(E204="NULL",E204,CONCATENATE("'",E204,"'"))),DATA_SOLICITUD!$F$1,IF(F204="NULL",F204,CONCATENATE("'",F204,"'"))),DATA_SOLICITUD!$G$1,IF(G204="NULL",G204,CONCATENATE("'",G204,"'"))),DATA_SOLICITUD!$H$1,IF(H204="NULL",H204,CONCATENATE("'",H204,"'"))),DATA_SOLICITUD!$I$1,IF(I204="NULL",I204,CONCATENATE("'",I204,"'"))),DATA_SOLICITUD!$J$1,IF(J204="NULL",J204,CONCATENATE("'",J204,"'"))),DATA_SOLICITUD!$K$1,IF(K204="NULL",K204,CONCATENATE("'",K204,"'"))),DATA_SOLICITUD!$L$1,IF(L204="NULL",L204,CONCATENATE("'",L204,"'"))) -> INSERT INTO `multitabla` (`id_multitabla`, `codigo_tabla`, `nombre_tabla`, `codigo`, `orden`, `valor`, `valor_aux`, `valor_crm`, `estado`, `estado_tabla`, `usuario_crea`, `fecha_crea`, `usuario_modif`, `fecha_modif`) VALUES (DEFAULT, '026', 'Estado Solicitud Bandeja', '6', '6', 'Emitido', NULL, NULL, '1', '1', 'admin', DEFAULT, NULL, NULL);
A205: DEFAULT | B205: 027 | C205: Departamentos | D205: NULL | E205: NULL | F205: NULL | G205: NULL | H205: NULL | I205: NULL | J205: NULL | K205: 1 | L205: admin | M205: DEFAULT | N205: NULL | O205: NULL | P205: =SUBSTITUTE(SUBSTITUTE(SUBSTITUTE(SUBSTITUTE(SUBSTITUTE(SUBSTITUTE(SUBSTITUTE(SUBSTITUTE(SUBSTITUTE(SUBSTITUTE(SUBSTITUTE(INSERT!$B$3,DATA_SOLICITUD!$B$1,IF(B205="NULL",B205,CONCATENATE("'",B205,"'"))),DATA_SOLICITUD!$C$1,IF(C205="NULL",C205,CONCATENATE("'",C205,"'"))),DATA_SOLICITUD!$D$1,IF(D205="NULL",D205,CONCATENATE("'",D205,"'"))),DATA_SOLICITUD!$E$1,IF(E205="NULL",E205,CONCATENATE("'",E205,"'"))),DATA_SOLICITUD!$F$1,IF(F205="NULL",F205,CONCATENATE("'",F205,"'"))),DATA_SOLICITUD!$G$1,IF(G205="NULL",G205,CONCATENATE("'",G205,"'"))),DATA_SOLICITUD!$H$1,IF(H205="NULL",H205,CONCATENATE("'",H205,"'"))),DATA_SOLICITUD!$I$1,IF(I205="NULL",I205,CONCATENATE("'",I205,"'"))),DATA_SOLICITUD!$J$1,IF(J205="NULL",J205,CONCATENATE("'",J205,"'"))),DATA_SOLICITUD!$K$1,IF(K205="NULL",K205,CONCATENATE("'",K205,"'"))),DATA_SOLICITUD!$L$1,IF(L205="NULL",L205,CONCATENATE("'",L205,"'"))) -> INSERT INTO `multitabla` (`id_multitabla`, `codigo_tabla`, `nombre_tabla`, `codigo`, `orden`, `valor`, `valor_aux`, `valor_crm`, `estado`, `estado_tabla`, `usuario_crea`, `fecha_crea`, `usuario_modif`, `fecha_modif`) VALUES (DEFAULT, '027', 'Departamentos', NULL, NULL, NULL, NULL, NULL, NULL, '1', 'admin', DEFAULT, NULL, NULL);
A206: DEFAULT | B206: 027 | C206: Departamentos | D206: 1 | E206: 1 | F206: AMAZONAS | G206: 01 | H206: 010000 | I206: NULL | J206: 1 | K206: 1 | L206: admin | M206: DEFAULT | N206: NULL | O206: NULL | P206: =SUBSTITUTE(SUBSTITUTE(SUBSTITUTE(SUBSTITUTE(SUBSTITUTE(SUBSTITUTE(SUBSTITUTE(SUBSTITUTE(SUBSTITUTE(SUBSTITUTE(SUBSTITUTE(INSERT!$B$3,DATA_SOLICITUD!$B$1,IF(B206="NULL",B206,CONCATENATE("'",B206,"'"))),DATA_SOLICITUD!$C$1,IF(C206="NULL",C206,CONCATENATE("'",C206,"'"))),DATA_SOLICITUD!$D$1,IF(D206="NULL",D206,CONCATENATE("'",D206,"'"))),DATA_SOLICITUD!$E$1,IF(E206="NULL",E206,CONCATENATE("'",E206,"'"))),DATA_SOLICITUD!$F$1,IF(F206="NULL",F206,CONCATENATE("'",F206,"'"))),DATA_SOLICITUD!$G$1,IF(G206="NULL",G206,CONCATENATE("'",G206,"'"))),DATA_SOLICITUD!$H$1,IF(H206="NULL",H206,CONCATENATE("'",H206,"'"))),DATA_SOLICITUD!$I$1,IF(I206="NULL",I206,CONCATENATE("'",I206,"'"))),DATA_SOLICITUD!$J$1,IF(J206="NULL",J206,CONCATENATE("'",J206,"'"))),DATA_SOLICITUD!$K$1,IF(K206="NULL",K206,CONCATENATE("'",K206,"'"))),DATA_SOLICITUD!$L$1,IF(L206="NULL",L206,CONCATENATE("'",L206,"'"))) -> INSERT INTO `multitabla` (`id_multitabla`, `codigo_tabla`, `nombre_tabla`, `codigo`, `orden`, `valor`, `valor_aux`, `valor_crm`, `estado`, `estado_tabla`, `usuario_crea`, `fecha_crea`, `usuario_modif`, `fecha_modif`) VALUES (DEFAULT, '027', 'Departamentos', '1', '1', 'AMAZONAS', '01', '010000', '1', '1', 'admin', DEFAULT, NULL, NULL);
A207: DEFAULT | B207: 027 | C207: Departamentos | D207: 2 | E207: 2 | F207: ANCASH | G207: 02 | H207: 020000 | I207: NULL | J207: 1 | K207: 1 | L207: admin | M207: DEFAULT | N207: NULL | O207: NULL | P207: =SUBSTITUTE(SUBSTITUTE(SUBSTITUTE(SUBSTITUTE(SUBSTITUTE(SUBSTITUTE(SUBSTITUTE(SUBSTITUTE(SUBSTITUTE(SUBSTITUTE(SUBSTITUTE(INSERT!$B$3,DATA_SOLICITUD!$B$1,IF(B207="NULL",B207,CONCATENATE("'",B207,"'"))),DATA_SOLICITUD!$C$1,IF(C207="NULL",C207,CONCATENATE("'",C207,"'"))),DATA_SOLICITUD!$D$1,IF(D207="NULL",D207,CONCATENATE("'",D207,"'"))),DATA_SOLICITUD!$E$1,IF(E207="NULL",E207,CONCATENATE("'",E207,"'"))),DATA_SOLICITUD!$F$1,IF(F207="NULL",F207,CONCATENATE("'",F207,"'"))),DATA_SOLICITUD!$G$1,IF(G207="NULL",G207,CONCATENATE("'",G207,"'"))),DATA_SOLICITUD!$H$1,IF(H207="NULL",H207,CONCATENATE("'",H207,"'"))),DATA_SOLICITUD!$I$1,IF(I207="NULL",I207,CONCATENATE("'",I207,"'"))),DATA_SOLICITUD!$J$1,IF(J207="NULL",J207,CONCATENATE("'",J207,"'"))),DATA_SOLICITUD!$K$1,IF(K207="NULL",K207,CONCATENATE("'",K207,"'"))),DATA_SOLICITUD!$L$1,IF(L207="NULL",L207,CONCATENATE("'",L207,"'"))) -> INSERT INTO `multitabla` (`id_multitabla`, `codigo_tabla`, `nombre_tabla`, `codigo`, `orden`, `valor`, `valor_aux`, `valor_crm`, `estado`, `estado_tabla`, `usuario_crea`, `fecha_crea`, `usuario_modif`, `fecha_modif`) VALUES (DEFAULT, '027', 'Departamentos', '2', '2', 'ANCASH', '02', '020000', '1', '1', 'admin', DEFAULT, NULL, NULL);
A208: DEFAULT | B208: 027 | C208: Departamentos | D208: 3 | E208: 3 | F208: APURIMAC | G208: 03 | H208: 030000 | I208: NULL | J208: 1 | K208: 1 | L208: admin | M208: DEFAULT | N208: NULL | O208: NULL | P208: =SUBSTITUTE(SUBSTITUTE(SUBSTITUTE(SUBSTITUTE(SUBSTITUTE(SUBSTITUTE(SUBSTITUTE(SUBSTITUTE(SUBSTITUTE(SUBSTITUTE(SUBSTITUTE(INSERT!$B$3,DATA_SOLICITUD!$B$1,IF(B208="NULL",B208,CONCATENATE("'",B208,"'"))),DATA_SOLICITUD!$C$1,IF(C208="NULL",C208,CONCATENATE("'",C208,"'"))),DATA_SOLICITUD!$D$1,IF(D208="NULL",D208,CONCATENATE("'",D208,"'"))),DATA_SOLICITUD!$E$1,IF(E208="NULL",E208,CONCATENATE("'",E208,"'"))),DATA_SOLICITUD!$F$1,IF(F208="NULL",F208,CONCATENATE("'",F208,"'"))),DATA_SOLICITUD!$G$1,IF(G208="NULL",G208,CONCATENATE("'",G208,"'"))),DATA_SOLICITUD!$H$1,IF(H208="NULL",H208,CONCATENATE("'",H208,"'"))),DATA_SOLICITUD!$I$1,IF(I208="NULL",I208,CONCATENATE("'",I208,"'"))),DATA_SOLICITUD!$J$1,IF(J208="NULL",J208,CONCATENATE("'",J208,"'"))),DATA_SOLICITUD!$K$1,IF(K208="NULL",K208,CONCATENATE("'",K208,"'"))),DATA_SOLICITUD!$L$1,IF(L208="NULL",L208,CONCATENATE("'",L208,"'"))) -> INSERT INTO `multitabla` (`id_multitabla`, `codigo_tabla`, `nombre_tabla`, `codigo`, `orden`, `valor`, `valor_aux`, `valor_crm`, `estado`, `estado_tabla`, `usuario_crea`, `fecha_crea`, `usuario_modif`, `fecha_modif`) VALUES (DEFAULT, '027', 'Departamentos', '3', '3', 'APURIMAC', '03', '030000', '1', '1', 'admin', DEFAULT, NULL, NULL);
A209: DEFAULT | B209: 027 | C209: Departamentos | D209: 4 | E209: 4 | F209: AREQUIPA | G209: 04 | H209: 040000 | I209: NULL | J209: 1 | K209: 1 | L209: admin | M209: DEFAULT | N209: NULL | O209: NULL | P209: =SUBSTITUTE(SUBSTITUTE(SUBSTITUTE(SUBSTITUTE(SUBSTITUTE(SUBSTITUTE(SUBSTITUTE(SUBSTITUTE(SUBSTITUTE(SUBSTITUTE(SUBSTITUTE(INSERT!$B$3,DATA_SOLICITUD!$B$1,IF(B209="NULL",B209,CONCATENATE("'",B209,"'"))),DATA_SOLICITUD!$C$1,IF(C209="NULL",C209,CONCATENATE("'",C209,"'"))),DATA_SOLICITUD!$D$1,IF(D209="NULL",D209,CONCATENATE("'",D209,"'"))),DATA_SOLICITUD!$E$1,IF(E209="NULL",E209,CONCATENATE("'",E209,"'"))),DATA_SOLICITUD!$F$1,IF(F209="NULL",F209,CONCATENATE("'",F209,"'"))),DATA_SOLICITUD!$G$1,IF(G209="NULL",G209,CONCATENATE("'",G209,"'"))),DATA_SOLICITUD!$H$1,IF(H209="NULL",H209,CONCATENATE("'",H209,"'"))),DATA_SOLICITUD!$I$1,IF(I209="NULL",I209,CONCATENATE("'",I209,"'"))),DATA_SOLICITUD!$J$1,IF(J209="NULL",J209,CONCATENATE("'",J209,"'"))),DATA_SOLICITUD!$K$1,IF(K209="NULL",K209,CONCATENATE("'",K209,"'"))),DATA_SOLICITUD!$L$1,IF(L209="NULL",L209,CONCATENATE("'",L209,"'"))) -> INSERT INTO `multitabla` (`id_multitabla`, `codigo_tabla`, `nombre_tabla`, `codigo`, `orden`, `valor`, `valor_aux`, `valor_crm`, `estado`, `estado_tabla`, `usuario_crea`, `fecha_crea`, `usuario_modif`, `fecha_modif`) VALUES (DEFAULT, '027', 'Departamentos', '4', '4', 'AREQUIPA', '04', '040000', '1', '1', 'admin', DEFAULT, NULL, NULL);
A210: DEFAULT | B210: 027 | C210: Departamentos | D210: 5 | E210: 5 | F210: AYACUCHO | G210: 05 | H210: 050000 | I210: NULL | J210: 1 | K210: 1 | L210: admin | M210: DEFAULT | N210: NULL | O210: NULL | P210: =SUBSTITUTE(SUBSTITUTE(SUBSTITUTE(SUBSTITUTE(SUBSTITUTE(SUBSTITUTE(SUBSTITUTE(SUBSTITUTE(SUBSTITUTE(SUBSTITUTE(SUBSTITUTE(INSERT!$B$3,DATA_SOLICITUD!$B$1,IF(B210="NULL",B210,CONCATENATE("'",B210,"'"))),DATA_SOLICITUD!$C$1,IF(C210="NULL",C210,CONCATENATE("'",C210,"'"))),DATA_SOLICITUD!$D$1,IF(D210="NULL",D210,CONCATENATE("'",D210,"'"))),DATA_SOLICITUD!$E$1,IF(E210="NULL",E210,CONCATENATE("'",E210,"'"))),DATA_SOLICITUD!$F$1,IF(F210="NULL",F210,CONCATENATE("'",F210,"'"))),DATA_SOLICITUD!$G$1,IF(G210="NULL",G210,CONCATENATE("'",G210,"'"))),DATA_SOLICITUD!$H$1,IF(H210="NULL",H210,CONCATENATE("'",H210,"'"))),DATA_SOLICITUD!$I$1,IF(I210="NULL",I210,CONCATENATE("'",I210,"'"))),DATA_SOLICITUD!$J$1,IF(J210="NULL",J210,CONCATENATE("'",J210,"'"))),DATA_SOLICITUD!$K$1,IF(K210="NULL",K210,CONCATENATE("'",K210,"'"))),DATA_SOLICITUD!$L$1,IF(L210="NULL",L210,CONCATENATE("'",L210,"'"))) -> INSERT INTO `multitabla` (`id_multitabla`, `codigo_tabla`, `nombre_tabla`, `codigo`, `orden`, `valor`, `valor_aux`, `valor_crm`, `estado`, `estado_tabla`, `usuario_crea`, `fecha_crea`, `usuario_modif`, `fecha_modif`) VALUES (DEFAULT, '027', 'Departamentos', '5', '5', 'AYACUCHO', '05', '050000', '1', '1', 'admin', DEFAULT, NULL, NULL);
A211: DEFAULT | B211: 027 | C211: Departamentos | D211: 6 | E211: 6 | F211: CAJAMARCA | G211: 06 | H211: 060000 | I211: NULL | J211: 1 | K211: 1 | L211: admin | M211: DEFAULT | N211: NULL | O211: NULL | P211: =SUBSTITUTE(SUBSTITUTE(SUBSTITUTE(SUBSTITUTE(SUBSTITUTE(SUBSTITUTE(SUBSTITUTE(SUBSTITUTE(SUBSTITUTE(SUBSTITUTE(SUBSTITUTE(INSERT!$B$3,DATA_SOLICITUD!$B$1,IF(B211="NULL",B211,CONCATENATE("'",B211,"'"))),DATA_SOLICITUD!$C$1,IF(C211="NULL",C211,CONCATENATE("'",C211,"'"))),DATA_SOLICITUD!$D$1,IF(D211="NULL",D211,CONCATENATE("'",D211,"'"))),DATA_SOLICITUD!$E$1,IF(E211="NULL",E211,CONCATENATE("'",E211,"'"))),DATA_SOLICITUD!$F$1,IF(F211="NULL",F211,CONCATENATE("'",F211,"'"))),DATA_SOLICITUD!$G$1,IF(G211="NULL",G211,CONCATENATE("'",G211,"'"))),DATA_SOLICITUD!$H$1,IF(H211="NULL",H211,CONCATENATE("'",H211,"'"))),DATA_SOLICITUD!$I$1,IF(I211="NULL",I211,CONCATENATE("'",I211,"'"))),DATA_SOLICITUD!$J$1,IF(J211="NULL",J211,CONCATENATE("'",J211,"'"))),DATA_SOLICITUD!$K$1,IF(K211="NULL",K211,CONCATENATE("'",K211,"'"))),DATA_SOLICITUD!$L$1,IF(L211="NULL",L211,CONCATENATE("'",L211,"'"))) -> INSERT INTO `multitabla` (`id_multitabla`, `codigo_tabla`, `nombre_tabla`, `codigo`, `orden`, `valor`, `valor_aux`, `valor_crm`, `estado`, `estado_tabla`, `usuario_crea`, `fecha_crea`, `usuario_modif`, `fecha_modif`) VALUES (DEFAULT, '027', 'Departamentos', '6', '6', 'CAJAMARCA', '06', '060000', '1', '1', 'admin', DEFAULT, NULL, NULL);
A212: DEFAULT | B212: 027 | C212: Departamentos | D212: 7 | E212: 7 | F212: CUSCO | G212: 08 | H212: 080000 | I212: NULL | J212: 1 | K212: 1 | L212: admin | M212: DEFAULT | N212: NULL | O212: NULL | P212: =SUBSTITUTE(SUBSTITUTE(SUBSTITUTE(SUBSTITUTE(SUBSTITUTE(SUBSTITUTE(SUBSTITUTE(SUBSTITUTE(SUBSTITUTE(SUBSTITUTE(SUBSTITUTE(INSERT!$B$3,DATA_SOLICITUD!$B$1,IF(B212="NULL",B212,CONCATENATE("'",B212,"'"))),DATA_SOLICITUD!$C$1,IF(C212="NULL",C212,CONCATENATE("'",C212,"'"))),DATA_SOLICITUD!$D$1,IF(D212="NULL",D212,CONCATENATE("'",D212,"'"))),DATA_SOLICITUD!$E$1,IF(E212="NULL",E212,CONCATENATE("'",E212,"'"))),DATA_SOLICITUD!$F$1,IF(F212="NULL",F212,CONCATENATE("'",F212,"'"))),DATA_SOLICITUD!$G$1,IF(G212="NULL",G212,CONCATENATE("'",G212,"'"))),DATA_SOLICITUD!$H$1,IF(H212="NULL",H212,CONCATENATE("'",H212,"'"))),DATA_SOLICITUD!$I$1,IF(I212="NULL",I212,CONCATENATE("'",I212,"'"))),DATA_SOLICITUD!$J$1,IF(J212="NULL",J212,CONCATENATE("'",J212,"'"))),DATA_SOLICITUD!$K$1,IF(K212="NULL",K212,CONCATENATE("'",K212,"'"))),DATA_SOLICITUD!$L$1,IF(L212="NULL",L212,CONCATENATE("'",L212,"'"))) -> INSERT INTO `multitabla` (`id_multitabla`, `codigo_tabla`, `nombre_tabla`, `codigo`, `orden`, `valor`, `valor_aux`, `valor_crm`, `estado`, `estado_tabla`, `usuario_crea`, `fecha_crea`, `usuario_modif`, `fecha_modif`) VALUES (DEFAULT, '027', 'Departamentos', '7', '7', 'CUSCO', '08', '080000', '1', '1', 'admin', DEFAULT, NULL, NULL);
A213: DEFAULT | B213: 027 | C213: Departamentos | D213: 8 | E213: 8 | F213: HUANCAVELICA | G213: 09 | H213: 090000 | I213: NULL | J213: 1 | K213: 1 | L213: admin | M213: DEFAULT | N213: NULL | O213: NULL | P213: =SUBSTITUTE(SUBSTITUTE(SUBSTITUTE(SUBSTITUTE(SUBSTITUTE(SUBSTITUTE(SUBSTITUTE(SUBSTITUTE(SUBSTITUTE(SUBSTITUTE(SUBSTITUTE(INSERT!$B$3,DATA_SOLICITUD!$B$1,IF(B213="NULL",B213,CONCATENATE("'",B213,"'"))),DATA_SOLICITUD!$C$1,IF(C213="NULL",C213,CONCATENATE("'",C213,"'"))),DATA_SOLICITUD!$D$1,IF(D213="NULL",D213,CONCATENATE("'",D213,"'"))),DATA_SOLICITUD!$E$1,IF(E213="NULL",E213,CONCATENATE("'",E213,"'"))),DATA_SOLICITUD!$F$1,IF(F213="NULL",F213,CONCATENATE("'",F213,"'"))),DATA_SOLICITUD!$G$1,IF(G213="NULL",G213,CONCATENATE("'",G213,"'"))),DATA_SOLICITUD!$H$1,IF(H213="NULL",H213,CONCATENATE("'",H213,"'"))),DATA_SOLICITUD!$I$1,IF(I213="NULL",I213,CONCATENATE("'",I213,"'"))),DATA_SOLICITUD!$J$1,IF(J213="NULL",J213,CONCATENATE("'",J213,"'"))),DATA_SOLICITUD!$K$1,IF(K213="NULL",K213,CONCATENATE("'",K213,"'"))),DATA_SOLICITUD!$L$1,IF(L213="NULL",L213,CONCATENATE("'",L213,"'"))) -> INSERT INTO `multitabla` (`id_multitabla`, `codigo_tabla`, `nombre_tabla`, `codigo`, `orden`, `valor`, `valor_aux`, `valor_crm`, `estado`, `estado_tabla`, `usuario_crea`, `fecha_crea`, `usuario_modif`, `fecha_modif`) VALUES (DEFAULT, '027', 'Departamentos', '8', '8', 'HUANCAVELICA', '09', '090000', '1', '1', 'admin', DEFAULT, NULL, NULL);
A214: DEFAULT | B214: 027 | C214: Departamentos | D214: 9 | E214: 9 | F214: HUANUCO | G214: 10 | H214: 100000 | I214: NULL | J214: 1 | K214: 1 | L214: admin | M214: DEFAULT | N214: NULL | O214: NULL | P214: =SUBSTITUTE(SUBSTITUTE(SUBSTITUTE(SUBSTITUTE(SUBSTITUTE(SUBSTITUTE(SUBSTITUTE(SUBSTITUTE(SUBSTITUTE(SUBSTITUTE(SUBSTITUTE(INSERT!$B$3,DATA_SOLICITUD!$B$1,IF(B214="NULL",B214,CONCATENATE("'",B214,"'"))),DATA_SOLICITUD!$C$1,IF(C214="NULL",C214,CONCATENATE("'",C214,"'"))),DATA_SOLICITUD!$D$1,IF(D214="NULL",D214,CONCATENATE("'",D214,"'"))),DATA_SOLICITUD!$E$1,IF(E214="NULL",E214,CONCATENATE("'",E214,"'"))),DATA_SOLICITUD!$F$1,IF(F214="NULL",F214,CONCATENATE("'",F214,"'"))),DATA_SOLICITUD!$G$1,IF(G214="NULL",G214,CONCATENATE("'",G214,"'"))),DATA_SOLICITUD!$H$1,IF(H214="NULL",H214,CONCATENATE("'",H214,"'"))),DATA_SOLICITUD!$I$1,IF(I214="NULL",I214,CONCATENATE("'",I214,"'"))),DATA_SOLICITUD!$J$1,IF(J214="NULL",J214,CONCATENATE("'",J214,"'"))),DATA_SOLICITUD!$K$1,IF(K214="NULL",K214,CONCATENATE("'",K214,"'"))),DATA_SOLICITUD!$L$1,IF(L214="NULL",L214,CONCATENATE("'",L214,"'"))) -> INSERT INTO `multitabla` (`id_multitabla`, `codigo_tabla`, `nombre_tabla`, `codigo`, `orden`, `valor`, `valor_aux`, `valor_crm`, `estado`, `estado_tabla`, `usuario_crea`, `fecha_crea`, `usuario_modif`, `fecha_modif`) VALUES (DEFAULT, '027', 'Departamentos', '9', '9', 'HUANUCO', '10', '100000', '1', '1', 'admin', DEFAULT, NULL, NULL);
A215: DEFAULT | B215: 027 | C215: Departamentos | D215: 10 | E215: 10 | F215: ICA | G215: 11 | H215: 110000 | I215: NULL | J215: 1 | K215: 1 | L215: admin | M215: DEFAULT | N215: NULL | O215: NULL | P215: =SUBSTITUTE(SUBSTITUTE(SUBSTITUTE(SUBSTITUTE(SUBSTITUTE(SUBSTITUTE(SUBSTITUTE(SUBSTITUTE(SUBSTITUTE(SUBSTITUTE(SUBSTITUTE(INSERT!$B$3,DATA_SOLICITUD!$B$1,IF(B215="NULL",B215,CONCATENATE("'",B215,"'"))),DATA_SOLICITUD!$C$1,IF(C215="NULL",C215,CONCATENATE("'",C215,"'"))),DATA_SOLICITUD!$D$1,IF(D215="NULL",D215,CONCATENATE("'",D215,"'"))),DATA_SOLICITUD!$E$1,IF(E215="NULL",E215,CONCATENATE("'",E215,"'"))),DATA_SOLICITUD!$F$1,IF(F215="NULL",F215,CONCATENATE("'",F215,"'"))),DATA_SOLICITUD!$G$1,IF(G215="NULL",G215,CONCATENATE("'",G215,"'"))),DATA_SOLICITUD!$H$1,IF(H215="NULL",H215,CONCATENATE("'",H215,"'"))),DATA_SOLICITUD!$I$1,IF(I215="NULL",I215,CONCATENATE("'",I215,"'"))),DATA_SOLICITUD!$J$1,IF(J215="NULL",J215,CONCATENATE("'",J215,"'"))),DATA_SOLICITUD!$K$1,IF(K215="NULL",K215,CONCATENATE("'",K215,"'"))),DATA_SOLICITUD!$L$1,IF(L215="NULL",L215,CONCATENATE("'",L215,"'"))) -> INSERT INTO `multitabla` (`id_multitabla`, `codigo_tabla`, `nombre_tabla`, `codigo`, `orden`, `valor`, `valor_aux`, `valor_crm`, `estado`, `estado_tabla`, `usuario_crea`, `fecha_crea`, `usuario_modif`, `fecha_modif`) VALUES (DEFAULT, '027', 'Departamentos', '10', '10', 'ICA', '11', '110000', '1', '1', 'admin', DEFAULT, NULL, NULL);
A216: DEFAULT | B216: 027 | C216: Departamentos | D216: 11 | E216: 11 | F216: JUNIN | G216: 12 | H216: 120000 | I216: NULL | J216: 1 | K216: 1 | L216: admin | M216: DEFAULT | N216: NULL | O216: NULL | P216: =SUBSTITUTE(SUBSTITUTE(SUBSTITUTE(SUBSTITUTE(SUBSTITUTE(SUBSTITUTE(SUBSTITUTE(SUBSTITUTE(SUBSTITUTE(SUBSTITUTE(SUBSTITUTE(INSERT!$B$3,DATA_SOLICITUD!$B$1,IF(B216="NULL",B216,CONCATENATE("'",B216,"'"))),DATA_SOLICITUD!$C$1,IF(C216="NULL",C216,CONCATENATE("'",C216,"'"))),DATA_SOLICITUD!$D$1,IF(D216="NULL",D216,CONCATENATE("'",D216,"'"))),DATA_SOLICITUD!$E$1,IF(E216="NULL",E216,CONCATENATE("'",E216,"'"))),DATA_SOLICITUD!$F$1,IF(F216="NULL",F216,CONCATENATE("'",F216,"'"))),DATA_SOLICITUD!$G$1,IF(G216="NULL",G216,CONCATENATE("'",G216,"'"))),DATA_SOLICITUD!$H$1,IF(H216="NULL",H216,CONCATENATE("'",H216,"'"))),DATA_SOLICITUD!$I$1,IF(I216="NULL",I216,CONCATENATE("'",I216,"'"))),DATA_SOLICITUD!$J$1,IF(J216="NULL",J216,CONCATENATE("'",J216,"'"))),DATA_SOLICITUD!$K$1,IF(K216="NULL",K216,CONCATENATE("'",K216,"'"))),DATA_SOLICITUD!$L$1,IF(L216="NULL",L216,CONCATENATE("'",L216,"'"))) -> INSERT INTO `multitabla` (`id_multitabla`, `codigo_tabla`, `nombre_tabla`, `codigo`, `orden`, `valor`, `valor_aux`, `valor_crm`, `estado`, `estado_tabla`, `usuario_crea`, `fecha_crea`, `usuario_modif`, `fecha_modif`) VALUES (DEFAULT, '027', 'Departamentos', '11', '11', 'JUNIN', '12', '120000', '1', '1', 'admin', DEFAULT, NULL, NULL);
A217: DEFAULT | B217: 027 | C217: Departamentos | D217: 12 | E217: 12 | F217: LA LIBERTAD | G217: 13 | H217: 130000 | I217: NULL | J217: 1 | K217: 1 | L217: admin | M217: DEFAULT | N217: NULL | O217: NULL | P217: =SUBSTITUTE(SUBSTITUTE(SUBSTITUTE(SUBSTITUTE(SUBSTITUTE(SUBSTITUTE(SUBSTITUTE(SUBSTITUTE(SUBSTITUTE(SUBSTITUTE(SUBSTITUTE(INSERT!$B$3,DATA_SOLICITUD!$B$1,IF(B217="NULL",B217,CONCATENATE("'",B217,"'"))),DATA_SOLICITUD!$C$1,IF(C217="NULL",C217,CONCATENATE("'",C217,"'"))),DATA_SOLICITUD!$D$1,IF(D217="NULL",D217,CONCATENATE("'",D217,"'"))),DATA_SOLICITUD!$E$1,IF(E217="NULL",E217,CONCATENATE("'",E217,"'"))),DATA_SOLICITUD!$F$1,IF(F217="NULL",F217,CONCATENATE("'",F217,"'"))),DATA_SOLICITUD!$G$1,IF(G217="NULL",G217,CONCATENATE("'",G217,"'"))),DATA_SOLICITUD!$H$1,IF(H217="NULL",H217,CONCATENATE("'",H217,"'"))),DATA_SOLICITUD!$I$1,IF(I217="NULL",I217,CONCATENATE("'",I217,"'"))),DATA_SOLICITUD!$J$1,IF(J217="NULL",J217,CONCATENATE("'",J217,"'"))),DATA_SOLICITUD!$K$1,IF(K217="NULL",K217,CONCATENATE("'",K217,"'"))),DATA_SOLICITUD!$L$1,IF(L217="NULL",L217,CONCATENATE("'",L217,"'"))) -> INSERT INTO `multitabla` (`id_multitabla`, `codigo_tabla`, `nombre_tabla`, `codigo`, `orden`, `valor`, `valor_aux`, `valor_crm`, `estado`, `estado_tabla`, `usuario_crea`, `fecha_crea`, `usuario_modif`, `fecha_modif`) VALUES (DEFAULT, '027', 'Departamentos', '12', '12', 'LA LIBERTAD', '13', '130000', '1', '1', 'admin', DEFAULT, NULL, NULL);
... A230: DEFAULT | B230: 027 | C230: Departamentos | D230: 25 | E230: 25 | F230: UCAYALI | G230: 25 | H230: 250000 | I230: NULL | J230: 1 | K230: 1 | L230: admin | M230: DEFAULT | N230: NULL | O230: NULL | P230: =SUBSTITUTE(SUBSTITUTE(SUBSTITUTE(SUBSTITUTE(SUBSTITUTE(SUBSTITUTE(SUBSTITUTE(SUBSTITUTE(SUBSTITUTE(SUBSTITUTE(SUBSTITUTE(INSERT!$B$3,DATA_SOLICITUD!$B$1,IF(B230="NULL",B230,CONCATENATE("'",B230,"'"))),DATA_SOLICITUD!$C$1,IF(C230="NULL",C230,CONCATENATE("'",C230,"'"))),DATA_SOLICITUD!$D$1,IF(D230="NULL",D230,CONCATENATE("'",D230,"'"))),DATA_SOLICITUD!$E$1,IF(E230="NULL",E230,CONCATENATE("'",E230,"'"))),DATA_SOLICITUD!$F$1,IF(F230="NULL",F230,CONCATENATE("'",F230,"'"))),DATA_SOLICITUD!$G$1,IF(G230="NULL",G230,CONCATENATE("'",G230,"'"))),DATA_SOLICITUD!$H$1,IF(H230="NULL",H230,CONCATENATE("'",H230,"'"))),DATA_SOLICITUD!$I$1,IF(I230="NULL",I230,CONCATENATE("'",I230,"'"))),DATA_SOLICITUD!$J$1,IF(J230="NULL",J230,CONCATENATE("'",J230,"'"))),DATA_SOLICITUD!$K$1,IF(K230="NULL",K230,CONCATENATE("'",K230,"'"))),DATA_SOLICITUD!$L$1,IF(L230="NULL",L230,CONCATENATE("'",L230,"'"))) -> INSERT INTO `multitabla` (`id_multitabla`, `codigo_tabla`, `nombre_tabla`, `codigo`, `orden`, `valor`, `valor_aux`, `valor_crm`, `estado`, `estado_tabla`, `usuario_crea`, `fecha_crea`, `usuario_modif`, `fecha_modif`) VALUES (DEFAULT, '027', 'Departamentos', '25', '25', 'UCAYALI', '25', '250000', '1', '1', 'admin', DEFAULT, NULL, NULL);
A231: DEFAULT | B231: 028 | C231: Provincias | D231: NULL | E231: NULL | F231: NULL | G231: NULL | H231: NULL | I231: NULL | J231: NULL | K231: 1 | L231: admin | M231: DEFAULT | N231: NULL | O231: NULL | P231: =SUBSTITUTE(SUBSTITUTE(SUBSTITUTE(SUBSTITUTE(SUBSTITUTE(SUBSTITUTE(SUBSTITUTE(SUBSTITUTE(SUBSTITUTE(SUBSTITUTE(SUBSTITUTE(INSERT!$B$3,DATA_SOLICITUD!$B$1,IF(B231="NULL",B231,CONCATENATE("'",B231,"'"))),DATA_SOLICITUD!$C$1,IF(C231="NULL",C231,CONCATENATE("'",C231,"'"))),DATA_SOLICITUD!$D$1,IF(D231="NULL",D231,CONCATENATE("'",D231,"'"))),DATA_SOLICITUD!$E$1,IF(E231="NULL",E231,CONCATENATE("'",E231,"'"))),DATA_SOLICITUD!$F$1,IF(F231="NULL",F231,CONCATENATE("'",F231,"'"))),DATA_SOLICITUD!$G$1,IF(G231="NULL",G231,CONCATENATE("'",G231,"'"))),DATA_SOLICITUD!$H$1,IF(H231="NULL",H231,CONCATENATE("'",H231,"'"))),DATA_SOLICITUD!$I$1,IF(I231="NULL",I231,CONCATENATE("'",I231,"'"))),DATA_SOLICITUD!$J$1,IF(J231="NULL",J231,CONCATENATE("'",J231,"'"))),DATA_SOLICITUD!$K$1,IF(K231="NULL",K231,CONCATENATE("'",K231,"'"))),DATA_SOLICITUD!$L$1,IF(L231="NULL",L231,CONCATENATE("'",L231,"'"))) -> INSERT INTO `multitabla` (`id_multitabla`, `codigo_tabla`, `nombre_tabla`, `codigo`, `orden`, `valor`, `valor_aux`, `valor_crm`, `estado`, `estado_tabla`, `usuario_crea`, `fecha_crea`, `usuario_modif`, `fecha_modif`) VALUES (DEFAULT, '028', 'Provincias', NULL, NULL, NULL, NULL, NULL, NULL, '1', 'admin', DEFAULT, NULL, NULL);
A232: DEFAULT | B232: 028 | C232: Provincias | D232: 1 | E232: 1 | F232: ABANCAY | G232: 180100 | H232: 030100 | I232: NULL | J232: 1 | K232: 1 | L232: admin | M232: DEFAULT | N232: NULL | O232: NULL | P232: =SUBSTITUTE(SUBSTITUTE(SUBSTITUTE(SUBSTITUTE(SUBSTITUTE(SUBSTITUTE(SUBSTITUTE(SUBSTITUTE(SUBSTITUTE(SUBSTITUTE(SUBSTITUTE(INSERT!$B$3,DATA_SOLICITUD!$B$1,IF(B232="NULL",B232,CONCATENATE("'",B232,"'"))),DATA_SOLICITUD!$C$1,IF(C232="NULL",C232,CONCATENATE("'",C232,"'"))),DATA_SOLICITUD!$D$1,IF(D232="NULL",D232,CONCATENATE("'",D232,"'"))),DATA_SOLICITUD!$E$1,IF(E232="NULL",E232,CONCATENATE("'",E232,"'"))),DATA_SOLICITUD!$F$1,IF(F232="NULL",F232,CONCATENATE("'",F232,"'"))),DATA_SOLICITUD!$G$1,IF(G232="NULL",G232,CONCATENATE("'",G232,"'"))),DATA_SOLICITUD!$H$1,IF(H232="NULL",H232,CONCATENATE("'",H232,"'"))),DATA_SOLICITUD!$I$1,IF(I232="NULL",I232,CONCATENATE("'",I232,"'"))),DATA_SOLICITUD!$J$1,IF(J232="NULL",J232,CONCATENATE("'",J232,"'"))),DATA_SOLICITUD!$K$1,IF(K232="NULL",K232,CONCATENATE("'",K232,"'"))),DATA_SOLICITUD!$L$1,IF(L232="NULL",L232,CONCATENATE("'",L232,"'"))) -> INSERT INTO `multitabla` (`id_multitabla`, `codigo_tabla`, `nombre_tabla`, `codigo`, `orden`, `valor`, `valor_aux`, `valor_crm`, `estado`, `estado_tabla`, `usuario_crea`, `fecha_crea`, `usuario_modif`, `fecha_modif`) VALUES (DEFAULT, '028', 'Provincias', '1', '1', 'ABANCAY', '180100', '030100', '1', '1', 'admin', DEFAULT, NULL, NULL);
A233: DEFAULT | B233: 028 | C233: Provincias | D233: 2 | E233: 2 | F233: ACOBAMBA | G233: 160100 | H233: 090200 | I233: NULL | J233: 1 | K233: 1 | L233: admin | M233: DEFAULT | N233: NULL | O233: NULL | P233: =SUBSTITUTE(SUBSTITUTE(SUBSTITUTE(SUBSTITUTE(SUBSTITUTE(SUBSTITUTE(SUBSTITUTE(SUBSTITUTE(SUBSTITUTE(SUBSTITUTE(SUBSTITUTE(INSERT!$B$3,DATA_SOLICITUD!$B$1,IF(B233="NULL",B233,CONCATENATE("'",B233,"'"))),DATA_SOLICITUD!$C$1,IF(C233="NULL",C233,CONCATENATE("'",C233,"'"))),DATA_SOLICITUD!$D$1,IF(D233="NULL",D233,CONCATENATE("'",D233,"'"))),DATA_SOLICITUD!$E$1,IF(E233="NULL",E233,CONCATENATE("'",E233,"'"))),DATA_SOLICITUD!$F$1,IF(F233="NULL",F233,CONCATENATE("'",F233,"'"))),DATA_SOLICITUD!$G$1,IF(G233="NULL",G233,CONCATENATE("'",G233,"'"))),DATA_SOLICITUD!$H$1,IF(H233="NULL",H233,CONCATENATE("'",H233,"'"))),DATA_SOLICITUD!$I$1,IF(I233="NULL",I233,CONCATENATE("'",I233,"'"))),DATA_SOLICITUD!$J$1,IF(J233="NULL",J233,CONCATENATE("'",J233,"'"))),DATA_SOLICITUD!$K$1,IF(K233="NULL",K233,CONCATENATE("'",K233,"'"))),DATA_SOLICITUD!$L$1,IF(L233="NULL",L233,CONCATENATE("'",L233,"'"))) -> INSERT INTO `multitabla` (`id_multitabla`, `codigo_tabla`, `nombre_tabla`, `codigo`, `orden`, `valor`, `valor_aux`, `valor_crm`, `estado`, `estado_tabla`, `usuario_crea`, `fecha_crea`, `usuario_modif`, `fecha_modif`) VALUES (DEFAULT, '028', 'Provincias', '2', '2', 'ACOBAMBA', '160100', '090200', '1', '1', 'admin', DEFAULT, NULL, NULL);
A234: DEFAULT | B234: 028 | C234: Provincias | D234: 3 | E234: 3 | F234: ACOMAYO | G234: 190100 | H234: 080200 | I234: NULL | J234: 1 | K234: 1 | L234: admin | M234: DEFAULT | N234: NULL | O234: NULL | P234: =SUBSTITUTE(SUBSTITUTE(SUBSTITUTE(SUBSTITUTE(SUBSTITUTE(SUBSTITUTE(SUBSTITUTE(SUBSTITUTE(SUBSTITUTE(SUBSTITUTE(SUBSTITUTE(INSERT!$B$3,DATA_SOLICITUD!$B$1,IF(B234="NULL",B234,CONCATENATE("'",B234,"'"))),DATA_SOLICITUD!$C$1,IF(C234="NULL",C234,CONCATENATE("'",C234,"'"))),DATA_SOLICITUD!$D$1,IF(D234="NULL",D234,CONCATENATE("'",D234,"'"))),DATA_SOLICITUD!$E$1,IF(E234="NULL",E234,CONCATENATE("'",E234,"'"))),DATA_SOLICITUD!$F$1,IF(F234="NULL",F234,CONCATENATE("'",F234,"'"))),DATA_SOLICITUD!$G$1,IF(G234="NULL",G234,CONCATENATE("'",G234,"'"))),DATA_SOLICITUD!$H$1,IF(H234="NULL",H234,CONCATENATE("'",H234,"'"))),DATA_SOLICITUD!$I$1,IF(I234="NULL",I234,CONCATENATE("'",I234,"'"))),DATA_SOLICITUD!$J$1,IF(J234="NULL",J234,CONCATENATE("'",J234,"'"))),DATA_SOLICITUD!$K$1,IF(K234="NULL",K234,CONCATENATE("'",K234,"'"))),DATA_SOLICITUD!$L$1,IF(L234="NULL",L234,CONCATENATE("'",L234,"'"))) -> INSERT INTO `multitabla` (`id_multitabla`, `codigo_tabla`, `nombre_tabla`, `codigo`, `orden`, `valor`, `valor_aux`, `valor_crm`, `estado`, `estado_tabla`, `usuario_crea`, `fecha_crea`, `usuario_modif`, `fecha_modif`) VALUES (DEFAULT, '028', 'Provincias', '3', '3', 'ACOMAYO', '190100', '080200', '1', '1', 'admin', DEFAULT, NULL, NULL);
A235: DEFAULT | B235: 028 | C235: Provincias | D235: 4 | E235: 4 | F235: AIJA | G235: 90100 | H235: 020200 | I235: NULL | J235: 1 | K235: 1 | L235: admin | M235: DEFAULT | N235: NULL | O235: NULL | P235: =SUBSTITUTE(SUBSTITUTE(SUBSTITUTE(SUBSTITUTE(SUBSTITUTE(SUBSTITUTE(SUBSTITUTE(SUBSTITUTE(SUBSTITUTE(SUBSTITUTE(SUBSTITUTE(INSERT!$B$3,DATA_SOLICITUD!$B$1,IF(B235="NULL",B235,CONCATENATE("'",B235,"'"))),DATA_SOLICITUD!$C$1,IF(C235="NULL",C235,CONCATENATE("'",C235,"'"))),DATA_SOLICITUD!$D$1,IF(D235="NULL",D235,CONCATENATE("'",D235,"'"))),DATA_SOLICITUD!$E$1,IF(E235="NULL",E235,CONCATENATE("'",E235,"'"))),DATA_SOLICITUD!$F$1,IF(F235="NULL",F235,CONCATENATE("'",F235,"'"))),DATA_SOLICITUD!$G$1,IF(G235="NULL",G235,CONCATENATE("'",G235,"'"))),DATA_SOLICITUD!$H$1,IF(H235="NULL",H235,CONCATENATE("'",H235,"'"))),DATA_SOLICITUD!$I$1,IF(I235="NULL",I235,CONCATENATE("'",I235,"'"))),DATA_SOLICITUD!$J$1,IF(J235="NULL",J235,CONCATENATE("'",J235,"'"))),DATA_SOLICITUD!$K$1,IF(K235="NULL",K235,CONCATENATE("'",K235,"'"))),DATA_SOLICITUD!$L$1,IF(L235="NULL",L235,CONCATENATE("'",L235,"'"))) -> INSERT INTO `multitabla` (`id_multitabla`, `codigo_tabla`, `nombre_tabla`, `codigo`, `orden`, `valor`, `valor_aux`, `valor_crm`, `estado`, `estado_tabla`, `usuario_crea`, `fecha_crea`, `usuario_modif`, `fecha_modif`) VALUES (DEFAULT, '028', 'Provincias', '4', '4', 'AIJA', '90100', '020200', '1', '1', 'admin', DEFAULT, NULL, NULL);
A236: DEFAULT | B236: 028 | C236: Provincias | D236: 5 | E236: 5 | F236: ALTO AMAZONAS | G236: 60100 | H236: 160200 | I236: NULL | J236: 1 | K236: 1 | L236: admin | M236: DEFAULT | N236: NULL | O236: NULL | P236: =SUBSTITUTE(SUBSTITUTE(SUBSTITUTE(SUBSTITUTE(SUBSTITUTE(SUBSTITUTE(SUBSTITUTE(SUBSTITUTE(SUBSTITUTE(SUBSTITUTE(SUBSTITUTE(INSERT!$B$3,DATA_SOLICITUD!$B$1,IF(B236="NULL",B236,CONCATENATE("'",B236,"'"))),DATA_SOLICITUD!$C$1,IF(C236="NULL",C236,CONCATENATE("'",C236,"'"))),DATA_SOLICITUD!$D$1,IF(D236="NULL",D236,CONCATENATE("'",D236,"'"))),DATA_SOLICITUD!$E$1,IF(E236="NULL",E236,CONCATENATE("'",E236,"'"))),DATA_SOLICITUD!$F$1,IF(F236="NULL",F236,CONCATENATE("'",F236,"'"))),DATA_SOLICITUD!$G$1,IF(G236="NULL",G236,CONCATENATE("'",G236,"'"))),DATA_SOLICITUD!$H$1,IF(H236="NULL",H236,CONCATENATE("'",H236,"'"))),DATA_SOLICITUD!$I$1,IF(I236="NULL",I236,CONCATENATE("'",I236,"'"))),DATA_SOLICITUD!$J$1,IF(J236="NULL",J236,CONCATENATE("'",J236,"'"))),DATA_SOLICITUD!$K$1,IF(K236="NULL",K236,CONCATENATE("'",K236,"'"))),DATA_SOLICITUD!$L$1,IF(L236="NULL",L236,CONCATENATE("'",L236,"'"))) -> INSERT INTO `multitabla` (`id_multitabla`, `codigo_tabla`, `nombre_tabla`, `codigo`, `orden`, `valor`, `valor_aux`, `valor_crm`, `estado`, `estado_tabla`, `usuario_crea`, `fecha_crea`, `usuario_modif`, `fecha_modif`) VALUES (DEFAULT, '028', 'Provincias', '5', '5', 'ALTO AMAZONAS', '60100', '160200', '1', '1', 'admin', DEFAULT, NULL, NULL);
A237: DEFAULT | B237: 028 | C237: Provincias | D237: 6 | E237: 6 | F237: AMBO | G237: 100100 | H237: 100200 | I237: NULL | J237: 1 | K237: 1 | L237: admin | M237: DEFAULT | N237: NULL | O237: NULL | P237: =SUBSTITUTE(SUBSTITUTE(SUBSTITUTE(SUBSTITUTE(SUBSTITUTE(SUBSTITUTE(SUBSTITUTE(SUBSTITUTE(SUBSTITUTE(SUBSTITUTE(SUBSTITUTE(INSERT!$B$3,DATA_SOLICITUD!$B$1,IF(B237="NULL",B237,CONCATENATE("'",B237,"'"))),DATA_SOLICITUD!$C$1,IF(C237="NULL",C237,CONCATENATE("'",C237,"'"))),DATA_SOLICITUD!$D$1,IF(D237="NULL",D237,CONCATENATE("'",D237,"'"))),DATA_SOLICITUD!$E$1,IF(E237="NULL",E237,CONCATENATE("'",E237,"'"))),DATA_SOLICITUD!$F$1,IF(F237="NULL",F237,CONCATENATE("'",F237,"'"))),DATA_SOLICITUD!$G$1,IF(G237="NULL",G237,CONCATENATE("'",G237,"'"))),DATA_SOLICITUD!$H$1,IF(H237="NULL",H237,CONCATENATE("'",H237,"'"))),DATA_SOLICITUD!$I$1,IF(I237="NULL",I237,CONCATENATE("'",I237,"'"))),DATA_SOLICITUD!$J$1,IF(J237="NULL",J237,CONCATENATE("'",J237,"'"))),DATA_SOLICITUD!$K$1,IF(K237="NULL",K237,CONCATENATE("'",K237,"'"))),DATA_SOLICITUD!$L$1,IF(L237="NULL",L237,CONCATENATE("'",L237,"'"))) -> INSERT INTO `multitabla` (`id_multitabla`, `codigo_tabla`, `nombre_tabla`, `codigo`, `orden`, `valor`, `valor_aux`, `valor_crm`, `estado`, `estado_tabla`, `usuario_crea`, `fecha_crea`, `usuario_modif`, `fecha_modif`) VALUES (DEFAULT, '028', 'Provincias', '6', '6', 'AMBO', '100100', '100200', '1', '1', 'admin', DEFAULT, NULL, NULL);
A238: DEFAULT | B238: 028 | C238: Provincias | D238: 7 | E238: 7 | F238: ANDAHUAYLAS | G238: 180200 | H238: 030200 | I238: NULL | J238: 1 | K238: 1 | L238: admin | M238: DEFAULT | N238: NULL | O238: NULL | P238: =SUBSTITUTE(SUBSTITUTE(SUBSTITUTE(SUBSTITUTE(SUBSTITUTE(SUBSTITUTE(SUBSTITUTE(SUBSTITUTE(SUBSTITUTE(SUBSTITUTE(SUBSTITUTE(INSERT!$B$3,DATA_SOLICITUD!$B$1,IF(B238="NULL",B238,CONCATENATE("'",B238,"'"))),DATA_SOLICITUD!$C$1,IF(C238="NULL",C238,CONCATENATE("'",C238,"'"))),DATA_SOLICITUD!$D$1,IF(D238="NULL",D238,CONCATENATE("'",D238,"'"))),DATA_SOLICITUD!$E$1,IF(E238="NULL",E238,CONCATENATE("'",E238,"'"))),DATA_SOLICITUD!$F$1,IF(F238="NULL",F238,CONCATENATE("'",F238,"'"))),DATA_SOLICITUD!$G$1,IF(G238="NULL",G238,CONCATENATE("'",G238,"'"))),DATA_SOLICITUD!$H$1,IF(H238="NULL",H238,CONCATENATE("'",H238,"'"))),DATA_SOLICITUD!$I$1,IF(I238="NULL",I238,CONCATENATE("'",I238,"'"))),DATA_SOLICITUD!$J$1,IF(J238="NULL",J238,CONCATENATE("'",J238,"'"))),DATA_SOLICITUD!$K$1,IF(K238="NULL",K238,CONCATENATE("'",K238,"'"))),DATA_SOLICITUD!$L$1,IF(L238="NULL",L238,CONCATENATE("'",L238,"'"))) -> INSERT INTO `multitabla` (`id_multitabla`, `codigo_tabla`, `nombre_tabla`, `codigo`, `orden`, `valor`, `valor_aux`, `valor_crm`, `estado`, `estado_tabla`, `usuario_crea`, `fecha_crea`, `usuario_modif`, `fecha_modif`) VALUES (DEFAULT, '028', 'Provincias', '7', '7', 'ANDAHUAYLAS', '180200', '030200', '1', '1', 'admin', DEFAULT, NULL, NULL);
A239: DEFAULT | B239: 028 | C239: Provincias | D239: 8 | E239: 8 | F239: ANGARAES | G239: 160200 | H239: 090300 | I239: NULL | J239: 1 | K239: 1 | L239: admin | M239: DEFAULT | N239: NULL | O239: NULL | P239: =SUBSTITUTE(SUBSTITUTE(SUBSTITUTE(SUBSTITUTE(SUBSTITUTE(SUBSTITUTE(SUBSTITUTE(SUBSTITUTE(SUBSTITUTE(SUBSTITUTE(SUBSTITUTE(INSERT!$B$3,DATA_SOLICITUD!$B$1,IF(B239="NULL",B239,CONCATENATE("'",B239,"'"))),DATA_SOLICITUD!$C$1,IF(C239="NULL",C239,CONCATENATE("'",C239,"'"))),DATA_SOLICITUD!$D$1,IF(D239="NULL",D239,CONCATENATE("'",D239,"'"))),DATA_SOLICITUD!$E$1,IF(E239="NULL",E239,CONCATENATE("'",E239,"'"))),DATA_SOLICITUD!$F$1,IF(F239="NULL",F239,CONCATENATE("'",F239,"'"))),DATA_SOLICITUD!$G$1,IF(G239="NULL",G239,CONCATENATE("'",G239,"'"))),DATA_SOLICITUD!$H$1,IF(H239="NULL",H239,CONCATENATE("'",H239,"'"))),DATA_SOLICITUD!$I$1,IF(I239="NULL",I239,CONCATENATE("'",I239,"'"))),DATA_SOLICITUD!$J$1,IF(J239="NULL",J239,CONCATENATE("'",J239,"'"))),DATA_SOLICITUD!$K$1,IF(K239="NULL",K239,CONCATENATE("'",K239,"'"))),DATA_SOLICITUD!$L$1,IF(L239="NULL",L239,CONCATENATE("'",L239,"'"))) -> INSERT INTO `multitabla` (`id_multitabla`, `codigo_tabla`, `nombre_tabla`, `codigo`, `orden`, `valor`, `valor_aux`, `valor_crm`, `estado`, `estado_tabla`, `usuario_crea`, `fecha_crea`, `usuario_modif`, `fecha_modif`) VALUES (DEFAULT, '028', 'Provincias', '8', '8', 'ANGARAES', '160200', '090300', '1', '1', 'admin', DEFAULT, NULL, NULL);
A240: DEFAULT | B240: 028 | C240: Provincias | D240: 9 | E240: 9 | F240: ANTA | G240: 190200 | H240: 080300 | I240: NULL | J240: 1 | K240: 1 | L240: admin | M240: DEFAULT | N240: NULL | O240: NULL | P240: =SUBSTITUTE(SUBSTITUTE(SUBSTITUTE(SUBSTITUTE(SUBSTITUTE(SUBSTITUTE(SUBSTITUTE(SUBSTITUTE(SUBSTITUTE(SUBSTITUTE(SUBSTITUTE(INSERT!$B$3,DATA_SOLICITUD!$B$1,IF(B240="NULL",B240,CONCATENATE("'",B240,"'"))),DATA_SOLICITUD!$C$1,IF(C240="NULL",C240,CONCATENATE("'",C240,"'"))),DATA_SOLICITUD!$D$1,IF(D240="NULL",D240,CONCATENATE("'",D240,"'"))),DATA_SOLICITUD!$E$1,IF(E240="NULL",E240,CONCATENATE("'",E240,"'"))),DATA_SOLICITUD!$F$1,IF(F240="NULL",F240,CONCATENATE("'",F240,"'"))),DATA_SOLICITUD!$G$1,IF(G240="NULL",G240,CONCATENATE("'",G240,"'"))),DATA_SOLICITUD!$H$1,IF(H240="NULL",H240,CONCATENATE("'",H240,"'"))),DATA_SOLICITUD!$I$1,IF(I240="NULL",I240,CONCATENATE("'",I240,"'"))),DATA_SOLICITUD!$J$1,IF(J240="NULL",J240,CONCATENATE("'",J240,"'"))),DATA_SOLICITUD!$K$1,IF(K240="NULL",K240,CONCATENATE("'",K240,"'"))),DATA_SOLICITUD!$L$1,IF(L240="NULL",L240,CONCATENATE("'",L240,"'"))) -> INSERT INTO `multitabla` (`id_multitabla`, `codigo_tabla`, `nombre_tabla`, `codigo`, `orden`, `valor`, `valor_aux`, `valor_crm`, `estado`, `estado_tabla`, `usuario_crea`, `fecha_crea`, `usuario_modif`, `fecha_modif`) VALUES (DEFAULT, '028', 'Provincias', '9', '9', 'ANTA', '190200', '080300', '1', '1', 'admin', DEFAULT, NULL, NULL);
A241: DEFAULT | B241: 028 | C241: Provincias | D241: 10 | E241: 10 | F241: ANTABAMBA | G241: 180300 | H241: 030300 | I241: NULL | J241: 1 | K241: 1 | L241: admin | M241: DEFAULT | N241: NULL | O241: NULL | P241: =SUBSTITUTE(SUBSTITUTE(SUBSTITUTE(SUBSTITUTE(SUBSTITUTE(SUBSTITUTE(SUBSTITUTE(SUBSTITUTE(SUBSTITUTE(SUBSTITUTE(SUBSTITUTE(INSERT!$B$3,DATA_SOLICITUD!$B$1,IF(B241="NULL",B241,CONCATENATE("'",B241,"'"))),DATA_SOLICITUD!$C$1,IF(C241="NULL",C241,CONCATENATE("'",C241,"'"))),DATA_SOLICITUD!$D$1,IF(D241="NULL",D241,CONCATENATE("'",D241,"'"))),DATA_SOLICITUD!$E$1,IF(E241="NULL",E241,CONCATENATE("'",E241,"'"))),DATA_SOLICITUD!$F$1,IF(F241="NULL",F241,CONCATENATE("'",F241,"'"))),DATA_SOLICITUD!$G$1,IF(G241="NULL",G241,CONCATENATE("'",G241,"'"))),DATA_SOLICITUD!$H$1,IF(H241="NULL",H241,CONCATENATE("'",H241,"'"))),DATA_SOLICITUD!$I$1,IF(I241="NULL",I241,CONCATENATE("'",I241,"'"))),DATA_SOLICITUD!$J$1,IF(J241="NULL",J241,CONCATENATE("'",J241,"'"))),DATA_SOLICITUD!$K$1,IF(K241="NULL",K241,CONCATENATE("'",K241,"'"))),DATA_SOLICITUD!$L$1,IF(L241="NULL",L241,CONCATENATE("'",L241,"'"))) -> INSERT INTO `multitabla` (`id_multitabla`, `codigo_tabla`, `nombre_tabla`, `codigo`, `orden`, `valor`, `valor_aux`, `valor_crm`, `estado`, `estado_tabla`, `usuario_crea`, `fecha_crea`, `usuario_modif`, `fecha_modif`) VALUES (DEFAULT, '028', 'Provincias', '10', '10', 'ANTABAMBA', '180300', '030300', '1', '1', 'admin', DEFAULT, NULL, NULL);
A242: DEFAULT | B242: 028 | C242: Provincias | D242: 11 | E242: 11 | F242: ANTONIO RAYMONDI | G242: 90200 | H242: 020300 | I242: NULL | J242: 1 | K242: 1 | L242: admin | M242: DEFAULT | N242: NULL | O242: NULL | P242: =SUBSTITUTE(SUBSTITUTE(SUBSTITUTE(SUBSTITUTE(SUBSTITUTE(SUBSTITUTE(SUBSTITUTE(SUBSTITUTE(SUBSTITUTE(SUBSTITUTE(SUBSTITUTE(INSERT!$B$3,DATA_SOLICITUD!$B$1,IF(B242="NULL",B242,CONCATENATE("'",B242,"'"))),DATA_SOLICITUD!$C$1,IF(C242="NULL",C242,CONCATENATE("'",C242,"'"))),DATA_SOLICITUD!$D$1,IF(D242="NULL",D242,CONCATENATE("'",D242,"'"))),DATA_SOLICITUD!$E$1,IF(E242="NULL",E242,CONCATENATE("'",E242,"'"))),DATA_SOLICITUD!$F$1,IF(F242="NULL",F242,CONCATENATE("'",F242,"'"))),DATA_SOLICITUD!$G$1,IF(G242="NULL",G242,CONCATENATE("'",G242,"'"))),DATA_SOLICITUD!$H$1,IF(H242="NULL",H242,CONCATENATE("'",H242,"'"))),DATA_SOLICITUD!$I$1,IF(I242="NULL",I242,CONCATENATE("'",I242,"'"))),DATA_SOLICITUD!$J$1,IF(J242="NULL",J242,CONCATENATE("'",J242,"'"))),DATA_SOLICITUD!$K$1,IF(K242="NULL",K242,CONCATENATE("'",K242,"'"))),DATA_SOLICITUD!$L$1,IF(L242="NULL",L242,CONCATENATE("'",L242,"'"))) -> INSERT INTO `multitabla` (`id_multitabla`, `codigo_tabla`, `nombre_tabla`, `codigo`, `orden`, `valor`, `valor_aux`, `valor_crm`, `estado`, `estado_tabla`, `usuario_crea`, `fecha_crea`, `usuario_modif`, `fecha_modif`) VALUES (DEFAULT, '028', 'Provincias', '11', '11', 'ANTONIO RAYMONDI', '90200', '020300', '1', '1', 'admin', DEFAULT, NULL, NULL);
A243: DEFAULT | B243: 028 | C243: Provincias | D243: 12 | E243: 12 | F243: AREQUIPA | G243: 210100 | H243: 040100 | I243: NULL | J243: 1 | K243: 1 | L243: admin | M243: DEFAULT | N243: NULL | O243: NULL | P243: =SUBSTITUTE(SUBSTITUTE(SUBSTITUTE(SUBSTITUTE(SUBSTITUTE(SUBSTITUTE(SUBSTITUTE(SUBSTITUTE(SUBSTITUTE(SUBSTITUTE(SUBSTITUTE(INSERT!$B$3,DATA_SOLICITUD!$B$1,IF(B243="NULL",B243,CONCATENATE("'",B243,"'"))),DATA_SOLICITUD!$C$1,IF(C243="NULL",C243,CONCATENATE("'",C243,"'"))),DATA_SOLICITUD!$D$1,IF(D243="NULL",D243,CONCATENATE("'",D243,"'"))),DATA_SOLICITUD!$E$1,IF(E243="NULL",E243,CONCATENATE("'",E243,"'"))),DATA_SOLICITUD!$F$1,IF(F243="NULL",F243,CONCATENATE("'",F243,"'"))),DATA_SOLICITUD!$G$1,IF(G243="NULL",G243,CONCATENATE("'",G243,"'"))),DATA_SOLICITUD!$H$1,IF(H243="NULL",H243,CONCATENATE("'",H243,"'"))),DATA_SOLICITUD!$I$1,IF(I243="NULL",I243,CONCATENATE("'",I243,"'"))),DATA_SOLICITUD!$J$1,IF(J243="NULL",J243,CONCATENATE("'",J243,"'"))),DATA_SOLICITUD!$K$1,IF(K243="NULL",K243,CONCATENATE("'",K243,"'"))),DATA_SOLICITUD!$L$1,IF(L243="NULL",L243,CONCATENATE("'",L243,"'"))) -> INSERT INTO `multitabla` (`id_multitabla`, `codigo_tabla`, `nombre_tabla`, `codigo`, `orden`, `valor`, `valor_aux`, `valor_crm`, `estado`, `estado_tabla`, `usuario_crea`, `fecha_crea`, `usuario_modif`, `fecha_modif`) VALUES (DEFAULT, '028', 'Provincias', '12', '12', 'AREQUIPA', '210100', '040100', '1', '1', 'admin', DEFAULT, NULL, NULL);
... A426: DEFAULT | B426: 028 | C426: Provincias | D426: 195 | E426: 195 | F426: ZARUMILLA | G426: 10300 | H426: 240300 | I426: NULL | J426: 1 | K426: 1 | L426: admin | M426: DEFAULT | N426: NULL | O426: NULL | P426: =SUBSTITUTE(SUBSTITUTE(SUBSTITUTE(SUBSTITUTE(SUBSTITUTE(SUBSTITUTE(SUBSTITUTE(SUBSTITUTE(SUBSTITUTE(SUBSTITUTE(SUBSTITUTE(INSERT!$B$3,DATA_SOLICITUD!$B$1,IF(B426="NULL",B426,CONCATENATE("'",B426,"'"))),DATA_SOLICITUD!$C$1,IF(C426="NULL",C426,CONCATENATE("'",C426,"'"))),DATA_SOLICITUD!$D$1,IF(D426="NULL",D426,CONCATENATE("'",D426,"'"))),DATA_SOLICITUD!$E$1,IF(E426="NULL",E426,CONCATENATE("'",E426,"'"))),DATA_SOLICITUD!$F$1,IF(F426="NULL",F426,CONCATENATE("'",F426,"'"))),DATA_SOLICITUD!$G$1,IF(G426="NULL",G426,CONCATENATE("'",G426,"'"))),DATA_SOLICITUD!$H$1,IF(H426="NULL",H426,CONCATENATE("'",H426,"'"))),DATA_SOLICITUD!$I$1,IF(I426="NULL",I426,CONCATENATE("'",I426,"'"))),DATA_SOLICITUD!$J$1,IF(J426="NULL",J426,CONCATENATE("'",J426,"'"))),DATA_SOLICITUD!$K$1,IF(K426="NULL",K426,CONCATENATE("'",K426,"'"))),DATA_SOLICITUD!$L$1,IF(L426="NULL",L426,CONCATENATE("'",L426,"'"))) -> INSERT INTO `multitabla` (`id_multitabla`, `codigo_tabla`, `nombre_tabla`, `codigo`, `orden`, `valor`, `valor_aux`, `valor_crm`, `estado`, `estado_tabla`, `usuario_crea`, `fecha_crea`, `usuario_modif`, `fecha_modif`) VALUES (DEFAULT, '028', 'Provincias', '195', '195', 'ZARUMILLA', '10300', '240300', '1', '1', 'admin', DEFAULT, NULL, NULL);
A427: DEFAULT | B427: 029 | C427: Distritos | D427: NULL | E427: NULL | F427: NULL | G427: NULL | H427: NULL | I427: NULL | J427: NULL | K427: 1 | L427: admin | M427: DEFAULT | N427: NULL | O427: NULL | P427: =SUBSTITUTE(SUBSTITUTE(SUBSTITUTE(SUBSTITUTE(SUBSTITUTE(SUBSTITUTE(SUBSTITUTE(SUBSTITUTE(SUBSTITUTE(SUBSTITUTE(SUBSTITUTE(INSERT!$B$3,DATA_SOLICITUD!$B$1,IF(B427="NULL",B427,CONCATENATE("'",B427,"'"))),DATA_SOLICITUD!$C$1,IF(C427="NULL",C427,CONCATENATE("'",C427,"'"))),DATA_SOLICITUD!$D$1,IF(D427="NULL",D427,CONCATENATE("'",D427,"'"))),DATA_SOLICITUD!$E$1,IF(E427="NULL",E427,CONCATENATE("'",E427,"'"))),DATA_SOLICITUD!$F$1,IF(F427="NULL",F427,CONCATENATE("'",F427,"'"))),DATA_SOLICITUD!$G$1,IF(G427="NULL",G427,CONCATENATE("'",G427,"'"))),DATA_SOLICITUD!$H$1,IF(H427="NULL",H427,CONCATENATE("'",H427,"'"))),DATA_SOLICITUD!$I$1,IF(I427="NULL",I427,CONCATENATE("'",I427,"'"))),DATA_SOLICITUD!$J$1,IF(J427="NULL",J427,CONCATENATE("'",J427,"'"))),DATA_SOLICITUD!$K$1,IF(K427="NULL",K427,CONCATENATE("'",K427,"'"))),DATA_SOLICITUD!$L$1,IF(L427="NULL",L427,CONCATENATE("'",L427,"'"))) -> INSERT INTO `multitabla` (`id_multitabla`, `codigo_tabla`, `nombre_tabla`, `codigo`, `orden`, `valor`, `valor_aux`, `valor_crm`, `estado`, `estado_tabla`, `usuario_crea`, `fecha_crea`, `usuario_modif`, `fecha_modif`) VALUES (DEFAULT, '029', 'Distritos', NULL, NULL, NULL, NULL, NULL, NULL, '1', 'admin', DEFAULT, NULL, NULL);
A428: DEFAULT | B428: 029 | C428: Distritos | D428: 1 | E428: 1 | F428: 26 DE OCTUBRE | G428: 29991 | H428: 200115 | I428: NULL | J428: 1 | K428: 1 | L428: admin | M428: DEFAULT | N428: NULL | O428: NULL | P428: =SUBSTITUTE(SUBSTITUTE(SUBSTITUTE(SUBSTITUTE(SUBSTITUTE(SUBSTITUTE(SUBSTITUTE(SUBSTITUTE(SUBSTITUTE(SUBSTITUTE(SUBSTITUTE(INSERT!$B$3,DATA_SOLICITUD!$B$1,IF(B428="NULL",B428,CONCATENATE("'",B428,"'"))),DATA_SOLICITUD!$C$1,IF(C428="NULL",C428,CONCATENATE("'",C428,"'"))),DATA_SOLICITUD!$D$1,IF(D428="NULL",D428,CONCATENATE("'",D428,"'"))),DATA_SOLICITUD!$E$1,IF(E428="NULL",E428,CONCATENATE("'",E428,"'"))),DATA_SOLICITUD!$F$1,IF(F428="NULL",F428,CONCATENATE("'",F428,"'"))),DATA_SOLICITUD!$G$1,IF(G428="NULL",G428,CONCATENATE("'",G428,"'"))),DATA_SOLICITUD!$H$1,IF(H428="NULL",H428,CONCATENATE("'",H428,"'"))),DATA_SOLICITUD!$I$1,IF(I428="NULL",I428,CONCATENATE("'",I428,"'"))),DATA_SOLICITUD!$J$1,IF(J428="NULL",J428,CONCATENATE("'",J428,"'"))),DATA_SOLICITUD!$K$1,IF(K428="NULL",K428,CONCATENATE("'",K428,"'"))),DATA_SOLICITUD!$L$1,IF(L428="NULL",L428,CONCATENATE("'",L428,"'"))) -> INSERT INTO `multitabla` (`id_multitabla`, `codigo_tabla`, `nombre_tabla`, `codigo`, `orden`, `valor`, `valor_aux`, `valor_crm`, `estado`, `estado_tabla`, `usuario_crea`, `fecha_crea`, `usuario_modif`, `fecha_modif`) VALUES (DEFAULT, '029', 'Distritos', '1', '1', '26 DE OCTUBRE', '29991', '200115', '1', '1', 'admin', DEFAULT, NULL, NULL);
A429: DEFAULT | B429: 029 | C429: Distritos | D429: 2 | E429: 2 | F429: A | G429: 240300 | I429: NULL | J429: 1 | K429: 1 | L429: admin | M429: DEFAULT | N429: NULL | O429: NULL | P429: =SUBSTITUTE(SUBSTITUTE(SUBSTITUTE(SUBSTITUTE(SUBSTITUTE(SUBSTITUTE(SUBSTITUTE(SUBSTITUTE(SUBSTITUTE(SUBSTITUTE(SUBSTITUTE(INSERT!$B$3,DATA_SOLICITUD!$B$1,IF(B429="NULL",B429,CONCATENATE("'",B429,"'"))),DATA_SOLICITUD!$C$1,IF(C429="NULL",C429,CONCATENATE("'",C429,"'"))),DATA_SOLICITUD!$D$1,IF(D429="NULL",D429,CONCATENATE("'",D429,"'"))),DATA_SOLICITUD!$E$1,IF(E429="NULL",E429,CONCATENATE("'",E429,"'"))),DATA_SOLICITUD!$F$1,IF(F429="NULL",F429,CONCATENATE("'",F429,"'"))),DATA_SOLICITUD!$G$1,IF(G429="NULL",G429,CONCATENATE("'",G429,"'"))),DATA_SOLICITUD!$H$1,IF(H429="NULL",H429,CONCATENATE("'",H429,"'"))),DATA_SOLICITUD!$I$1,IF(I429="NULL",I429,CONCATENATE("'",I429,"'"))),DATA_SOLICITUD!$J$1,IF(J429="NULL",J429,CONCATENATE("'",J429,"'"))),DATA_SOLICITUD!$K$1,IF(K429="NULL",K429,CONCATENATE("'",K429,"'"))),DATA_SOLICITUD!$L$1,IF(L429="NULL",L429,CONCATENATE("'",L429,"'"))) -> INSERT INTO `multitabla` (`id_multitabla`, `codigo_tabla`, `nombre_tabla`, `codigo`, `orden`, `valor`, `valor_aux`, `valor_crm`, `estado`, `estado_tabla`, `usuario_crea`, `fecha_crea`, `usuario_modif`, `fecha_modif`) VALUES (DEFAULT, '029', 'Distritos', '2', '2', 'A', '240300', ' ', '1', '1', 'admin', DEFAULT, NULL, NULL);
A430: DEFAULT | B430: 029 | C430: Distritos | D430: 3 | E430: 3 | F430: ABANCAY | G430: 180102 | H430: 030101 | I430: NULL | J430: 1 | K430: 1 | L430: admin | M430: DEFAULT | N430: NULL | O430: NULL | P430: =SUBSTITUTE(SUBSTITUTE(SUBSTITUTE(SUBSTITUTE(SUBSTITUTE(SUBSTITUTE(SUBSTITUTE(SUBSTITUTE(SUBSTITUTE(SUBSTITUTE(SUBSTITUTE(INSERT!$B$3,DATA_SOLICITUD!$B$1,IF(B430="NULL",B430,CONCATENATE("'",B430,"'"))),DATA_SOLICITUD!$C$1,IF(C430="NULL",C430,CONCATENATE("'",C430,"'"))),DATA_SOLICITUD!$D$1,IF(D430="NULL",D430,CONCATENATE("'",D430,"'"))),DATA_SOLICITUD!$E$1,IF(E430="NULL",E430,CONCATENATE("'",E430,"'"))),DATA_SOLICITUD!$F$1,IF(F430="NULL",F430,CONCATENATE("'",F430,"'"))),DATA_SOLICITUD!$G$1,IF(G430="NULL",G430,CONCATENATE("'",G430,"'"))),DATA_SOLICITUD!$H$1,IF(H430="NULL",H430,CONCATENATE("'",H430,"'"))),DATA_SOLICITUD!$I$1,IF(I430="NULL",I430,CONCATENATE("'",I430,"'"))),DATA_SOLICITUD!$J$1,IF(J430="NULL",J430,CONCATENATE("'",J430,"'"))),DATA_SOLICITUD!$K$1,IF(K430="NULL",K430,CONCATENATE("'",K430,"'"))),DATA_SOLICITUD!$L$1,IF(L430="NULL",L430,CONCATENATE("'",L430,"'"))) -> INSERT INTO `multitabla` (`id_multitabla`, `codigo_tabla`, `nombre_tabla`, `codigo`, `orden`, `valor`, `valor_aux`, `valor_crm`, `estado`, `estado_tabla`, `usuario_crea`, `fecha_crea`, `usuario_modif`, `fecha_modif`) VALUES (DEFAULT, '029', 'Distritos', '3', '3', 'ABANCAY', '180102', '030101', '1', '1', 'admin', DEFAULT, NULL, NULL);
...

Sheet INSERT
B2: QUERY_INSERT
B3: INSERT INTO `multitabla` (`id_multitabla`, `codigo_tabla`, `nombre_tabla`, `codigo`, `orden`, `valor`, `valor_aux`, `valor_crm`, `estado`, `estado_tabla`, `usuario_crea`, `fecha_crea`, `usuario_modif`, `fecha_modif`) VALUES (DEFAULT, @codigo_tabla, @nombre_tabla, @codigo, @orden, @valor@, @valor_aux, @valor_crm, @estado@, @estado_tabla, @usuario_crea, DEFAULT, NULL, NULL);
